Workbook

Sheet About
A1: Web App Data | B1: Rhode Island | C1: 46294 | G1: abrv | H1: state
B2: =_xlfn.XLOOKUP(B1,H:H,G:G,0,0,1) -> RI | C2: =_xlfn.XLOOKUP(B2,G:G, H:H, 0,0,1) -> Rhode Island | G2: AK | H2: Alaska
A3: This spreadsheet contains data that is used to populate the web application interface | G3: AL | H3: Alabama
A4: for the Energy Policy Simulator. The data in other tabs in this spreadsheet are used | G4: AR | H4: Arkansas
A5: to establish the policy levers, lever bounds, descriptive text for pop-over | G5: AZ | H5: Arizona
A6: panels, output graphs, and reference scenarios available in the web app. | G6: CA | H6: California
G7: CO | H7: Colorado
A8: A live version of the web application interface powered by a copy of this model | G8: CT | H8: Connecticut
A9: can be found at: | G9: DC | H9: DC
A10: https://www.energypolicy.solutions | G10: DE | H10: Delaware
G11: FL | H11: Florida
A12: You are unlikely to need to use or change the contents of this spreadsheet, unless | G12: GA | H12: Georgia
A13: you are adapting the Energy Policy Simulator to a new country and desire | G13: HI | H13: Hawaii
A14: a web application interface customized for your country-specific model version. | G14: IA | H14: Iowa
G15: ID | H15: Idaho
A16: Checks for Policy ID Number Validity | G16: IL | H16: Illinois
A17: Max policy ID number in use | B17: =MAX(PolicyLevers!H:H) -> 2799 | G17: IN | H17: Indiana
A18: Lowest duplicate ID number | B18: {=IF(MIN(IF(COUNTIF(PolicyLevers!$H$2:$H$2053,PolicyLevers!$H$2:$H$2053)>1,PolicyLevers!$H$2:$H$2053, ""))=0,"No duplicate ID numbers",MIN(IF(COUNTIF(PolicyLevers!$H$2:$H$2053,PolicyLevers!$H$2:$H$2053)>1,PolicyLevers!$H$2:$H$2053, "")))} -> No duplicate ID numbers | G18: KS | H18: Kansas
A19: Row of first policy missing a valid ID number | B19: {=IF(MIN(IF((NOT(ISNUMBER(PolicyLevers!$H$2:$H$2053)))*(ISTEXT(PolicyLevers!$I$2:$I$2053)),ROW(PolicyLevers!$H$2:$H$2053)))=0,"No missing ID numbers",MIN(IF((NOT(ISNUMBER(PolicyLevers!$H$2:$H$2053)))*(ISTEXT(PolicyLevers!$I$2:$I$2053)),ROW(PolicyLevers!$H$2:$H$2053))))} -> No missing ID numbers | G19: KY | H19: Kentucky
G20: LA | H20: Louisiana
A21: Customizing Policy Levers | G21: MA | H21: Massachusetts
A22: Define most policy properties on the "Policy Characteristics" tab. | G22: MD | H22: Maryland
A23: Specify the subscripted elements of each policy and which are enabled/disabled on the "PolicyLevers" tab. | G23: ME | H23: Maine
A24: On the PolicyLevers tab, only manually edit the cells under the green column headers. Simply extend the | G24: MI | H24: Michigan
A25: existing formulas up or down to fill cells under the red headers on that tab. | G25: MN | H25: Minnesota
G26: MO | H26: Missouri
A27: Notes on Meaning of Blank Cells on the Policy Characteristics Tab | G27: MS | H27: Mississippi
A28: Leave the "Policy Schedule Subscript" cell blank to deny the ability to edit the implementation | G28: MT | H28: Montana
A29: schedule for a lever. This should generally only be done for levers that do not use an | G29: NC | H29: North Carolina
A30: implementation schedule: the toggle to Non-BAU Mandated Capacity Construction | G30: ND | H30: North Dakota
A31: (which has its own schedule built into its input data) and the Nuclear Lifetime Extension | G31: NE | H31: Nebraska
A32: (which simply delays retirements that would occur in the BAU Retirements input data). | G32: NH | H32: New Hampshire
G33: NJ | H33: New Jersey
A34: Leave the "Policy Group" cell blank to exclude a lever from wedge diagrams and abatement cost curves. | G34: NM | H34: New Mexico
A35: This should always be done for "Control Settings" (which affect both the BAU and policy cases), | G35: NV | H35: Nevada
A36: and should generally never be done for actual policy levers. | G36: NY | H36: New York
G37: OH | H37: Ohio
A38: Leave the "URL for "How the model handles this policy" links" cell blank to exclude this link from | G38: OK | H38: Oklahoma
A39: the policy's pop-over pane. You should generally do this whenever there is no on-topic place | G39: OR | H39: Oregon
A40: in the documentation to which to send a user. | G40: PA | H40: Pennsylvania
G41: RI | H41: Rhode Island
A42: Leave the "URL for "How to design this policy well" links" cell blank to exclude this link from | G42: SC | H42: South Carolina
A43: the policy's pop-over pane. You should generally do this whenever no documentation page | G43: SD | H43: South Dakota
A44: for that policy exists. | G44: TN | H44: Tennessee
G45: TX | H45: Texas
A46: Notes on Unit Formatting on Policy Characteristics Tab | G46: UT | H46: Utah
A47: If you want a policy lever to be formatted as a percentage in the web interface, the percent | G47: VA | H47: Virginia
A48: symbol (%) must appear somewhere in the "Units" field for that policy. | G48: VT | H48: Vermont
G49: WA | H49: Washington
A50: For percentages, the web interface will choose the number of decimal places to show for | G50: WI | H50: Wisconsin
A51: policy settings based on the "Slider Step Size." Up to 2 decimal places (e.g. showing values as | G51: WV | H51: West Virginia
A52: small as 0.01%) are supported. If the slider step size is 1% or larger, you must use an integer | G52: WY | H52: Wyoming
A53: step size (e.g. 1.5% is not a valid step size, but 1%, 2%, 0.5% and 0.05% are all valid).

Sheet Policy Characteristics
A1: This tab contains information about each policy that does not vary by subscripted element of that policy.
A2: It matches policies to the listing in the "PolicyLevers" tab using the "Vensim Variable Name" column.
A3: Sector | B3: Short Name | C3: Vensim Variable Name | D3: Policy Group | E3: Policy Schedule Subscript | F3: Min Slider Value | G3: Max Slider Value | H3: Slider Step Size | I3: Units | J3: Text for Pop-Over Panel Description | K3: URL for "How the model handles this policy" links | L3: URL for "How to design this policy well" links | M3: Source for Guidance Text (if any) | N3: Source for Max Slider Value (if any)
A4: Agriculture, Land Use, and Forestry | B4: Afforestation and Reforestation | C4: Fraction of Afforestation and Reforestation Achieved | D4: Afforestation and Reforestation | E4: land afforestation and reforestation | F4: -3 | G4: 1 | H4: 0.01 | I4: % of potential achieved | J4: **Description:** This policy increases the sequestration of CO2 by planting forests. Planted forests are assumed to be managed with best practices and are not used for timber harvesting. A negative values implies less sequestration compared to the Current Policies scenario. | K4: lulucf.html#aff-ref | L4: afforestation-and-reforestation.html | M4: Calculated from model data; see the relevant variable(s) in the InputData folder for source information. | N4: Ross W. Gorte, 2009, "U.S. Tree Planting for Carbon Sequestration," Congressional Research Service, https://www.fas.org/sgp/crs/misc/R40562.pdf, p.3, paragraph 1
A5: Agriculture, Land Use, and Forestry | B5: Avoid Deforestation | C5: Fraction of Avoided Deforestation Achieved | D5: Avoid Deforestation | E5: land avoid deforestation | F5: 0 | G5: 1 | H5: 0.01 | I5: % of potential achieved | J5: **Description:** This policy prevents clear cutting of forests that would otherwise be cleared. Preserved forests are assumed to be managed with best practices. | K5: lulucf.html#avoid-def | L5: avoid-deforestation.html
A6: Agriculture, Land Use, and Forestry | B6: Cropland and Rice Measures | C6: Fraction of Cropland and Rice Measures Achieved | D6: Cropland and Rice Measures | E6: indst cropland and rice measures | F6: 0 | G6: 1 | H6: 0.01 | I6: % of potential achieved | J6: **Description:** This policy reduces CH4 and N2O emissions from agriculture through cropland management practices, such as improved crop rotations, reduced soil tillage, and improvements in fertilizer composition and application. Measures particular to rice cultivation include improved flooding practices that avoid anaerobic, methane-forming conditions. | K6: industry-ag-main.html#cropland | L6: cropland-management.html | M6: Calculated from model data; see the relevant variable(s) in the InputData folder for source information.
A7: Agriculture, Land Use, and Forestry | B7: Forest Set-Asides | C7: Fraction of Forest Set Asides Achieved | D7: Forest Set-Asides | E7: land forest set asides | F7: 0 | G7: 1 | H7: 0.01 | I7: % of potential achieved | J7: **Description:** This policy avoids the release of CO2 from forests by reducing timber harvesting. // **Guidance for setting values:** A 100% setting of this lever reduces timber harvesting by 2% of the BAU amount per year, reaching a roughly 70% reduction in timber harvesting by 2050. | K7: lulucf.html#set-asides | L7: forest-set-asides.html | M7: Calculated from model data; see the relevant variable(s) in the InputData folder for source information.
A8: Agriculture, Land Use, and Forestry | B8: Grassland Restoration and Avoided Conversion | C8: Fraction of Forest Restoration Achieved | D8: Grassland Restoration and Avoided Conversion | E8: land forest restoration | F8: 0 | G8: 1 | H8: 0.01 | I8: % of potential achieved | J8: **Description:** This policy increases CO2 sequestration by avoiding the conversion of grasslands and restoring grassland areas. | L8: forest-restoration.html | M8: See file PLANAbPiaSY
A9: Agriculture, Land Use, and Forestry | B9: Improved Forest Management | C9: Fraction of Improved Forest Management Achieved | D9: Improved Forest Management | E9: land forest management | F9: -1.5 | G9: 1 | H9: 0.01 | I9: % of potential achieved | J9: **Description:** This policy increases CO2 sequestration by forests through improved forest management practices. A negative values implies less sequestration compared to the Current Policies scenario. | K9: lulucf.html#forest-mgmt | L9: improved-forest-management.html | M9: Calculated from model data; see the relevant variable(s) in the InputData folder for source information.
A10: Agriculture, Land Use, and Forestry | B10: Improved Soil Measures | C10: Fraction of CO2 Storage Through Tillage Practices | D10: Improved Soil Measures | E10: indst tillage | F10: 0 | G10: 1 | H10: 0.01 | I10: % of potential achieved | J10: **Description:** This policy stores CO2 in agricultural soils through improved tillage practices, retiring organic and marginal soils, and establishing windbreaks/shelterbelts.
A11: Agriculture, Land Use, and Forestry | B11: Livestock Measures | C11: Fraction of Livestock Measures Achieved | D11: Livestock Measures | E11: indst livestock measures | F11: 0 | G11: 1 | H11: 0.01 | I11: % of potential achieved | J11: **Description:** This policy reduces greenhouse gas emissions from agriculture through livestock-related measures, such as feed supplements or drugs to prevent enteric methane formation. | K11: industry-ag-main.html#livestock | L11: livestock-measures.html | M11: Calculated from model data; see the relevant variable(s) in the InputData folder for source information.
A12: Agriculture, Land Use, and Forestry | B12: Shift to Non-Animal Products | C12: Percent Animal Products Shifted to Nonanimal Products | D12: Shift to Non-Animal Products | E12: indst shift to nonanimal products | F12: 0 | G12: 1 | H12: 0.01 | I12: % reduction in animal products | J12: **Description:** This policy causes animal products to be substituted for non-animal products, which might be achieved by changes in consumer preferences or by changes in costs of agricultural products (such as by redirecting subsidies currently paid to farmers who raise animals or feed crops to farmers growing fruits, vegetables, and other plant-based foods for human consumption). Moderate settings of this policy lever do not imply a vegan diet: for instance, a 50% setting could represent each individual consuming half as many animal products, rather than half of the population consuming no animal products. // **Guidance for setting values:** According to OECD statistics, the U.S. has the highest per-capita meat consumption in the world, at 99 kg/person/year. If the U.S. were to achieve a rate similar to that in Europe (70 kg/person/yr), Japan (36 kg/person/yr), or India (3 kg/person/yr), this would be a reduction of 29% (Europe), 64% (Japan), or 97% (India) respectively. | L12: shift-to-non-animal-products.html | M12: https://en.wikipedia.org/wiki/List_of_countries_by_meat_consumption_per_capita (article revision 00:12, 22 Feb 2019)
A13: Agriculture, Land Use, and Forestry | B13: Wetland Restoration | C13: Fraction of Peatland Restoration Achieved | D13: Wetland Restoration | E13: land peatland restoration | F13: 0 | G13: 1 | H13: 0.01 | I13: % of potential achieved | J13: **Description:** This policy increases CO2 sequestration by restoring wetlands and riparian forest buffers. | L13: peatland-restoration.html | M13: https://www.usda.gov/sites/default/files/documents/White_Paper_WEB71816.pdf
A14: Buildings and Appliances | B14: Building Component Electrification | C14: Fraction of New Bldg Components Shifted to Other Fuels | D14: Building Component Electrification | E14: bldgs new component fuel shifting | F14: 0 | G14: 1 | H14: 0.01 | I14: % of newly sold non-electric building components | J14: **Description:** This policy replaces the specified fraction of newly sold non-electric building components of the selected type(s) in buildings of the selected type(s) with electricity-using components. | K14: buildings-sector-main.html#component-elec | L14: building-component-electrification.html | M14: EIA AEO
A15: Buildings and Appliances | B15: Building Energy Efficiency Standards | C15: Reduction in E Use Allowed by Component Eff Std | D15: Building Energy Efficiency Standards | E15: bldgs efficiency standards | F15: 0 | G15: 0.75 | H15: 0.01 | I15: % reduction in energy use | J15: **Description:** This policy tightens energy efficiency standards for the selected component(s) in the selected building type(s). The policy only applies to newly sold components each year (whether for new buildings or replacement of old components of existing buildings). // **Guidance for setting values:** In "Assessment of Electricity Savings in the U.S. Achievable through New Appliance/Equipment Efficiency Standards and Building Efficiency Codes, 2010-2025" (2011), the Edison Foundation considered a 30% reduction in whole-building energy use (moderate case) and 40-45% (aggressive case) relative to BAU from 2010 to 2025. | K15: buildings-sector-main.html#eff-stds | L15: building-energy-efficiency-standards.html | M15: Edison Foundation, 2011, "Assessment of Electricity Savings in the U.S. Achievable through New Appliance/Equipment Efficiency Standards and Building Efficiency Codes (2010 - 2025)", http://www.edisonfoundation.net/iei/Documents/IEE_CodesandStandardsAssessment_2010-2025_UPDATE.pdf, Page B-2, Table B-1. | N15: Itron, 2007, "ASSESSMENT OF LONG-TERM ELECTRIC ENERGY EFFICIENCY POTENTIAL IN CALIFORNIA’S RESIDENTIAL SECTOR," http://www.energy.ca.gov/2007publications/CEC-500-2007-002/CEC-500-2007-002.PDF, p.33, Table 5-1
A16: Buildings and Appliances | B16: Contractor Training | C16: Boolean Improved Contractor Edu and Training | D16: Contractor Training | E16: bldgs contractor training | F16: 0 | G16: 1 | H16: 1 | I16: on/off | J16: **Description:** This policy represents a program to train contractors in energy-efficient products and installation practices. This covers activities such as air sealing, building framing, and choice and application of insulation. This policy affects newly sold building envelope components, which reduce the energy use of heating, cooling, and ventilation systems in buildings by 3.7% (based on a 2006 study from the Energy Center of Wisconsin). | K16: buildings-sector-main.html#contractor-ed | L16: contractor-training.html
A17: Buildings and Appliances | B17: Distributed Solar Capacity Requirement | C17: Min Required Rooftop Solar Capacity | D17: Distributed Solar Promotion | E17: bldgs min req rooftop solar | F17: 0 | G17: 600000 | H17: 5000 | I17: MW | J17: **Description:** This policy requires at least the specified capacity of distributed solar be built by the model.
A18: Buildings and Appliances | B18: Distributed Solar Carve-Out | C18: Min Fraction of Total Elec Demand to be Met by Distributed Solar PV | D18: Distributed Solar Promotion | E18: bldgs min fraction distributed solar | F18: 0 | G18: =ROUND(MaxBoundCalculations!B172,2) -> 0.24 | H18: 0.005 | I18: minimum % elec from solar | J18: **Description:** This policy requires at least the specified percentage of total retail electricity demand to be generated by residential and commercial buildings' distributed solar systems (typically rooftop PV). // **Guidance for setting values:** Colorado has established a 3% carve-out for 2020 (though it includes non-solar on-site sources). | K18: buildings-sector-main.html#solar-carve-out | L18: solar-carve-out.html | M18: MASSACHUSETTS: http://www.mass.gov/eea/energy-utilities-clean-tech/renewable-energy/solar/rps-solar-carve-out/current-status-of-the-rps-solar-carve-out-program.html COLORADO: http://www.seia.org/research-resources/rps-solar-carve-out-colorado | N18: RMI, 2011, "Reinventing Fire Electricity Sector Methodology," http://www.rmi.org/cms/Download.aspx?id=10765&file=Reinventing+Fire+Electricity+Sector+Methodology.pdf&title=Reinventing+Fire+Electricity+Sector+Methodology, Page 11, 2050 Generation by Case
A19: Buildings and Appliances | B19: Distributed Solar Subsidy | C19: Additional Perc Subsidy for Distributed Solar PV Capacity | D19: Distributed Solar Promotion | E19: bldgs distributed solar subsidy | F19: 0 | G19: 0.5 | H19: 0.01 | I19: % of PV system cost | J19: **Description:** This policy causes the government to reimburse building owners for an additional percentage of the cost of new distributed solar PV capacity that is installed on or around buildings. // **Guidance for setting values:** The Inflation Reduction Act included a 30% tax credit for residential solar, although it was cut short by the One Big Beautiful Bill Act. Commercial buildings also qualified for the utility-scale 30% investment tax credit. | K19: buildings-sector-main.html#distributed-solar-subsidy | L19: distributed-solar-subsidy.html | M19: Department of Energy. Business Energy Investment Tax Credit (ITC). http://energy.gov/savings/business-energy-investment-tax-credit-itc
A20: Buildings and Appliances | B20: Improved Labeling | C20: Boolean Improved Device Labeling | D20: Improved Labeling | E20: bldgs device labeling | F20: 0 | G20: 1 | H20: 1 | I20: on/off | J20: **Description:** This policy represents a program requiring newly sold heating systems, cooling and ventilation systems, and appliances to feature prominent, well-designed labels highlighting their energy efficiencies. The policy reduces energy consumption of newly sold building components of these types by 10%. | K20: buildings-sector-main.html#device-labeling | L20: improved-labeling.html | M20: none
A21: Buildings and Appliances | B21: Non BAU Distributed Solar Capacity | C21: Boolean Use Non BAU Distributed Solar Capacity | D21: Distributed Solar Promotion | E21: non BAU dist solar | F21: 0 | G21: 1 | H21: 1 | I21: on/off | J21: **Description:** This policy adds or subtracts an amount of distributed solar according to an alternate input data file. For the U.S., this file is configured to remove the amount of incremental distributed solar deployment expected from the Inflation Reduction Act. //
A22: Buildings and Appliances | B22: Rebate for Efficient Products | C22: Boolean Rebate Program for Efficient Components | D22: Rebate for Efficient Products | E22: bldgs rebate | F22: 0 | G22: 1 | H22: 1 | I22: on/off | J22: **Description:** This policy represents a modest rebate paid to customers who purchase energy-efficient building equipment of the selected type(s). Typical rebate amounts represented by this policy are $50-100 for a clothes washer and $25-50 for a dishwasher or refrigerator. | K22: buildings-sector-main.html#rebate | L22: rebate-for-efficient-products.html
A23: Buildings and Appliances | B23: Retrofit Existing Buildings | C23: Share of Preexisting Buildings Subject to Retrofitting | D23: Increased Retrofitting | E23: bldgs retrofitting | F23: 0 | G23: 0.5 | H23: 0.01 | I23: % of existing buildings | J23: **Description:** This policy retrofits the specified percentage of buildings to more efficient heating, cooling, and envelope components. // **Guidance for setting values:** Without additional policy, by 2050, roughly 90% of the preexisting residential buildings and 85% of commercial buildings will survive without major renovations. This policy renovates them more quickly than they would have otherwise, improving the efficiency of building stock. A policy value of 100% causes all preexisting buildings to be renovated along the schedule specified by the user. If required by 2050, for example, this policy would induce retrofits of the 90% of residential buildings and 85% of commercial buildings not overhauled in the model baseline. A value of 50% in 2050 would renovate 45% of preexisting residential and 42.5% of preexisting commercial buildings, and so forth. | K23: buildings-sector-main.html#retrofitting | L23: increased-retrofitting.html | M23: Calculated from model data; see the relevant variable(s) in the InputData folder for source information.
A24: Carbon Removal | B24: Direct Air Capture | C24: Fraction of Direct Air Capture Potential Achieved | D24: Carbon Dioxide Removal | E24: geoeng direct air capture | F24: 0 | G24: 1 | H24: 0.01 | I24: % of potential achieved | J24: **Description:** This policy causes direct air capture (DAC) technology to be used to remove carbon dioxide from the atmosphere. The modeled technology is based on hydroxide sorbents, as this is the most mature DAC technology. Alternatives (such as amine-based technologies) are unlikely to have a perceptible impact by 2050, the last year of the EPS model run. Note that all DAC technologies, even hydroxide sorbents, have their greatest potential effects after 2050, which cannot be seen in a model run that ends in 2050. (DAC refers only to mechanical methods of carbon dioxide removal, not afforestation and other land use measures. For those measures, see the policy levers in the "Agriculture, Land Use, and Forestry" category.) // **Guidance for setting values:** A 100% setting implies large DAC research and development investments starting today, and deployment in line with the published Long-Term Strategy of the United States: Pathways to Net-Zero Greenhouse Gas Emissions by 2050 (roughly 350 MMT in 2050). | K24: direct-air-capture.html#dac | L24: direct-air-capture.html | M24: Realmonte et al., 2019, An inter-model assessment of the role of direct air capture in deep mitigation pathways, https://www.nature.com/articles/s41467-019-10842-5, Table 2, https://static-content.springer.com/esm/art%3A10.1038%2Fs41467-019-10842-5/MediaObjects/41467_2019_10842_MOESM1_ESM.pdf, Supplementary materials, Fig 3
A25: Carbon Removal | B25: Enhanced Rock Weathering | C25: Fraction of Enhanced Rock Weathering Potential Achieved | D25: Carbon Dioxide Removal | E25: geoeng enhanced rock weathering | F25: 0 | G25: 1 | H25: 0.01 | I25: % of potential achieved | J25: **Description:** This policy causes deployment of enhanced rock weathering practices to absorb CO2 from the atmosphere. We use data from Fuhrman et al., which assumes application of crushed basalt to croplands. // **Guidance for setting values:** A 100% setting implies rock application to roughly 45 million acres. | M25: Strefler et al., 2018, (used as a source on total acrege for our Fuhrman et al. data, https://content.cld.iop.org/journals/1748-9326/13/3/034010/revision2/ERL_034010_SD.pdf?Expires=1720629928&Signature=jHMnzWhptSu-2LByE4KdFSDS-DnRp9gzhnqimxxA1RXqsDDTo015nrsWRJqNRyNqExM59e0IjQOWRK1k6zkpTdrMxwQTaE1yD5yczeGsUNqiCqXYn5Zfj08uJQ-HIiuHek1qKCp8Njc9HMrxocyo~nIcf7eRRWkaRfOclfayd-52YV1Dgwv9N~rc2fbap9xGqOB5p8gCkQDmkXX2z5QnMMIkGBr-tGCrxZUxe0CuCxiYpVtI3rRDXkIgQamshSf4yA1QfcIwukn3F564By~Ztx0vUTUvbT7CIcfvUNkYkQDSKpzzi50D2Nv7usXFRIyOckZu1AJWhhzHbzcwburKrQ__&Key-Pair-Id=KL1D8TIY3N7T8
A26: Control Settings | B26: COVID-19 Recession | C26: EGGRA Boolean Use Exogenous GDP Growth Rate Adjustment | E26: settings exogenous GDP adjustment | F26: 0 | G26: 1 | H26: 1 | I26: on/off | J26: **Description:** This control setting is not used in the U.S. EPS at present, but it could be used to enable or disable the impacts of a or disables the GDP impact of a recession or other GDP-impacting event not accounted for in the energy use input data files. It was previously used to model the recession caused by SARS-CoV-2 (COVID-19).
A27: Control Settings | B27: Exclude Elec Exports from Elec Portfolio Stds | C27: BEEEfEPS Boolean Exclude Elec Exports from Elec Portfolio Stds | D27: Clean Electricity Standard | F27: 0 | G27: 1 | H27: 1 | I27: on/off | J27: **Description:** This policy lever excludes exported electricity from the clean electricity standard requirements.
A28: Control Settings | B28: Non BAU First Year | C28: Boolean Use Non BAU First Year Impacting Future Policies | F28: 0 | G28: 1 | H28: 1 | I28: on/off | J28: **Description:** When a government designs a clean electricity standard or renewable portfolio standard, they typically offer utilities time to achieve compliance by scheduling increases in stringency far in advance. We assume no additional compliance with these policies in historical years, which are calibrated. But in a policy scenario, this lever can be used to switch out the first year behavior can reflect future policies to a different year, for example to examine "what if" scenarios around changes in political administrations.
A29: Control Settings | B29: Use 20-Year GWP Values | C29: BUTYGV Boolean Use Twenty Year GWP Values | F29: 0 | G29: 1 | H29: 1 | I29: on/off | J29: **Description:** Non-CO2 GHGs are converted to CO2 equivalent by comparing their warming power per unit mass to that of CO2. This ratio is called a gas' Global Warming Potential (GWP). Since different GHGs have different atmospheric lifetimes, the ratio is not static, so GWP values are defined as the cumulative warming effect over a particular timeframe. By default, the EPS uses 100-year GWP values, i.e., reflecting the ratio of the warming caused by a non-CO2 GHG to CO2 over a 100-year period after the pollutant is emitted. This is the most common timeframe used in policymaking and in the literature. Enabling this control setting switches to 20-year GWP values, the second-most-common timeframe used in the literature. Except for F-gases, non-CO2 GHGs will appear more important when using 20-year GWP values because they have shorter atmospheric lifetimes than CO2. // Note that F-gases in the model are a mixture of many gases, not a single chemical species. Input data on F-gases was available in 100-year GWP terms and cannot be converted to 20-year GWP values because of the unknown breakdown of the F-gas mixture. _Therefore, F-gases are always expressed in 100-year GWP terms, ignoring this lever setting._
A30: Cross-Sector | B30: Carbon Price | C30: Additional Carbon Tax Rate | D30: Carbon Price | E30: cross carbon tax | F30: 0 | G30: 300 | H30: 5 | I30: =UnitControlCenter!$B$55 -> $/metric ton CO2e | J30: **Description:** This policy applies a price on fuels used in the selected sector(s) based on their greenhouse gas emissions. It also increases the base cost of capital equipment (e.g., vehicles, power plants, building components) according to their embedded carbon content. When applied to the Industry Sector, the tax **is** levied on greenhouse gas emissions from non-energy industrial and agricultural processes by default, but these emissions sources can be exempted from the tax by enabling the policy lever "Exempt Process Emissions from C Tax." Note that by default, a carbon price will not include a border adjustment, but a border adjustment can be enabled using the policy lever "Toggle Carbon Tax Border Adjustment." // **Guidance for setting values:** The U.S. government's revised Social Cost of Carbon estimates for the year 2050 range from $200 to $520 per ton (in inflation-adjusted 2020 dollars), depending on one's choice of discount rate. | K30: fuels.html#carbon-tax | L30: carbon-tax.html | M30: U.S. EPA, 2015, "The Social Cost of Carbon", https://www.epa.gov/climatechange/social-cost-carbon, Row "2050". (For source for adjustment to 2018 dollars, see cpi.xlsx in InputData.) | N30: U.S. EPA, 2016, "Social Cost of CO2, 2015-2020," https://www.epa.gov/climatechange/social-cost-carbon
A31: Cross-Sector | B31: Change in Fuel Prices | C31: Policy Driven Change in Fuel Price | D31: Change in Fuel Prices | E31: cross fuel price change | F31: -0.5 | G31: 0.5 | H31: 0.01 | I31: % change in fuel price | J31: **Description:** The EPS endogenously calculates adjusts electricity prices in response to policies that shift supply, demand, and costs. But it does not endogenously adjust the price of other fuels. This lever allows the user to exogenously adjust prices to represent economic changes from other policies.
A32: Cross-Sector | B32: End Existing Subsidies | C32: Percent Reduction in BAU Subsidies | D32: End Existing Subsidies | E32: cross reduce BAU subsidies | F32: 0 | G32: 1 | H32: 0.01 | I32: % reduction in BAU subsidies | J32: **Description:** This policy reduces the subsidies paid for the production of the selected energy source(s) (relative to the BAU case). Note that some subsidies affect the cost of fuel (such as coal and natural gas), while some subsidies are for electricity production or capacity construction (federal Production Tax Credits and Investment Tax Credits). | K32: fuels.html#end-subsidies | L32: end-existing-subsidies.html | M32: Calculated from model data; see the relevant variable(s) in the InputData folder for source information.
A33: Cross-Sector | B33: Exempt Non-CO2 Emissions from C Tax | C33: Toggle Whether Carbon Tax Affects Non CO2 Emissions | E33: cross toggle whether carbon tax affects non CO2 emissions | F33: 0 | G33: 1 | H33: 1 | I33: on/off | J33: **Description:** By default, the carbon tax applies to CO2 and non-CO2 emissions. This policy exempts non-CO2 emissions, meaning the carbon tax will only apply to CO2 emissions. | K33: fuels.html#carbon-tax | L33: carbon-tax.html
A34: Cross-Sector | B34: Exempt Process Emissions from C Tax | C34: BEPEfCT Boolean Exempt Process Emissions from Carbon Tax | E34: cross toggle whether carbon tax affects process emissions | F34: 0 | G34: 1 | H34: 1 | I34: on/off | J34: **Description:** Turning this policy lever on prevents the carbon tax from being levied on process emissions from the selected industry categories. (Process emissions are non-energy greenhouse gas emissions from industrial and agricultural operations, for example emissions released due to chemical reactions during cement production). By default, we exempt agriculture and water and waste process emissions, as these categories are generally not covered by carbon tax proposals. | K34: fuels.html#carbon-tax | L34: carbon-tax.html
A35: Cross-Sector | B35: Fixed Energy Prices | C35: Toggle Whether Policies Affect Energy Prices | D35: Fixed Energy Prices | E35: cross toggle whether policies affect energy prices | F35: 0 | G35: 1 | H35: 1 | I35: on/off
A36: Cross-Sector | B36: Fuel Price Deregulation | C36: Fuel Price Deregulation | D36: Fuel Price Deregulation | E36: cross fuel price deregulation | F36: 0 | G36: 1 | H36: 0.01 | I36: % of price deregulated | J36: **Description:** This policy causes the price of the selected fuel(s) for domestic buyers to approach international market prices. // **Guidance for setting values:** A value of 100% causes domestic fuel prices to equal international market prices, increasing the domestic price by roughly X% in 2050. | K36: fuels.html#fuel-price-deregulation
A37: Cross-Sector | B37: Fuel Taxes or Subsidies | C37: Additional Fuel Tax or Subsidy Rate by Fuel | D37: Fuel Taxes or Subsidies | E37: cross fuel tax | F37: -0.9 | G37: 0.9 | H37: 0.01 | I37: % of BAU price | J37: **Description:** This policy changes the tax rate for the selected fuel type(s). It is expressed as a percentage of the BAU Scenario price, which includes sales and excise taxes. To increase the tax rate, set a positive value. To reduce the BAU tax rate (or to apply a subsidy), set a negative value. // **Guidance for setting values:** In 2012, the national average sales tax rate was 6.8% and the national average tax rate on gasoline was 14%. | K37: fuels.html#fuel-taxes | L37: fuel-taxes.html | M37: AVG SALES TAX: The Sales Tax Clearinghouse, FAQ, https://thestc.com/FAQ.stm, Question "What is the average sales tax nationally?" AVG GASOLINE TAX: Energy Information Administration, 2014, Annual Energy Outlook 2014, http://www.eia.gov/forecasts/aeo/supplement/suptab_130.xlsx, Supplement Table 130.
A38: Cross-Sector | B38: Non BAU Carbon Tax Industry Qualification | C38: Boolean Use Non BAU Carbon Tax Industry Category Qualification | F38: 0 | G38: 1 | H38: 1 | I38: on/off | J38: **Description:** This lever determines which industry categories are captured under the scope of a carbon tax. In some regions, only certain industries are covered by a carbon tax or cap.
A39: Cross-Sector | B39: Non BAU Carbon Tax Vehicle Qualification | C39: Boolean Use Non BAU Carbon Tax Vehicle Type Qualification | F39: 0 | G39: 1 | H39: 1 | I39: on/off | J39: **Description:** This lever determines which vehicle types are captured under the scope of a carbon tax. In some regions, only certain vehicle types are covered by a carbon tax or cap.
A40: Cross-Sector | B40: Non BAU CBAM Industry Qualification | C40: Boolean Use Non BAU Carbon Tax Border Adjustment Industry Qualification | F40: 0 | G40: 1 | H40: 1 | I40: on/off | J40: **Description:** This lever determines which industry categories are captured under the scope of a carbon border adjustment mechanism. In some regions, only certain industries are covered by a border mechanism.
A41: Cross-Sector | B41: Toggle Carbon Tax Border Adjustment | C41: BDCTBA Boolean Disable Carbon Tax Border Adjustment | F41: 0 | G41: 1 | H41: 1 | I41: on/off | J41: **Description:** By default, carbon taxes apply to only domestically produced goods. Turning this policy lever on enables carbon tax border adjustments, meaning the carbon tax will apply to both domestically produced and imported goods. | K41: fuels.html#carbon-tax | L41: carbon-tax.html
A42: District Heat and Hydrogen | B42: Non BAU Hydrogen Production Pathways | C42: Boolean Use Non BAU Hydrogen Shifting | D42: Hydrogen Steam Methane Reforming | E42: hydgn non BAU shift | F42: 0 | G42: 1 | H42: 1 | I42: on/off | J42: **Description:** This lever changes the direction of the "Shift Hydrogen Production Pathways" lever. By default, the "Shift Hydrogen Production Pathways" lever causes a percentage of merchant hydrogen (i.e. hydrogen produced for sale, not hydrogen produced and consumed on-site within a facility) to be produced via electrolysis rather than via other production pathways. If the Non BAU Hydrogen Production Pathways lever is enabled, it causes hydrogen production pathway shifting to work in the opposite direction by shifting hydrogen production to steam methane reforming. // **Guidance for setting values:** As of 2024, in the United States, roughly 95% of hydrogen is produced via steam reforming of natural gas and 5% is produced via electrolysis. These shares are projected to shift towards electrolysis in the Current Policies scenario due to hydrogen tax credits provided by the Inflation Reduction Act. Enabling this lever can be used to model repealing the Inflation Reduction Act tax credits. | L42: switch-hydrogen-production-pathway.html
A43: District Heat and Hydrogen | B43: Produce District Heat with Electricity | C43: Fraction of District Heat Fuel Use Shifted to Other Fuels | D43: District Heat Fuel Switching | E43: heat fuel type shifting | F43: 0 | G43: 1 | H43: 0.01 | I43: % of fuel use | J43: **Description:** This policy causes a percentage of the demand for district heat to be met with electricity instead of the fuels used in the BAU case. // **Guidance for setting values:** In the United States, 64% of district heat is made by burning natural gas, 17% from coal, 16% from biomass, and 3% from petroleum. Large scale electric heat pump technologies for district heating are still emerging, and it is not yet clear which will be the most economical pathway for decarbonizing this sector. | K43: district-heating.html#convert-coal | L43: district-heat-fuel-switching.html | M43: Calculated from model data; see the relevant variable(s) in the InputData folder for source information.
A44: District Heat and Hydrogen | B44: Shift Hydrogen Production Pathways | C44: Fraction of Hydrogen Production Pathways Shifted | D44: Shift Hydrogen Production Pathways | E44: hydgn shift production pathways | F44: 0 | G44: 1 | H44: 0.01 | I44: % of hydrogen production | J44: **Description:** By default, this policy causes a percentage of merchant hydrogen (i.e. hydrogen produced for sale, not hydrogen produced and consumed on-site within a facility) to be produced via electrolysis rather than via other production pathways. If the Non BAU Hydrogen Production Pathways lever is enabled, this lever works in the opposite direction by shifting hydrogen production to steam methane reforming. // **Guidance for setting values:** As of 2024, in the United States, roughly 95% of hydrogen is produced via steam reforming of natural gas and 5% is produced via electrolysis. These shares are projected to shift towards electrolysis. | L44: switch-hydrogen-production-pathway.html
A45: District Heat and Hydrogen | B45: Use CHP for District Heat | C45: Fraction of Non CHP Heat Production Converted to CHP | D45: District Heat CHP | E45: heat convert heat to CHP | F45: 0 | G45: 1 | H45: 0.01 | I45: % non-CHP heat converted | J45: **Description:** This policy causes a percentage of the district heat that would be generated by dedicated heat plants to instead be generated via CHP plants. In this model, this causes them to consume no additional fuel, since it is assumed CHP plants would be run anyway in order to produce electricity. // **Guidance for setting values:** In the BAU Scenario, the fraction of heat derived from CHP plants is constant at roughly 50%. Therefore, a policy setting of 50% would increase the CHP fraction to 75% in 2050. | K45: district-heating.html#chp | L45: convert-non-chp-heat-production.html | M45: Calculated from model data; see the relevant variable(s) in the InputData folder for source information.
A46: Electricity Supply | B46: Restrict New Power Plant Retrofits | C46: Boolean Ban New Power Plant Retrofits | D46: Restrict New Power Plant Retrofits | E46: elec ban new power plant retrofits | F46: 0 | G46: 1 | H46: 1 | I46: on/off | J46: **Description:** This policy prevents new capacity of the selected CCS plant type(s) from being built to replace existing non-CCS plants.
A47: Electricity Supply | B47: Restrict New Power Plants | C47: Boolean Ban New Power Plants | D47: Restrict New Power Plants | E47: elec ban new power plants | F47: 0 | G47: 1 | H47: 1 | I47: on/off | J47: **Description:** This policy prevents new capacity of the selected type(s) from being built or deployed. | K47: electricity-sector-main.html#ban | L47: ban-new-capacity.html
A48: Electricity Supply | B48: Change Electricity Exports | C48: Percent Change in Electricity Exports | D48: Electricity Imports and Exports | E48: elec change exports | F48: -1 | G48: 1 | H48: 0.02 | I48: % change in exports | J48: **Description:** This policy increases or decreases the amount of electricity exported from the state to surrounding states. It does not cause the construction or removal of transmission lines linking these states. | K48: electricity-sector-main.html#elec-exports | L48: electricity-imports-exports.html | M48: Energy Information Administation. 2016. Electric Power Annual. Table 2.13.
A49: Electricity Supply | B49: Change Electricity Imports | C49: Percent Change in Electricity Imports | D49: Electricity Imports and Exports | E49: elec change imports | F49: -1 | G49: 1 | H49: 0.02 | I49: % change in imports | J49: **Description:** This policy increases or decreases the amount of electricity imported to the state from surrounding states. It does not cause the construction or removal of transmission lines linking these states. | K49: electricity-sector-main.html#elec-imports | L49: electricity-imports-exports.html | M49: Energy Information Administation. 2016. Electric Power Annual. Table 2.13.
A50: Electricity Supply | B50: Change in Expected Power Plant Capacity Factor | C50: Percentage Reduction in Plant Downtime | D50: Reduce Plant Downtime | E50: elec reduce plant downtime | F50: -0.3 | G50: 0.6 | H50: 0.01 | I50: % reduction in downtime | J50: **Description:** This policy specifies the change in capacity factor (time spent generating power) for new natural gas combined cycle plants. This policy changes these plants' expected capacity factors, but it does not force them to be dispatched if it would be uneconomical to do so. A negative value implies a decrease in capacity factor relative to the Current Policies scenario. // **Guidance for setting values:** // **Natural Gas Combined Cycle:** As part of EPA's Clean Air Act Section 111 regulations for new power plants, natural gas combined cycle plants that operate more than 40 percent of the time must capture 90 percent of on-site emissions by 2032. This would effectively block new natural gas plants without CCS (which are tracked as a separate power plant type in the model). Therefore, we adjust the expected capacity factor for new combined cycle plants so that they would run at a maximum capacity factor of 40 percent starting in 2032. | K50: electricity-sector-main.html#red-downtime | L50: reduce-downtime.html | M50: E&E Publishing. The Clean Power Plan - A Summary. http://www.eenews.net/interactive/clean_power_plan/fact_sheets/rule National Renewable Energy Laboratory. United States (48 Contiguous States) Potential Wind Capacity Cumulative Area vs. Gross Capacity Factor. http://apps2.eere.energy.gov/wind/windexchange/pdfs/wind_maps/us_contiguous_wind_potential_chart.pdf See the discussion of multi-junction solar cells on Wikipedia at https://en.wikipedia.org/wiki/Multi-junction_solar_cell. Also NREL has a useful chart at http://www.nrel.gov/ncpv/images/efficiency_chart.jpg.
A51: Electricity Supply | B51: Clean Electricity Standard | C51: Clean Electricity Std Percentage | D51: Clean Electricity Standard | E51: elec clean electricity standards | F51: 0 | G51: 1 | H51: 0.01 | I51: % of electricity generation | J51: **Description:** This policy specifies the fraction of electricity generation that must come from qualifying carbon-free sources (wind, solar, biomass, nuclear, hydro, and geothermal) in 2050. This policy has no effect until the user-set value exceeds the existing fraction of carbon-free electricity and any carbon-free electricity standards which have been enacted at the state level. Also note that the model incorporates a cap on the CES credit price. If the CES credit price hits this $/MWh amount in a given year, the model will not deploy any additional CES qualifying resources. You can change the maximum CES credit price in the Clean Electricity Standard Alternative Compliance Payment lever. // **Guidance for setting values:** Multiple states have set 100% clean energy or renewable energy laws or goals, including California, Hawaii, New Jersey, New York, Washington, New Mexico, Maine, Wisconsin, Minnesota, Nevada, and Washington DC. The earliest 100% target is Washington DC by 2032, with other states pledging to reach 100% clean or renewable energy by 2040-2050. At very high CES values, the associated policy costs are highly uncertain and should be complemented with other modeling. | K51: electricity-sector-main.html#ces | L51: clean-energy-standard.html | M51: White House, 2015, "Fact Sheet: President Obama to Announce Historic Carbon Pollution Standards for Power Plants", https://www.whitehouse.gov/the-press-office/2015/08/03/fact-sheet-president-obama-announce-historic-carbon-pollution-standards.
A52: Electricity Supply | B52: Clean Electricity Standard Foresight | C52: BESHFoFRV Boolean Electricity Suppliers Have Foresight of Future RPS Values | F52: 0 | G52: 1 | H52: 1 | I52: on/off | J52: **Description:** This setting indicates whether electricity suppliers have foresight of future-year CES values (both BAU case values and any values set by the user in the CES policy lever). With foresight, electricity suppliers will build some CES-qualifying resources in earlier years than would be strictly necessary to meet the CES requirement in those years if it allows them to approach a higher, future-year CES target more gradually, lessening the need to build power plants abruptly if the CES rises more steeply in the future.
A53: Electricity Supply | B53: Decrease Cost of Capital | C53: Percentage Decrease in Cost of Capital for Power Plants | D53: Decrease Electricity Sector Cost of Capital | E53: elec power plant cost of capital | F53: 0 | G53: 1 | H53: 1 | I53: % decrease | J53: **Description:** This policy decreases the cost of capital for new power plant investments, making the specified plant type more attractive to deploy. // **Guidance for setting values:** The BAU cost of capital for all plant types is calculated as 7.4%, based on data from Lazard. | M53: https://www.lazard.com/media/451905/lazards-levelized-cost-of-energy-version-150-vf.pdf
A54: Electricity Supply | B54: Demand Response | C54: Fraction of Additional Demand Response Potential Achieved | D54: Demand Response | E54: elec demand response | F54: 0 | G54: 1 | H54: 0.01 | I54: % of potential achieved | J54: **Description:** This policy represents regulations that cause more demand response (DR) capacity to be added to the electric grid. Demand response provides flexibility that allows for the integration of more wind and solar PV, if the electricity system is flexibility-constrained. Demand response can be load-shedding (demand is reduced in the worst hours without adding demand in other hours) or load-shifting (demand is reduced in the worst hours and added in other hours). The type of demand response modeled here is load-shedding, which is by far the most common type of demand response that exists today. | K54: electricity-sector-main.html#dr | L54: demand-response.html | M54: Calculated from model data; see the relevant variable(s) in the InputData folder for source information.
A55: Electricity Supply | B55: Early Retirement of Power Plants | C55: Annual Additional Capacity Retired due to Early Retirement Policy | D55: Early Retirement of Power Plants | E55: elec early retirement | F55: 0 | G55: 5000 | H55: 500 | I55: MW/year | J55: **Description:** This policy causes the specified quantity of otherwise non-retiring capacity of the selected type(s) to be retired each year. | K55: electricity-sector-main.html#early-ret | L55: early-retirement-of-power-plants.html | M55: Energy Information Administration, 2014, "Annual Energy Outlook 2014", http://www.eia.gov/oiaf/aeo/tablebrowser/#release=AEO2014&subject=6-AEO2014&table=9-AEO2014&region=0-0&cases=hccstom-d012314a,ref2014-d102413a, Table Browser. Select Electric Power Sector, Electricity Generating Capacity (and check Reference and Accelerated coal retirements scenarios). | N55: The Brattle Group, 2012, "Potential Coal Plant Retirements: 2012 Update," http://greatlakeslegalfoundation.org/wwcms/wp-content/uploads/documents/regulatory/TrainWreck/12Oct15_BrattleStudy.pdf, Page 8, Table 4
A56: Electricity Supply | B56: Electricity CCS Subsidy | C56: Additional Subsidy for Elec CCS | D56: Electricity CCS Subsidy | E56: elec CCS subsidy | F56: -100 | G56: 100 | H56: 1 | I56: $ / metric ton CO2e | J56: **Description:** This policy provides a dollar per metric ton CO2e subsidy, additional to any BAU subsidies. // **Guidance for setting values:** The 45Q tax credits provide $85 per metric ton CO2e stored, which is included in the BAU case.
A57: Electricity Supply | B57: Existing Power Plant Production Subsidy | C57: Additional Subsidy for Elec Production for Existing Plants | D57: Existing Power Plant Production Subsidy | E57: elec existing plant generation subsidy | F57: 0 | G57: 60 | H57: 1 | I57: =UnitControlCenter!$B$56 -> $/MWh | J57: **Description:** This policy is a subsidy paid by the government to suppliers of electricity per unit of electricity generated from the selected plant type(s) for preexisting plants. // **Guidance for setting values:** The U.S. provides credits to existing nuclear plants at a rate of $15/MWh, with a 10% bonus credit for new plants. // Also note that the Energy Policy Simulator chooses which new power plants to build based on lifetime plant costs, and unlike the PTC, which is only available for the first 10 years of a project, this variable subsidy is available for the duration of a plant's lifetime.
A58: Electricity Supply | B58: Lift the Clean Electricity Standard Alternative Compliance Payment | C58: Boolean Use Non BAU RPS Alternative Compliance Payment | D58: Clean Electricity Standard | E58: elec non BAU RACP | F58: 0 | G58: 1 | H58: 1 | I58: on/off | J58: **Description:** The BAU scenario includes a CES alternative compliance payment of roughly 180 $/MWh, meaning the model will not deploy any additional CES qualifying resources above this price in an attempt to meet the CES. Enabling this policy lifts this cap, meaning there is no price constraint on new resources.
A59: Electricity Supply | B59: Non BAU Capacity Retirement Schedule | C59: Boolean Use Non BAU Capacity Retirement Schedule | D59: Non BAU Capacity Retirement Schedule | F59: 0 | G59: 1 | H59: 1 | I59: on/off | J59: **Description:** The EPS calculates economc capacity additions and retirements in each time step. In addition, it incorporates any announced retirements through input data files. This policy uses an alternate input data file specifying planned retirement schedules for existing capacity of the selected type(s). // **Guidance for setting values:** The Current Policies scenario includes all expected coal retirements resulting from EPA's Clean Air Act Section 111 regulations for power plants, as well as from other regulations and legislation like the Inflation Reduction Act. Turning this lever on removes the effect of those federal policies, resulting in fewer coal retirements.
A60: Electricity Supply | B60: Non BAU CES Qualifying Resources | C60: Boolean Use Non BAU Elec Portfolio Qualifying Definitions | D60: Clean Electricity Standard | E60: elec non BAU elec portfolio settings | F60: 0 | G60: 1 | H60: 1 | I60: on/off | J60: **Description:** This policy expands the definitions for qualifying carbon-free sources to include: nuclear, hydro, wind, solar, biomass, geothermal, municipal solid waste, carbon capture and storage, and hydrogen.//
A61: Electricity Supply | B61: Non BAU Guaranteed Dispatch | C61: Boolean Use Non BAU Guaranteed Dispatch Settings | D61: Non BAU Guaranteed Dispatch | E61: elec non BAU guaranteed dispatch | F61: 0 | G61: 1 | H61: 1 | I61: on/off
A62: Electricity Supply | B62: Non BAU Mandated Capacity CCUS Retrofits | C62: Boolean Use Non BAU Mandated Capacity Retrofit Schedule | D62: Non BAU Mandated Capacity CCUS Retrofits | F62: 0 | G62: 1 | H62: 1 | I62: on/off | J62: **Description:** The business-as-usual case does not include any planned CCUS retrofits. Turning this policy lever "on" assumes retrofits modeled by the EPA for its latest Clean Air Act Section 111 regulations for power plants.
A63: Electricity Supply | B63: Non BAU Mandated Capacity Construction | C63: Boolean Use Non BAU Mandated Capacity Construction Schedule | D63: Non BAU Mandated Capacity Construction | F63: 0 | G63: 1 | H63: 1 | I63: on/off | J63: **Description:** The business-as-usual case includes all capacity currently under construction (data provided by the U.S. Energy Information Administration). This policy uses an alternate set of planned capacity additions. // **Guidance for setting values:** // **Solar PV and Onshore Wind:** This policy lever includes all capacity currently under construction or planned but not yet under construction. // **Offshore Wind:** When used in the context of the NDC scenario, this policy results in roughly 30 GW of offshore wind by 2030 and 220 of offshore wind by 2050.
A64: Electricity Supply | B64: Reduce Soft Costs | C64: Percent Reduction in Soft Costs of Capacity Construction | D64: Reduce Soft Costs | E64: elec reduce soft costs | F64: 0 | G64: 0.9 | H64: 0.01 | I64: % reduction in soft costs | J64: **Description:** This policy specifies a reduction in soft costs (costs for things other than capital equipment) for new plants of the selected type(s), such as the costs of permitting, financing, project management, assembly, etc. // **Guidance for setting values:** Costs of permitting and financing can be reduced by streamlining permitting processes, but some soft costs (such as labor) may be difficult to reduce via policy. A value of 50% would be an aggressive soft cost reduction. | K64: endogenous-learning.html#red-soft-costs | L64: reduce-soft-costs.html
A65: Electricity Supply | B65: Reduce Transmission & Distribution Losses | C65: Percentage TnD Losses Avoided | D65: Reduce T&D Losses | E65: elec avoid TND loss | F65: 0 | G65: 0.4 | H65: 0.01 | I65: % of losses avoided | J65: **Description:** This policy specifies the reduction in transmission and distribution losses that will be achieved by 2050. // **Guidance for setting values:** The U.S. has transmission and distribution losses of about 6%. Germany, Japan, Finland, and the Netherlands have T&D losses of around 4%. Therefore, a 33% policy setting would cause the U.S. to match these countries' current level of T&D losses by 2050. | K65: electricity-sector-main.html#red-tnd-losses | L65: reduce-tnd-losses.html | M65: The World Bank. Electric power transmission and distribution losses (% of output). http://data.worldbank.org/indicator/EG.ELC.LOSS.ZS
A66: Electricity Supply | B66: Renewable Portfolio Standard | C66: Renewable Portfolio Std Percentage | D66: Renewable Portfolio Standard | E66: elec renewable portfolio standards | F66: 0 | G66: 1 | H66: 0.01 | I66: % of electricity generation | J66: **Description:** This policy specifies the fraction of electricity generation that must come from qualifying renewable sources (wind, solar, hydro, geothermal, and hydrogen) in 2050. This policy has no effect until the user-set value exceeds the existing fraction of renewable electricity and any renewable electricity standards which have been enacted at the state level. Also note that the model incorporates a cap on the RPS credit price. If the RPS credit price hits this $/MWh amount in a given year, the model will not deploy any additional RPS qualifying resources. You can change the maximum RPS credit price in the Clean Electricity Standard Alternative Compliance Payment lever. // **Guidance for setting values:** Multiple states have set 100% clean energy or renewable energy laws or goals, including California, Hawaii, New Jersey, New York, Washington, New Mexico, Maine, Wisconsin, Minnesota, Nevada, and Washington DC. The earliest 100% target is Washington DC by 2032, with other states pledging to reach 100% clean or renewable energy by 2040-2050. At very high RPS values, the associated policy costs are highly uncertain and should be complemented with other modeling.
A67: Electricity Supply | B67: Subsidy for Capacity Construction | C67: Perc Subsidy for Elec Capacity Construction | D67: Subsidy for Capacity Construction | E67: elec capacity construction subsidy | F67: 0 | G67: 0.95 | H67: 0.01 | I67: % of construction cost | J67: **Description:** This policy is a subsidy paid by the government to electricity suppliers per unit of new capacity constructed. This only applies to utilities, not distributed systems (such as rooftop solar). // **Guidance for setting values:** The U.S. provided clean electricity tax credits as part of the Inflation Reduction Act (IRA). Tax credits are claimed as either the Investment Tax Credit (per unit capacity) or Production Tax Credit (per unit electricity generation), depending on the plant type. However, the One Big Beautiful Bill Act (OBBBA) phased out these credits early, with qualification through 2030 for projects that commence construction by July 2026. The BAU assumes IRA tax credits will begin phasing out after the year 2028, reaching $0/MW in 2031, to reflect the declining stock of safe-harbored capacity through 2030. // **Nuclear:** The U.S. Federal Government has guaranteed billions of dollars of loans for the construction new nuclear plants and has funded billions of dollars of nuclear technology R&D. The construction of two new reactors at the Vogtle power plant, the only recently built nuclear energy project under construction in the U.S., received $12 billion in loan guarantees as of March 2019. (Loan guarantees are not equivalent to subsidies dollar-for-dollar, but they lower the cost of construction by enabling the plant to access cheaper financing.) // **Solar Thermal:** We assume IRA tax credits of 41.6%, based on assumptions on which share of new plants qualify for various bonus credits. // **Biomass:** The U.S. Federal Government has collectively guaranteed billions of dollars of loans for the construction new biomass plants. (Loan guarantees are not equivalent to subsidies dollar-for-dollar, but they lower the cost of construction by enabling the plant to access cheaper financing.) // **Geothermal:** We assume IRA tax credits of 41.6%, based on assumptions on which share of new plants qualify for various bonus credits. // **Offshore Wind:** We assume IRA tax credits of 41.6%, based on assumptions on which share of new plants qualify for various bonus credits. | K67: electricity-sector-main.html#subsidies | M67: https://www.energy.gov/articles/secretary-perry-announces-financial-close-additional-loan-guarantees-during-trip-vogtle https://www.energysage.com/solar/cost-benefit/solar-investment-tax-credit/ http://biomassmagazine.com/articles/8185/usda-loan-guarantees-support-3-biomass-power-plants
A68: Electricity Supply | B68: Subsidy for Electricity Production | C68: Subsidy for Elec Production by Fuel | D68: Subsidy for Electricity Production | E68: elec generation subsidy | F68: 0 | G68: 60 | H68: 1 | I68: =UnitControlCenter!$B$56 -> $/MWh | J68: **Description:** This policy is a subsidy paid by the government to suppliers of electricity per unit of electricity generated from the selected plant type(s). // **Guidance for setting values:** The U.S. provided clean electricity tax credits as part of the Inflation Reduction Act (IRA). Tax credits are claimed as either the Investment Tax Credit (per unit capacity) or Production Tax Credit (per unit electricity generation), depending on the plant type. The BAU assumes IRA tax credits will begin phasing out after the year 2036, when electricity sector emissions reach the target of 25% below 2022 levels. // Also note that the Energy Policy Simulator chooses which new power plants to build based on lifetime plant costs, and the PTC is only available for the first 10 years of a project. // **Nuclear:** We assume roughly $10/MWh worth of incentives for nuclear in our BAU as part of the IRA and the Infrastructure Investment and Jobs Act. // **Onshore Wind:** We assume IRA tax credits of roughly $32 per MWh, based on assumptions on which share of new plants qualify for various bonus credits. // **Solar PV:** We assume IRA tax credits of roughly $31, based on assumptions on which share of new plants qualify for various bonus credits. | K68: electricity-sector-main.html#subsidies | L68: subsidy-for-electricity-production.html | M68: PRODUCTION TAX CREDIT: Database of State Incentives for Renewables & Efficiency, 2013, "Renewable Energy Production Tax Credit (PTC)", http://dsireusa.org/incentives/incentive.cfm?Incentive_Code=US13F. STATE-LEVEL INCENTIVES: Energy Information Administration, 2013, "Feed-In Tariffs and similar programs", http://www.eia.gov/electricity/policies/provider_programs.cfm.
A69: Electricity Supply | B69: Subsidy for Grid Battery Capacity | C69: Additional Percent Subsidy per Unit Grid Battery Capacity Deployed | D69: Grid Battery Subsidy | E69: elec battery construction subsidy | F69: -1 | G69: 1 | H69: 0.01 | I69: % of capital costs | J69: **Description:** This policy subsidizes a percentage of grid battery capacity costs, additional to any BAU capacity construction subsidies. A negative value implies a tax or removal of subsidies. // **Guidance for setting values:** We assume IRA tax credits of 41.6%, based on assumptions on which share of new projects qualify for various bonus credits.
A70: Electricity Supply | B70: Subsidy for Grid Battery Output | C70: Additional Subsidy per Unit Electricity Supplied to the Grid by Grid Batteries | D70: Grid Battery Subsidy | E70: elec battery subsidy per output | F70: -100 | G70: 100 | H70: 1 | I70: $/kWh | J70: **Description:** This policy provides a subsidy in units of dollar per megawatt-hour electricity supplied to the grid, additional to any BAU subsidies. A negative value implies a tax or removal of subsidies. // **Guidance for setting values:** The BAU case has grid batteries claiming the Subsidy for Grid Battery Capacity, not a subsidy per unit output.
A71: Electricity Supply | B71: Subsidy for Grid Battery Production | C71: Additional Subsidy for Grid Battery Production | D71: Grid Battery Subsidy | E71: elec battery production subsidy | F71: -100 | G71: 100 | H71: 1 | I71: $/kWh | J71: **Description:** This policy provides a subsidy in units of dollars per kilowatt-hour of battery capacity produced by manufacturers, additional to any BAU subsidies. A negative value implies a tax or removal of subsidies. // **Guidance for setting values:** The BAU case has a $45/kWh production credit provided to manufacturers reflecting the Inflation Reduction Act's 45X tax credit.
A72: Electricity Supply | B72: Use EVs for Grid Balancing | C72: Share of EVs Used for Grid Balancing | D72: EVs for Grid Balancing | E72: elec use EVs for grid balancing | F72: 0 | G72: 1 | H72: 0.01 | I72: % of EVs used | J72: **Description:** This policy increases the share of EVs that are used to assist in grid balancing on an average day. This means the EV is connected to the grid during the hours when demand-shifting would be helpful (hours of net peak load) and can pause its charging or, ideally, can partially discharge its battery during these hours to help provide electricity to the grid. // **Guidance for setting values:** Today, EVs generally are not used to help with grid balancing, and EVs and chargers may not have the capability to send electricity in the reverse direction to supply the grid (and have suitable safety cut-off systems to prevent energizing the grid when utilities intentionally shut it down to do repairs and maintenance). Automatically changing the hours when an EV charges (but not discharging to support the grid) is technologically easier but provides less support to the grid.
A73: Government Revenue Accounting | B73: Battery Production Subsidy | C73: GRA for Battery Production Subsidy | E73: GRA battery production subsidy | F73: 0 | G73: 10 | H73: 1 | I73: weight | J73: **Description:** This setting is one of several "Government Revenue Accounting" control settings that help determine how the government accounts for certain changes in its cash flow (such as increased or decreased tax revenues or subsidy payments). These settings allow for new revenue or spending to be allocated to different purposes by designating shareweights to each accounting purpose. The accounting purposes are: **Regular Spending** increasing this weight means the government will use increased revenue (or account account for increased spending) by increasing (or decreasing) spending on its normal budget (e.g., activities such as defense, education, and administrative expenses). **Budget Deficit** increasing this weight means government will use increased revenue (or account for increased spending) on the deficit, shrinking (or growing) the national debt (with associated implications for interest payments)grow or shrink the national debt (with associated implications for interest payments). **Household Taxes** increasing this weight means the government will use increased revenue (or account for increased spending) to decrease (or increase) taxes on households. A "climate dividend" is considered to be a decrease in household taxes. **Payroll Taxes** increasing this weight means government will use increased revenue (or account for increased spending) to decrease (or increase) payroll taxes. **Corporate Taxes** increasing this weight means government will use increased revenue (or account for increased spending) to decrease (or increase) corporate taxes. // **Guidance for setting values:** This value is set as a weight (1 to 10) for each accounting purpose, in order to indicate how the increased revenue (or spending) from this policy should be allocated among the five revenue accounting options. The share of the change in cash flow allocated to each revenue accounting option is calculated as that option's weight divided by the total of the weights assigned to all options. If every purpose is assigned zero weight, they all receive an equal share of the change in cash flow. | K73: io-model.html
A74: Government Revenue Accounting | B74: Carbon Tax Revenue | C74: GRA for Carbon Tax Revenue | E74: GRA carbon tax revenue | F74: 0 | G74: 10 | H74: 1 | I74: weight | J74: **Description:** This setting is one of several "Government Revenue Accounting" control settings that help determine how the government accounts for certain changes in its cash flow (such as increased or decreased tax revenues or subsidy payments). These settings allow for new revenue or spending to be allocated to different purposes by designating shareweights to each accounting purpose. The accounting purposes are: **Regular Spending** increasing this weight means the government will use increased revenue (or account account for increased spending) by increasing (or decreasing) spending on its normal budget (e.g., activities such as defense, education, and administrative expenses). **Budget Deficit** increasing this weight means government will use increased revenue (or account for increased spending) on the deficit, shrinking (or growing) the national debt (with associated implications for interest payments)grow or shrink the national debt (with associated implications for interest payments). **Household Taxes** increasing this weight means the government will use increased revenue (or account for increased spending) to decrease (or increase) taxes on households. A "climate dividend" is considered to be a decrease in household taxes. **Payroll Taxes** increasing this weight means government will use increased revenue (or account for increased spending) to decrease (or increase) payroll taxes. **Corporate Taxes** increasing this weight means government will use increased revenue (or account for increased spending) to decrease (or increase) corporate taxes. // **Guidance for setting values:** This value is set as a weight (1 to 10) for each accounting purpose, in order to indicate how the increased revenue (or spending) from this policy should be allocated among the five revenue accounting options. The share of the change in cash flow allocated to each revenue accounting option is calculated as that option's weight divided by the total of the weights assigned to all options. If every purpose is assigned zero weight, they all receive an equal share of the change in cash flow. | K74: io-model.html
A75: Government Revenue Accounting | B75: CCS Subsidy | C75: GRA for CCS Subsidies | E75: GRA CCS subsidy | F75: 0 | G75: 10 | H75: 1 | I75: weight | J75: **Description:** This setting is one of several "Government Revenue Accounting" control settings that help determine how the government accounts for certain changes in its cash flow (such as increased or decreased tax revenues or subsidy payments). These settings allow for new revenue or spending to be allocated to different purposes by designating shareweights to each accounting purpose. The accounting purposes are: **Regular Spending** increasing this weight means the government will use increased revenue (or account account for increased spending) by increasing (or decreasing) spending on its normal budget (e.g., activities such as defense, education, and administrative expenses). **Budget Deficit** increasing this weight means government will use increased revenue (or account for increased spending) on the deficit, shrinking (or growing) the national debt (with associated implications for interest payments)grow or shrink the national debt (with associated implications for interest payments). **Household Taxes** increasing this weight means the government will use increased revenue (or account for increased spending) to decrease (or increase) taxes on households. A "climate dividend" is considered to be a decrease in household taxes. **Payroll Taxes** increasing this weight means government will use increased revenue (or account for increased spending) to decrease (or increase) payroll taxes. **Corporate Taxes** increasing this weight means government will use increased revenue (or account for increased spending) to decrease (or increase) corporate taxes. // **Guidance for setting values:** This value is set as a weight (1 to 10) for each accounting purpose, in order to indicate how the increased revenue (or spending) from this policy should be allocated among the five revenue accounting options. The share of the change in cash flow allocated to each revenue accounting option is calculated as that option's weight divided by the total of the weights assigned to all options. If every purpose is assigned zero weight, they all receive an equal share of the change in cash flow. | K75: io-model.html
A76: Government Revenue Accounting | B76: Distributed Solar Subsidy | C76: GRA for Distributed Solar Subsidy | E76: GRA dist solar subsidy | F76: 0 | G76: 10 | H76: 1 | I76: weight | J76: **Description:** This setting is one of several "Government Revenue Accounting" control settings that help determine how the government accounts for certain changes in its cash flow (such as increased or decreased tax revenues or subsidy payments). These settings allow for new revenue or spending to be allocated to different purposes by designating shareweights to each accounting purpose. The accounting purposes are: **Regular Spending** increasing this weight means the government will use increased revenue (or account account for increased spending) by increasing (or decreasing) spending on its normal budget (e.g., activities such as defense, education, and administrative expenses). **Budget Deficit** increasing this weight means government will use increased revenue (or account for increased spending) on the deficit, shrinking (or growing) the national debt (with associated implications for interest payments)grow or shrink the national debt (with associated implications for interest payments). **Household Taxes** increasing this weight means the government will use increased revenue (or account for increased spending) to decrease (or increase) taxes on households. A "climate dividend" is considered to be a decrease in household taxes. **Payroll Taxes** increasing this weight means government will use increased revenue (or account for increased spending) to decrease (or increase) payroll taxes. **Corporate Taxes** increasing this weight means government will use increased revenue (or account for increased spending) to decrease (or increase) corporate taxes. // **Guidance for setting values:** This value is set as a weight (1 to 10) for each accounting purpose, in order to indicate how the increased revenue (or spending) from this policy should be allocated among the five revenue accounting options. The share of the change in cash flow allocated to each revenue accounting option is calculated as that option's weight divided by the total of the weights assigned to all options. If every purpose is assigned zero weight, they all receive an equal share of the change in cash flow. | K76: io-model.html
A77: Government Revenue Accounting | B77: Electricity Capacity Construction Subsidy | C77: GRA for Electricity Capacity Construction Subsidies | E77: GRA elec cap const subsidy | F77: 0 | G77: 10 | H77: 1 | I77: weight | J77: **Description:** This setting is one of several "Government Revenue Accounting" control settings that help determine how the government accounts for certain changes in its cash flow (such as increased or decreased tax revenues or subsidy payments). These settings allow for new revenue or spending to be allocated to different purposes by designating shareweights to each accounting purpose. The accounting purposes are: **Regular Spending** increasing this weight means the government will use increased revenue (or account account for increased spending) by increasing (or decreasing) spending on its normal budget (e.g., activities such as defense, education, and administrative expenses). **Budget Deficit** increasing this weight means government will use increased revenue (or account for increased spending) on the deficit, shrinking (or growing) the national debt (with associated implications for interest payments)grow or shrink the national debt (with associated implications for interest payments). **Household Taxes** increasing this weight means the government will use increased revenue (or account for increased spending) to decrease (or increase) taxes on households. A "climate dividend" is considered to be a decrease in household taxes. **Payroll Taxes** increasing this weight means government will use increased revenue (or account for increased spending) to decrease (or increase) payroll taxes. **Corporate Taxes** increasing this weight means government will use increased revenue (or account for increased spending) to decrease (or increase) corporate taxes. // **Guidance for setting values:** This value is set as a weight (1 to 10) for each accounting purpose, in order to indicate how the increased revenue (or spending) from this policy should be allocated among the five revenue accounting options. The share of the change in cash flow allocated to each revenue accounting option is calculated as that option's weight divided by the total of the weights assigned to all options. If every purpose is assigned zero weight, they all receive an equal share of the change in cash flow. | K77: io-model.html
A78: Government Revenue Accounting | B78: Electricity Generation Subsidy | C78: GRA for Electricity Generation Subsidies | E78: GRA elec gen subsidy | F78: 0 | G78: 10 | H78: 1 | I78: weight | J78: **Description:** This setting is one of several "Government Revenue Accounting" control settings that help determine how the government accounts for certain changes in its cash flow (such as increased or decreased tax revenues or subsidy payments). These settings allow for new revenue or spending to be allocated to different purposes by designating shareweights to each accounting purpose. The accounting purposes are: **Regular Spending** increasing this weight means the government will use increased revenue (or account account for increased spending) by increasing (or decreasing) spending on its normal budget (e.g., activities such as defense, education, and administrative expenses). **Budget Deficit** increasing this weight means government will use increased revenue (or account for increased spending) on the deficit, shrinking (or growing) the national debt (with associated implications for interest payments)grow or shrink the national debt (with associated implications for interest payments). **Household Taxes** increasing this weight means the government will use increased revenue (or account for increased spending) to decrease (or increase) taxes on households. A "climate dividend" is considered to be a decrease in household taxes. **Payroll Taxes** increasing this weight means government will use increased revenue (or account for increased spending) to decrease (or increase) payroll taxes. **Corporate Taxes** increasing this weight means government will use increased revenue (or account for increased spending) to decrease (or increase) corporate taxes. // **Guidance for setting values:** This value is set as a weight (1 to 10) for each accounting purpose, in order to indicate how the increased revenue (or spending) from this policy should be allocated among the five revenue accounting options. The share of the change in cash flow allocated to each revenue accounting option is calculated as that option's weight divided by the total of the weights assigned to all options. If every purpose is assigned zero weight, they all receive an equal share of the change in cash flow. | K78: io-model.html
A79: Government Revenue Accounting | B79: Fuel Subsidy | C79: GRA for Fuel Subsidies | E79: GRA fuel subsidy | F79: 0 | G79: 10 | H79: 1 | I79: weight | J79: **Description:** This setting is one of several "Government Revenue Accounting" control settings that help determine how the government accounts for certain changes in its cash flow (such as increased or decreased tax revenues or subsidy payments). These settings allow for new revenue or spending to be allocated to different purposes by designating shareweights to each accounting purpose. The accounting purposes are: **Regular Spending** increasing this weight means the government will use increased revenue (or account account for increased spending) by increasing (or decreasing) spending on its normal budget (e.g., activities such as defense, education, and administrative expenses). **Budget Deficit** increasing this weight means government will use increased revenue (or account for increased spending) on the deficit, shrinking (or growing) the national debt (with associated implications for interest payments)grow or shrink the national debt (with associated implications for interest payments). **Household Taxes** increasing this weight means the government will use increased revenue (or account for increased spending) to decrease (or increase) taxes on households. A "climate dividend" is considered to be a decrease in household taxes. **Payroll Taxes** increasing this weight means government will use increased revenue (or account for increased spending) to decrease (or increase) payroll taxes. **Corporate Taxes** increasing this weight means government will use increased revenue (or account for increased spending) to decrease (or increase) corporate taxes. // **Guidance for setting values:** This value is set as a weight (1 to 10) for each accounting purpose, in order to indicate how the increased revenue (or spending) from this policy should be allocated among the five revenue accounting options. The share of the change in cash flow allocated to each revenue accounting option is calculated as that option's weight divided by the total of the weights assigned to all options. If every purpose is assigned zero weight, they all receive an equal share of the change in cash flow. | K79: io-model.html
A80: Government Revenue Accounting | B80: Fuel Tax Revenue | C80: GRA for Fuel Tax Revenue | E80: GRA fuel tax revenue | F80: 0 | G80: 10 | H80: 1 | I80: weight | J80: **Description:** This setting is one of several "Government Revenue Accounting" control settings that help determine how the government accounts for certain changes in its cash flow (such as increased or decreased tax revenues or subsidy payments). These settings allow for new revenue or spending to be allocated to different purposes by designating shareweights to each accounting purpose. The accounting purposes are: **Regular Spending** increasing this weight means the government will use increased revenue (or account account for increased spending) by increasing (or decreasing) spending on its normal budget (e.g., activities such as defense, education, and administrative expenses). **Budget Deficit** increasing this weight means government will use increased revenue (or account for increased spending) on the deficit, shrinking (or growing) the national debt (with associated implications for interest payments)grow or shrink the national debt (with associated implications for interest payments). **Household Taxes** increasing this weight means the government will use increased revenue (or account for increased spending) to decrease (or increase) taxes on households. A "climate dividend" is considered to be a decrease in household taxes. **Payroll Taxes** increasing this weight means government will use increased revenue (or account for increased spending) to decrease (or increase) payroll taxes. **Corporate Taxes** increasing this weight means government will use increased revenue (or account for increased spending) to decrease (or increase) corporate taxes. // **Guidance for setting values:** This value is set as a weight (1 to 10) for each accounting purpose, in order to indicate how the increased revenue (or spending) from this policy should be allocated among the five revenue accounting options. The share of the change in cash flow allocated to each revenue accounting option is calculated as that option's weight divided by the total of the weights assigned to all options. If every purpose is assigned zero weight, they all receive an equal share of the change in cash flow. | K80: io-model.html
A81: Government Revenue Accounting | B81: National Debt Interest | C81: GRA for National Debt Interest | E81: GRA national debt interest | F81: 0 | G81: 10 | H81: 1 | I81: weight | J81: **Description:** This setting is one of several "Government Revenue Accounting" control settings that help determine how the government accounts for certain changes in its cash flow (such as increased or decreased tax revenues or subsidy payments). These settings allow for new revenue or spending to be allocated to different purposes by designating shareweights to each accounting purpose. The accounting purposes are: **Regular Spending** increasing this weight means the government will use increased revenue (or account account for increased spending) by increasing (or decreasing) spending on its normal budget (e.g., activities such as defense, education, and administrative expenses). **Budget Deficit** increasing this weight means government will use increased revenue (or account for increased spending) on the deficit, shrinking (or growing) the national debt (with associated implications for interest payments)grow or shrink the national debt (with associated implications for interest payments). **Household Taxes** increasing this weight means the government will use increased revenue (or account for increased spending) to decrease (or increase) taxes on households. A "climate dividend" is considered to be a decrease in household taxes. **Payroll Taxes** increasing this weight means government will use increased revenue (or account for increased spending) to decrease (or increase) payroll taxes. **Corporate Taxes** increasing this weight means government will use increased revenue (or account for increased spending) to decrease (or increase) corporate taxes. // **Guidance for setting values:** This value is set as a weight (1 to 10) for each accounting purpose, in order to indicate how the increased revenue (or spending) from this policy should be allocated among the five revenue accounting options. The share of the change in cash flow allocated to each revenue accounting option is calculated as that option's weight divided by the total of the weights assigned to all options. If every purpose is assigned zero weight, they all receive an equal share of the change in cash flow. | K81: io-model.html
A82: Government Revenue Accounting | B82: Remaining Government Cash Flows | C82: GRA for Remaining Government Cash Flow Changes | E82: GRA remaining cash flow changes | F82: 0 | G82: 10 | H82: 1 | I82: weight | J82: **Description:** This setting is one of several "Government Revenue Accounting" control settings that help determine how the government accounts for certain changes in its cash flow (such as increased or decreased tax revenues or subsidy payments). These settings allow for new revenue or spending to be allocated to different purposes by designating shareweights to each accounting purpose. The accounting purposes are: **Regular Spending** increasing this weight means the government will use increased revenue (or account account for increased spending) by increasing (or decreasing) spending on its normal budget (e.g., activities such as defense, education, and administrative expenses). **Budget Deficit** increasing this weight means government will use increased revenue (or account for increased spending) on the deficit, shrinking (or growing) the national debt (with associated implications for interest payments)grow or shrink the national debt (with associated implications for interest payments). **Household Taxes** increasing this weight means the government will use increased revenue (or account for increased spending) to decrease (or increase) taxes on households. A "climate dividend" is considered to be a decrease in household taxes. **Payroll Taxes** increasing this weight means government will use increased revenue (or account for increased spending) to decrease (or increase) payroll taxes. **Corporate Taxes** increasing this weight means government will use increased revenue (or account for increased spending) to decrease (or increase) corporate taxes. // **Guidance for setting values:** This value is set as a weight (1 to 10) for each accounting purpose, in order to indicate how the increased revenue (or spending) from this policy should be allocated among the five revenue accounting options. The share of the change in cash flow allocated to each revenue accounting option is calculated as that option's weight divided by the total of the weights assigned to all options. If every purpose is assigned zero weight, they all receive an equal share of the change in cash flow. | K82: io-model.html
A83: Government Revenue Accounting | B83: Vehicle Subsidy | C83: GRA for Vehicle Subsidy | E83: GRA EV subsidy | F83: 0 | G83: 10 | H83: 1 | I83: weight | J83: **Description:** This setting is one of several "Government Revenue Accounting" control settings that help determine how the government accounts for certain changes in its cash flow (such as increased or decreased tax revenues or subsidy payments). These settings allow for new revenue or spending to be allocated to different purposes by designating shareweights to each accounting purpose. The accounting purposes are: **Regular Spending** increasing this weight means the government will use increased revenue (or account account for increased spending) by increasing (or decreasing) spending on its normal budget (e.g., activities such as defense, education, and administrative expenses). **Budget Deficit** increasing this weight means government will use increased revenue (or account for increased spending) on the deficit, shrinking (or growing) the national debt (with associated implications for interest payments)grow or shrink the national debt (with associated implications for interest payments). **Household Taxes** increasing this weight means the government will use increased revenue (or account for increased spending) to decrease (or increase) taxes on households. A "climate dividend" is considered to be a decrease in household taxes. **Payroll Taxes** increasing this weight means government will use increased revenue (or account for increased spending) to decrease (or increase) payroll taxes. **Corporate Taxes** increasing this weight means government will use increased revenue (or account for increased spending) to decrease (or increase) corporate taxes. // **Guidance for setting values:** This value is set as a weight (1 to 10) for each accounting purpose, in order to indicate how the increased revenue (or spending) from this policy should be allocated among the five revenue accounting options. The share of the change in cash flow allocated to each revenue accounting option is calculated as that option's weight divided by the total of the weights assigned to all options. If every purpose is assigned zero weight, they all receive an equal share of the change in cash flow. | K83: io-model.html
A84: Industry | B84: Buy In-Region Products | C84: Fraction of Imported Industrial Outputs Shifted to In Region Suppliers | D84: Buy In-Region Products | E84: indst buy in region outputs | F84: 0 | G84: 0.5 | H84: 0.01 | I84: % of imports shifted | J84: **Description:** This policy increases the extent to which the selected industry's products are supplied by producers within the modeled region. // **Guidance for setting values:** The lever specifies the percentage of imported products (in the BAU case) that are shifted to domestic suppliers (in the policy case). For example, suppose buyers within the modeled region purchase 60% of their road vehicles from domestic automakers and 40% from automakers outside the modeled region. If this policy lever is applied to the "Road Vehicles" industry with a 50% setting, buyers will obtain 80% of their road vehicles from domestic automakers and 20% from automakers outside the modeled region. // **Implementation Note:** This policy reduces imports. In reality, other regions might retaliate by restricting their own purchases of goods produced by the modeled region. However, the EPS only considers policies within the modeled region, so the Buy In-Region Products policy does not affect export levels (i.e., other countries/regions are assumed not to retaliate).
A85: Industry | B85: Carbon Capture and Sequestration | C85: Industry Sector Fraction of Potential Additional CCS Achieved | D85: Industry CCS | E85: indst CCS | F85: 0 | G85: 1 | H85: 0.01 | I85: % of CO2 captured | J85: **Description:** This policy specifies the fraction of CO2 emissions from industry that is captured and stored, above the amount predicted in the business-as-usual scenario. // **Guidance for setting values:** Very few CCS-equipped industrial facilities exist today, so in a scenario where industry does not transition to clean energy, a value over 20% is likely very optimistic. However, in scenarios in which industry mostly or entirely transitions to clean energy (i.e. due to other policies, such as industrial fuel switching and industrial energy efficiency), CCS settings as high as 100% (to capture the small amount of residual CO2 emissions, such as process CO2 from the cement industry) may be very feasible. | K85: ccs.html#ccs | L85: carbon-capture-and-sequestration.html
A86: Industry | B86: Cement Clinker Substitution | C86: Fraction of Cement Measures Achieved | D86: Cement Clinker Substitution | E86: indst cement measures | F86: 0 | G86: 1 | H86: 0.01 | I86: % of potential achieved | J86: **Description:** This policy reduces CO2 emissions from the cement industry by substituting other inputs, such as fly ash, for a portion of the clinker in cement. // **Guidance for setting values:** If this policy is fully implemented, the share of clinker in cement is reduced to 60%. | K86: industry-ag-main.html#clinker | L86: cement-clinker-substitution.html | M86: International Energy Agency and Cement Sustainability Initiative. 2018. Technology Roadmap: Low-Carbon Transition in the Cement Industry. p41. http://www.iea.org/publications/freepublications/publication/TechnologyRoadmapLowCarbonTransitionintheCementIndustry.pdf
A87: Industry | B87: Cogeneration and Waste Heat Recovery | C87: Fraction of Potential Cogeneration and Waste Heat Recovery Adopted | D87: Cogeneration and Waste Heat Recovery | E87: indst CHP | F87: 0 | G87: 1 | H87: 0.01 | I87: % of potential achieved | J87: **Description:** This policy reduces fuel consumption in the industry sector by increasing the use of cogeneration (also known as combined heat and power) and recovery of waste heat (to perform useful work). // **Guidance for setting values:** If this policy is fully implemented, fuel use is reduced by 7.9% for all industries in 2050. | K87: industry-ag-main.html#cogen | L87: cogeneration-and-waste-heat-recovery.html | M87: Calculated from model data; see the relevant variable(s) in the InputData folder for source information.
A88: Industry | B88: Early Retirement of Industrial Facilities | C88: Fraction of Energy Savings from Early Facility Retirement Achieved | D88: Early Retirement of Industrial Facilities | E88: indst early retirement | F88: 0 | G88: 1 | H88: 0.01 | I88: % of potential achieved | J88: **Description:** This policy reduces fuel consumption in the industry sector by retiring older, inefficient industrial facilities sooner than they otherwise would retire. This policy does not affect demand for industrial products, so it is assumed that any facilities retired under this policy are replaced by new facilities or increased output from existing facilities in the same year. // **Guidance for setting values:** If this policy is fully implemented, fuel use is reduced for most industries between 2% and 9% in 2050. | K88: industry-ag-main.html#early-ret | L88: early-retirement-of-industrial-facilities.html | M88: Calculated from model data; see the relevant variable(s) in the InputData folder for source information.
A89: Industry | B89: Electrification | C89: Fraction of Eligible Industrial Energy Use Shifted to Electricity | D89: Electrification | E89: indst shift to electricity | F89: 0 | G89: 1 | H89: 0.01 | I89: % of fuel shifted | J89: **Description:** This policy reduces greenhouse gas emissions from the selected industry by switching the fuels used by facilities to electricity. Only fuel consumed for energy, not fuel used as a chemical feedstock, is affected by this policy. Biomass and purchased heat (steam) are also unaffected. // **Guidance for setting values:** Over 90% of manufacturers' thermal fuels (excluding feedstocks) are used to generate process heat, including to fuel boilers. Generally, boilers/steam and low-temperature non-boiler heat are easier to electrify than higher-temperature heat. For U.S. manufacturing industries, 21% of heat demand is at low tempratures (below 165°C), 40% is at medium temperatures (165-400°C), and the remainder is at high temperatures (above 400°C). | K89: industry-ag-main.html#fuel-switching | L89: industry-elec-and-hydrogen.html
A90: Industry | B90: Feedstock Shifting | C90: Fraction of Feedstock Shifted | D90: Feedstock Shifting | E90: indst feedstock shifting | F90: 0 | G90: 1 | H90: 0.01 | I90: % of potential achieved | J90: **Description:** This policy shifts the use of fossil-fuel feedstocks to hydrogen. The production method for this new hydrogen demand can be shifted wiht the Fraction of Hydrogen Production Pathways Shifted lever. // **Guidance for setting values (Chemicals):** Approximately 52 percent of natural gas consumed as a chemical feedstock globally goes to producing ammonia and methanol. These pathways can be replaced with green electrolytic hydrogen to eliminate process emissions associated with production. // **Guidance for setting values (Iron & Steel):** Coal is the most significant feedstock used in the steel industry, largely for reducing iron ore in blast furnaces. A transition from the traditional steelmaking route (blast furnace-basic oxygen furnace) to alternatives (like hydrogen-based direct reduced iron with electric arc furnaces) can be represented by pairing this lever with electrification of industrial heat.
A91: Industry | B91: F-Gas Destruction | C91: Fraction of F Gas Destruction Achieved | D91: F-gas Measures | E91: indst f gas destruction | F91: 0 | G91: 1 | H91: 0.01 | I91: % of potential achieved | J91: **Description:** This policy reduces emissions of high-GWP, fluorinated gases (F-gases) from the industry sector by destroying F-gases created as byproducts during the creation of desired products. // **Guidance for setting values:** The production and consumption of f-gases are limited in the U.S. by the American Innovation and Manufacturing (AIM) Act, which is incorporated in the BAU. Therefore, the U.S. model reflects limited additional abatement potential. If this policy is fully implemented, F-gas emissions in 2050 are reduced by 1%. | K91: industry-ag-main.html#avoid-f-gases | L91: avoid-f-gases.html
A92: Industry | B92: F-Gas Eqpt. Maintenance & Retrofits | C92: Fraction of F Gas Inspct Maint Retrofit Achieved | D92: F-gas Measures | E92: indst f gas inspct maint retrofit | F92: 0 | G92: 1 | H92: 0.01 | I92: % of potential achieved | J92: **Description:** This policy reduces emissions of high-GWP, fluorinated gases (F-gases) from the industry sector by reducing leakage and losses through improved inspections, maintenance, and retrofitting of equipment. // **Guidance for setting values:** The production and consumption of f-gases are limited in the U.S. by the American Innovation and Manufacturing (AIM) Act, which is incorporated in the BAU. Therefore, the U.S. model reflects limited additional abatement potential. If this policy is fully implemented, F-gas emissions in 2050 are reduced by less than 1%. | K92: industry-ag-main.html#avoid-f-gases | L92: avoid-f-gases.html
A93: Industry | B93: F-Gas Recovery | C93: Fraction of F Gas Recovery Achieved | D93: F-gas Measures | E93: indst f gas recovery | F93: 0 | G93: 1 | H93: 0.01 | I93: % of potential achieved | J93: **Description:** This policy reduces emissions of high-GWP, fluorinated gases (F-gases) by recovering F-gases from equipment at the end of its service life and destroying or recycling those F-gases. // **Guidance for setting values:** The production and consumption of f-gases are limited in the U.S. by the American Innovation and Manufacturing (AIM) Act, which is incorporated in the BAU. Therefore, the U.S. model reflects limited additional abatement potential. If this policy is fully implemented, F-gas emissions in 2050 are reduced by 2%. | K93: industry-ag-main.html#avoid-f-gases | L93: avoid-f-gases.html
A94: Industry | B94: F-Gas Substitution | C94: Fraction of F Gas Substitution Achieved | D94: F-gas Measures | E94: indst f gas substitution | F94: 0 | G94: 1 | H94: 0.01 | I94: % of potential achieved | J94: **Description:** This policy reduces emissions of high-GWP, fluorinated gases (F-gases) from the industry sector by substituting less-harmful chemicals. // **Guidance for setting values:** The production and consumption of f-gases are limited in the U.S. by the American Innovation and Manufacturing (AIM) Act, which is incorporated in the BAU. Therefore, the U.S. model reflects limited additional abatement potential. If this policy is fully implemented, F-gas emissions in 2050 are reduced by 27%. | K94: industry-ag-main.html#avoid-f-gases | L94: avoid-f-gases.html | M94: Calculated from model data; see the relevant variable(s) in the InputData folder for source information.
A95: Industry | B95: Hydrogen Combustion | C95: Fraction of Eligible Industrial Energy Use Shifted to Hydrogen | D95: Hydrogen Combustion | E95: indst shift to hydrogen | F95: 0 | G95: 1 | H95: 0.01 | I95: % of fuel shifted | J95: **Description:** This policy reduces greenhouse gas emissions from the selected industry by switching the fuels used by facilities to hydrogen combustion. Only fuel consumed for energy, not fuel used as a chemical feedstock, is affected by this policy. Biomass and purchased heat (steam) are also unaffected. // **Guidance for setting values:** Over 90% of manufacturers' thermal fuels (excluding feedstocks) are used to generate process heat, including to fuel boilers. Generally, hydrogen combustion is reserved for high-temperature heat, since it is often simpler and more efficient to directly electrify heat at lower temperatures. For U.S. manufacturing industries, 21% of heat demand is at low tempratures (below 165°C), 40% is at medium temperatures (165-400°C), and the remainder is at high temperatures (above 400°C). | K95: industry-ag-main.html#fuel-switching | L95: industry-elec-and-hydrogen.html
A96: Industry | B96: Improved System Design | C96: Fraction of Installation and System Integration Issues Remedied | D96: Improved System Design | E96: indst system integration | F96: 0 | G96: 1 | H96: 0.01 | I96: % of potential achieved | J96: **Description:** This policy reduces fuel consumption in the industry sector by improving the way components are put together and the way material or energy flows between them. // **Guidance for setting values:** If this policy is fully implemented, fuel use is reduced by 3.6% for all industries in 2050. | K96: industry-ag-main.html#system-integ | L96: improved-system-design.html | M96: Calculated from model data; see the relevant variable(s) in the InputData folder for source information.
A97: Industry | B97: Industry Energy Efficiency Standards | C97: Percentage Improvement in Eqpt Efficiency Standards above BAU | D97: Industry Energy Efficiency Standards | E97: indst efficiency standards | F97: 0 | G97: 0.25 | H97: 0.01 | I97: % reduction in energy use | J97: **Description:** This policy reduces fuel consumption by the selected industry by increasing the efficiency of industrial equipment through stronger standards. The policy setting refers to overall energy use reduction, not the reduction in energy use of newly sold equipment. // **Guidance for setting values:** In 2016, the U.S. Department of Energy developed an industrial energy efficiency potential analysis that suggests the US could double its annual rate of improvement rate through 2030. Extended through 2050, this equates to a maximum potential improvement of 17% by 2050 relative to BAU. | K97: industry-ag-main.html#eff-stds | L97: industry-energy-efficiency-standards.html | M97: U.S. DOE, 2016, Industrial Energy Efficiency Potential Analysis, https://energy.gov/sites/prod/files/2017/04/f34/energy-savings-by-state-industrial-methodology.pdf | N97: U.S. DOE, 2016, Industrial Energy Efficiency Potential Analysis, https://energy.gov/sites/prod/files/2017/04/f34/energy-savings-by-state-industrial-methodology.pdf
A98: Industry | B98: Material Efficiency, Longevity, & Re-Use | C98: Percent Reduction in Nonenergy Nonagriculture Industry Product Demand | D98: Material Efficiency, Longevity, & Re-Use | E98: indst reduce nonenergy product demand | F98: 0 | G98: 1 | H98: 0.01 | I98: % demand reduction | J98: **Description:** // **Cement and Iron & Steel:** This policy reduces demand for the selected materials through techniques such as material-efficient building codes (using modern designs that require less material per unit floor area), requirements for greater building and infrastructure longevity, greater re-use and re-purposing of buildings (rather than tearing down and building new), etc. // **Guidance for setting values:** In "Sustainable Materials Without the Hot Air: Making Buildings, Vehicles and Products Efficiently and with Less New Material," Allwood and Cullen estimate that concrete use could be reduced by up to 40% using optimized molds, and concrete building longevity could be more than doubled to 200 years. Together, these measures might reduce concrete demand by up to 70%, if demand for building floorspace reaches steady state. They estimate that steel use could be reduced by 30% by optimizing designs and controlling the loads they experience during installation and use. If the lifetime of steel products could be doubled, the resulting material reduction could be up to 65%, if sales reach steady state. // **Water and Waste:** This policy reduces demand for water treatment and waste management services through techniques such as water conservation, reduction in disposable packaging, requirements for greater product longevity, greater repair and re-use of products, and increased recycling and composting. // **Guidance for setting values:** The majority of energy use and emissions from the water and waste sector are a result of water treatment, not solid waste management. The USDA reports that agriculture accounts for 80% of U.S. water consumption, and the U.S. EPA reports that "as much as 50 percent of the water we use outdoors is lost due to wind, evaporation, and runoff caused by inefficient irrigation methods and systems." Non-agriculture uses, including lawn irrigation and in-home use, may be able to achieve similar savings through improved practices and fixtures. | L98: material-efficiency-longevity-reuse.html | M98: Allwood and Cullen, "Sustainable Materials Without the Hot Air: Making Buildings, Vehicles and Products Efficiently and with Less New Material" Allwood and Cullen, "Sustainable Materials With Both Eyes Open" - page 185, http://www.withbotheyesopen.com/read.php?c=12 USDA Irrigation & Water Use: https://www.ers.usda.gov/topics/farm-practices-management/irrigation-water-use.aspx and EPA WaterSense Statistics and Facts: https://www.epa.gov/watersense/statistics-and-facts
A99: Industry | B99: Methane Capture | C99: Fraction of Methane Capture Opportunities Achieved | D99: Methane Capture and Destruction | E99: indst methane capture | F99: 0 | G99: 1 | H99: 0.01 | I99: % of potential achieved | J99: **Description:** This policy reduces methane emissions from the selected industry by increasing the capture of methane that is currently being released into the atmosphere (for example, stopping leaks from wellheads, pipes, coal mines, landfills, etc.). **Guidance for setting values:** The U.S. has standards for new and existing equipment covering the oil and gas production and energy pipelines and gas processing industries in the EPS, which are reflected in the BAU. The rules for existing equipment are together expected to reduce emissions by 119 MMT CO2e by the year 2039. | K99: industry-ag-main.html#methane-capture | L99: methane-capture.html
A100: Industry | B100: Methane Destruction | C100: Fraction of Methane Destruction Opportunities Achieved | D100: Methane Capture and Destruction | E100: indst methane destruction | F100: 0 | G100: 1 | H100: 0.01 | I100: % of potential achieved | J100: **Description:** This policy reduces methane emissions from the selected industry by increasing the burning of methane that is currently being released into the atmosphere (i.e. flaring instead of venting/leaking). **Guidance for setting values:** The U.S. has standards for new and existing equipment covering the oil and gas production and energy pipelines and gas processing industries in the EPS, which are reflected in the BAU. The rules for existing equipment are together expected to reduce emissions by 119 MMT CO2e by the year 2039. | K100: industry-ag-main.html#methane-destr | L100: methane-destruction.html
...

Sheet PolicyLevers
A1: Sector | B1: Short Name | C1: Vensim Variable Name | D1: Subscript 1 Value | E1: Subscript 2 Value | F1: Subscript 1 Display Name | G1: Subscript 2 Display Name | H1: Policy ID Number | I1: Include in Web App | J1: Policy Group | K1: Policy Schedule Subscript | L1: Min Slider Value | M1: Max Slider Value | N1: Slider Step Size | O1: Units | P1: Text for Pop-Over Panel Description | Q1: URL for "How the model handles this policy" links | R1: URL for "How to design this policy well" links | S1: Short Description | T1: Policy Schedule Graph Variable
A2: =IF(ISBLANK(INDEX('Policy Characteristics'!A:A,MATCH($C2,'Policy Characteristics'!$C:$C,0))),"",INDEX('Policy Characteristics'!A:A,MATCH($C2,'Policy Characteristics'!$C:$C,0))) -> Buildings and Appliances | B2: =IF(ISBLANK(INDEX('Policy Characteristics'!B:B,MATCH($C2,'Policy Characteristics'!$C:$C,0))),"",INDEX('Policy Characteristics'!B:B,MATCH($C2,'Policy Characteristics'!$C:$C,0))) -> Building Component Electrification | C2: Fraction of New Bldg Components Shifted to Other Fuels | D2: heating | E2: urban residential | F2: Heating | G2: Urban Residential | H2: 435 | I2: Yes | J2: =IF(ISBLANK(INDEX('Policy Characteristics'!D:D,MATCH($C2,'Policy Characteristics'!$C:$C,0))),"",INDEX('Policy Characteristics'!D:D,MATCH($C2,'Policy Characteristics'!$C:$C,0))) -> Building Component Electrification | K2: =IF(ISBLANK(INDEX('Policy Characteristics'!E:E,MATCH($C2,'Policy Characteristics'!$C:$C,0))),"",INDEX('Policy Characteristics'!E:E,MATCH($C2,'Policy Characteristics'!$C:$C,0))) -> bldgs new component fuel shifting | L2: =IF(ISBLANK(INDEX('Policy Characteristics'!F:F,MATCH($C2,'Policy Characteristics'!$C:$C,0))),"",INDEX('Policy Characteristics'!F:F,MATCH($C2,'Policy Characteristics'!$C:$C,0))) -> 0 | M2: =IF(ISBLANK(INDEX('Policy Characteristics'!G:G,MATCH($C2,'Policy Characteristics'!$C:$C,0))),"",INDEX('Policy Characteristics'!G:G,MATCH($C2,'Policy Characteristics'!$C:$C,0))) -> 1 | N2: =IF(ISBLANK(INDEX('Policy Characteristics'!H:H,MATCH($C2,'Policy Characteristics'!$C:$C,0))),"",INDEX('Policy Characteristics'!H:H,MATCH($C2,'Policy Characteristics'!$C:$C,0))) -> 0.01 | O2: =IF(ISBLANK(INDEX('Policy Characteristics'!I:I,MATCH($C2,'Policy Characteristics'!$C:$C,0))),"",INDEX('Policy Characteristics'!I:I,MATCH($C2,'Policy Characteristics'!$C:$C,0))) -> % of newly sold non-electric building components | P2: =IF(ISBLANK(INDEX('Policy Characteristics'!J:J,MATCH($C2,'Policy Characteristics'!$C:$C,0))),"",INDEX('Policy Characteristics'!J:J,MATCH($C2,'Policy Characteristics'!$C:$C,0))) -> **Description:** This policy replaces the specified fraction of newly sold non-electric building components of the selected type(s) in buildings of the selected type(s) with electricity-using components. | Q2: =IF(ISBLANK(INDEX('Policy Characteristics'!K:K,MATCH($C2,'Policy Characteristics'!$C:$C,0))),"",INDEX('Policy Characteristics'!K:K,MATCH($C2,'Policy Characteristics'!$C:$C,0))) -> buildings-sector-main.html#component-elec | R2: =IF(ISBLANK(INDEX('Policy Characteristics'!L:L,MATCH($C2,'Policy Characteristics'!$C:$C,0))),"",INDEX('Policy Characteristics'!L:L,MATCH($C2,'Policy Characteristics'!$C:$C,0))) -> building-component-electrification.html | S2: Increase the percentage of new building equipment sold that is electric.
A3: =IF(ISBLANK(INDEX('Policy Characteristics'!A:A,MATCH($C3,'Policy Characteristics'!$C:$C,0))),"",INDEX('Policy Characteristics'!A:A,MATCH($C3,'Policy Characteristics'!$C:$C,0))) -> Buildings and Appliances | B3: =IF(ISBLANK(INDEX('Policy Characteristics'!B:B,MATCH($C3,'Policy Characteristics'!$C:$C,0))),"",INDEX('Policy Characteristics'!B:B,MATCH($C3,'Policy Characteristics'!$C:$C,0))) -> Building Component Electrification | C3: Fraction of New Bldg Components Shifted to Other Fuels | D3: cooling and ventilation | E3: urban residential | F3: Cooling and Ventilation | G3: Urban Residential | H3: 436 | I3: No | J3: =IF(ISBLANK(INDEX('Policy Characteristics'!D:D,MATCH($C3,'Policy Characteristics'!$C:$C,0))),"",INDEX('Policy Characteristics'!D:D,MATCH($C3,'Policy Characteristics'!$C:$C,0))) -> Building Component Electrification | K3: =IF(ISBLANK(INDEX('Policy Characteristics'!E:E,MATCH($C3,'Policy Characteristics'!$C:$C,0))),"",INDEX('Policy Characteristics'!E:E,MATCH($C3,'Policy Characteristics'!$C:$C,0))) -> bldgs new component fuel shifting | L3: =IF(ISBLANK(INDEX('Policy Characteristics'!F:F,MATCH($C3,'Policy Characteristics'!$C:$C,0))),"",INDEX('Policy Characteristics'!F:F,MATCH($C3,'Policy Characteristics'!$C:$C,0))) -> 0 | M3: =IF(ISBLANK(INDEX('Policy Characteristics'!G:G,MATCH($C3,'Policy Characteristics'!$C:$C,0))),"",INDEX('Policy Characteristics'!G:G,MATCH($C3,'Policy Characteristics'!$C:$C,0))) -> 1 | N3: =IF(ISBLANK(INDEX('Policy Characteristics'!H:H,MATCH($C3,'Policy Characteristics'!$C:$C,0))),"",INDEX('Policy Characteristics'!H:H,MATCH($C3,'Policy Characteristics'!$C:$C,0))) -> 0.01 | O3: =IF(ISBLANK(INDEX('Policy Characteristics'!I:I,MATCH($C3,'Policy Characteristics'!$C:$C,0))),"",INDEX('Policy Characteristics'!I:I,MATCH($C3,'Policy Characteristics'!$C:$C,0))) -> % of newly sold non-electric building components | P3: =IF(ISBLANK(INDEX('Policy Characteristics'!J:J,MATCH($C3,'Policy Characteristics'!$C:$C,0))),"",INDEX('Policy Characteristics'!J:J,MATCH($C3,'Policy Characteristics'!$C:$C,0))) -> **Description:** This policy replaces the specified fraction of newly sold non-electric building components of the selected type(s) in buildings of the selected type(s) with electricity-using components. | Q3: =IF(ISBLANK(INDEX('Policy Characteristics'!K:K,MATCH($C3,'Policy Characteristics'!$C:$C,0))),"",INDEX('Policy Characteristics'!K:K,MATCH($C3,'Policy Characteristics'!$C:$C,0))) -> buildings-sector-main.html#component-elec | R3: =IF(ISBLANK(INDEX('Policy Characteristics'!L:L,MATCH($C3,'Policy Characteristics'!$C:$C,0))),"",INDEX('Policy Characteristics'!L:L,MATCH($C3,'Policy Characteristics'!$C:$C,0))) -> building-component-electrification.html
A4: =IF(ISBLANK(INDEX('Policy Characteristics'!A:A,MATCH($C4,'Policy Characteristics'!$C:$C,0))),"",INDEX('Policy Characteristics'!A:A,MATCH($C4,'Policy Characteristics'!$C:$C,0))) -> Buildings and Appliances | B4: =IF(ISBLANK(INDEX('Policy Characteristics'!B:B,MATCH($C4,'Policy Characteristics'!$C:$C,0))),"",INDEX('Policy Characteristics'!B:B,MATCH($C4,'Policy Characteristics'!$C:$C,0))) -> Building Component Electrification | C4: Fraction of New Bldg Components Shifted to Other Fuels | D4: lighting | E4: urban residential | F4: Lighting | G4: Urban Residential | H4: 437 | I4: No | J4: =IF(ISBLANK(INDEX('Policy Characteristics'!D:D,MATCH($C4,'Policy Characteristics'!$C:$C,0))),"",INDEX('Policy Characteristics'!D:D,MATCH($C4,'Policy Characteristics'!$C:$C,0))) -> Building Component Electrification | K4: =IF(ISBLANK(INDEX('Policy Characteristics'!E:E,MATCH($C4,'Policy Characteristics'!$C:$C,0))),"",INDEX('Policy Characteristics'!E:E,MATCH($C4,'Policy Characteristics'!$C:$C,0))) -> bldgs new component fuel shifting | L4: =IF(ISBLANK(INDEX('Policy Characteristics'!F:F,MATCH($C4,'Policy Characteristics'!$C:$C,0))),"",INDEX('Policy Characteristics'!F:F,MATCH($C4,'Policy Characteristics'!$C:$C,0))) -> 0 | M4: =IF(ISBLANK(INDEX('Policy Characteristics'!G:G,MATCH($C4,'Policy Characteristics'!$C:$C,0))),"",INDEX('Policy Characteristics'!G:G,MATCH($C4,'Policy Characteristics'!$C:$C,0))) -> 1 | N4: =IF(ISBLANK(INDEX('Policy Characteristics'!H:H,MATCH($C4,'Policy Characteristics'!$C:$C,0))),"",INDEX('Policy Characteristics'!H:H,MATCH($C4,'Policy Characteristics'!$C:$C,0))) -> 0.01 | O4: =IF(ISBLANK(INDEX('Policy Characteristics'!I:I,MATCH($C4,'Policy Characteristics'!$C:$C,0))),"",INDEX('Policy Characteristics'!I:I,MATCH($C4,'Policy Characteristics'!$C:$C,0))) -> % of newly sold non-electric building components | P4: =IF(ISBLANK(INDEX('Policy Characteristics'!J:J,MATCH($C4,'Policy Characteristics'!$C:$C,0))),"",INDEX('Policy Characteristics'!J:J,MATCH($C4,'Policy Characteristics'!$C:$C,0))) -> **Description:** This policy replaces the specified fraction of newly sold non-electric building components of the selected type(s) in buildings of the selected type(s) with electricity-using components. | Q4: =IF(ISBLANK(INDEX('Policy Characteristics'!K:K,MATCH($C4,'Policy Characteristics'!$C:$C,0))),"",INDEX('Policy Characteristics'!K:K,MATCH($C4,'Policy Characteristics'!$C:$C,0))) -> buildings-sector-main.html#component-elec | R4: =IF(ISBLANK(INDEX('Policy Characteristics'!L:L,MATCH($C4,'Policy Characteristics'!$C:$C,0))),"",INDEX('Policy Characteristics'!L:L,MATCH($C4,'Policy Characteristics'!$C:$C,0))) -> building-component-electrification.html
A5: =IF(ISBLANK(INDEX('Policy Characteristics'!A:A,MATCH($C5,'Policy Characteristics'!$C:$C,0))),"",INDEX('Policy Characteristics'!A:A,MATCH($C5,'Policy Characteristics'!$C:$C,0))) -> Buildings and Appliances | B5: =IF(ISBLANK(INDEX('Policy Characteristics'!B:B,MATCH($C5,'Policy Characteristics'!$C:$C,0))),"",INDEX('Policy Characteristics'!B:B,MATCH($C5,'Policy Characteristics'!$C:$C,0))) -> Building Component Electrification | C5: Fraction of New Bldg Components Shifted to Other Fuels | D5: appliances | E5: urban residential | F5: Appliances | G5: Urban Residential | H5: 438 | I5: Yes | J5: =IF(ISBLANK(INDEX('Policy Characteristics'!D:D,MATCH($C5,'Policy Characteristics'!$C:$C,0))),"",INDEX('Policy Characteristics'!D:D,MATCH($C5,'Policy Characteristics'!$C:$C,0))) -> Building Component Electrification | K5: =IF(ISBLANK(INDEX('Policy Characteristics'!E:E,MATCH($C5,'Policy Characteristics'!$C:$C,0))),"",INDEX('Policy Characteristics'!E:E,MATCH($C5,'Policy Characteristics'!$C:$C,0))) -> bldgs new component fuel shifting | L5: =IF(ISBLANK(INDEX('Policy Characteristics'!F:F,MATCH($C5,'Policy Characteristics'!$C:$C,0))),"",INDEX('Policy Characteristics'!F:F,MATCH($C5,'Policy Characteristics'!$C:$C,0))) -> 0 | M5: =IF(ISBLANK(INDEX('Policy Characteristics'!G:G,MATCH($C5,'Policy Characteristics'!$C:$C,0))),"",INDEX('Policy Characteristics'!G:G,MATCH($C5,'Policy Characteristics'!$C:$C,0))) -> 1 | N5: =IF(ISBLANK(INDEX('Policy Characteristics'!H:H,MATCH($C5,'Policy Characteristics'!$C:$C,0))),"",INDEX('Policy Characteristics'!H:H,MATCH($C5,'Policy Characteristics'!$C:$C,0))) -> 0.01 | O5: =IF(ISBLANK(INDEX('Policy Characteristics'!I:I,MATCH($C5,'Policy Characteristics'!$C:$C,0))),"",INDEX('Policy Characteristics'!I:I,MATCH($C5,'Policy Characteristics'!$C:$C,0))) -> % of newly sold non-electric building components | P5: =IF(ISBLANK(INDEX('Policy Characteristics'!J:J,MATCH($C5,'Policy Characteristics'!$C:$C,0))),"",INDEX('Policy Characteristics'!J:J,MATCH($C5,'Policy Characteristics'!$C:$C,0))) -> **Description:** This policy replaces the specified fraction of newly sold non-electric building components of the selected type(s) in buildings of the selected type(s) with electricity-using components. | Q5: =IF(ISBLANK(INDEX('Policy Characteristics'!K:K,MATCH($C5,'Policy Characteristics'!$C:$C,0))),"",INDEX('Policy Characteristics'!K:K,MATCH($C5,'Policy Characteristics'!$C:$C,0))) -> buildings-sector-main.html#component-elec | R5: =IF(ISBLANK(INDEX('Policy Characteristics'!L:L,MATCH($C5,'Policy Characteristics'!$C:$C,0))),"",INDEX('Policy Characteristics'!L:L,MATCH($C5,'Policy Characteristics'!$C:$C,0))) -> building-component-electrification.html
A6: =IF(ISBLANK(INDEX('Policy Characteristics'!A:A,MATCH($C6,'Policy Characteristics'!$C:$C,0))),"",INDEX('Policy Characteristics'!A:A,MATCH($C6,'Policy Characteristics'!$C:$C,0))) -> Buildings and Appliances | B6: =IF(ISBLANK(INDEX('Policy Characteristics'!B:B,MATCH($C6,'Policy Characteristics'!$C:$C,0))),"",INDEX('Policy Characteristics'!B:B,MATCH($C6,'Policy Characteristics'!$C:$C,0))) -> Building Component Electrification | C6: Fraction of New Bldg Components Shifted to Other Fuels | D6: other component | E6: urban residential | F6: Other Components | G6: Urban Residential | H6: 439 | I6: Yes | J6: =IF(ISBLANK(INDEX('Policy Characteristics'!D:D,MATCH($C6,'Policy Characteristics'!$C:$C,0))),"",INDEX('Policy Characteristics'!D:D,MATCH($C6,'Policy Characteristics'!$C:$C,0))) -> Building Component Electrification | K6: =IF(ISBLANK(INDEX('Policy Characteristics'!E:E,MATCH($C6,'Policy Characteristics'!$C:$C,0))),"",INDEX('Policy Characteristics'!E:E,MATCH($C6,'Policy Characteristics'!$C:$C,0))) -> bldgs new component fuel shifting | L6: =IF(ISBLANK(INDEX('Policy Characteristics'!F:F,MATCH($C6,'Policy Characteristics'!$C:$C,0))),"",INDEX('Policy Characteristics'!F:F,MATCH($C6,'Policy Characteristics'!$C:$C,0))) -> 0 | M6: =IF(ISBLANK(INDEX('Policy Characteristics'!G:G,MATCH($C6,'Policy Characteristics'!$C:$C,0))),"",INDEX('Policy Characteristics'!G:G,MATCH($C6,'Policy Characteristics'!$C:$C,0))) -> 1 | N6: =IF(ISBLANK(INDEX('Policy Characteristics'!H:H,MATCH($C6,'Policy Characteristics'!$C:$C,0))),"",INDEX('Policy Characteristics'!H:H,MATCH($C6,'Policy Characteristics'!$C:$C,0))) -> 0.01 | O6: =IF(ISBLANK(INDEX('Policy Characteristics'!I:I,MATCH($C6,'Policy Characteristics'!$C:$C,0))),"",INDEX('Policy Characteristics'!I:I,MATCH($C6,'Policy Characteristics'!$C:$C,0))) -> % of newly sold non-electric building components | P6: =IF(ISBLANK(INDEX('Policy Characteristics'!J:J,MATCH($C6,'Policy Characteristics'!$C:$C,0))),"",INDEX('Policy Characteristics'!J:J,MATCH($C6,'Policy Characteristics'!$C:$C,0))) -> **Description:** This policy replaces the specified fraction of newly sold non-electric building components of the selected type(s) in buildings of the selected type(s) with electricity-using components. | Q6: =IF(ISBLANK(INDEX('Policy Characteristics'!K:K,MATCH($C6,'Policy Characteristics'!$C:$C,0))),"",INDEX('Policy Characteristics'!K:K,MATCH($C6,'Policy Characteristics'!$C:$C,0))) -> buildings-sector-main.html#component-elec | R6: =IF(ISBLANK(INDEX('Policy Characteristics'!L:L,MATCH($C6,'Policy Characteristics'!$C:$C,0))),"",INDEX('Policy Characteristics'!L:L,MATCH($C6,'Policy Characteristics'!$C:$C,0))) -> building-component-electrification.html
A7: =IF(ISBLANK(INDEX('Policy Characteristics'!A:A,MATCH($C7,'Policy Characteristics'!$C:$C,0))),"",INDEX('Policy Characteristics'!A:A,MATCH($C7,'Policy Characteristics'!$C:$C,0))) -> Buildings and Appliances | B7: =IF(ISBLANK(INDEX('Policy Characteristics'!B:B,MATCH($C7,'Policy Characteristics'!$C:$C,0))),"",INDEX('Policy Characteristics'!B:B,MATCH($C7,'Policy Characteristics'!$C:$C,0))) -> Building Component Electrification | C7: Fraction of New Bldg Components Shifted to Other Fuels | D7: heating | E7: rural residential | F7: Heating | G7: Rural Residential | H7: 440 | I7: Yes | J7: =IF(ISBLANK(INDEX('Policy Characteristics'!D:D,MATCH($C7,'Policy Characteristics'!$C:$C,0))),"",INDEX('Policy Characteristics'!D:D,MATCH($C7,'Policy Characteristics'!$C:$C,0))) -> Building Component Electrification | K7: =IF(ISBLANK(INDEX('Policy Characteristics'!E:E,MATCH($C7,'Policy Characteristics'!$C:$C,0))),"",INDEX('Policy Characteristics'!E:E,MATCH($C7,'Policy Characteristics'!$C:$C,0))) -> bldgs new component fuel shifting | L7: =IF(ISBLANK(INDEX('Policy Characteristics'!F:F,MATCH($C7,'Policy Characteristics'!$C:$C,0))),"",INDEX('Policy Characteristics'!F:F,MATCH($C7,'Policy Characteristics'!$C:$C,0))) -> 0 | M7: =IF(ISBLANK(INDEX('Policy Characteristics'!G:G,MATCH($C7,'Policy Characteristics'!$C:$C,0))),"",INDEX('Policy Characteristics'!G:G,MATCH($C7,'Policy Characteristics'!$C:$C,0))) -> 1 | N7: =IF(ISBLANK(INDEX('Policy Characteristics'!H:H,MATCH($C7,'Policy Characteristics'!$C:$C,0))),"",INDEX('Policy Characteristics'!H:H,MATCH($C7,'Policy Characteristics'!$C:$C,0))) -> 0.01 | O7: =IF(ISBLANK(INDEX('Policy Characteristics'!I:I,MATCH($C7,'Policy Characteristics'!$C:$C,0))),"",INDEX('Policy Characteristics'!I:I,MATCH($C7,'Policy Characteristics'!$C:$C,0))) -> % of newly sold non-electric building components | P7: =IF(ISBLANK(INDEX('Policy Characteristics'!J:J,MATCH($C7,'Policy Characteristics'!$C:$C,0))),"",INDEX('Policy Characteristics'!J:J,MATCH($C7,'Policy Characteristics'!$C:$C,0))) -> **Description:** This policy replaces the specified fraction of newly sold non-electric building components of the selected type(s) in buildings of the selected type(s) with electricity-using components. | Q7: =IF(ISBLANK(INDEX('Policy Characteristics'!K:K,MATCH($C7,'Policy Characteristics'!$C:$C,0))),"",INDEX('Policy Characteristics'!K:K,MATCH($C7,'Policy Characteristics'!$C:$C,0))) -> buildings-sector-main.html#component-elec | R7: =IF(ISBLANK(INDEX('Policy Characteristics'!L:L,MATCH($C7,'Policy Characteristics'!$C:$C,0))),"",INDEX('Policy Characteristics'!L:L,MATCH($C7,'Policy Characteristics'!$C:$C,0))) -> building-component-electrification.html
A8: =IF(ISBLANK(INDEX('Policy Characteristics'!A:A,MATCH($C8,'Policy Characteristics'!$C:$C,0))),"",INDEX('Policy Characteristics'!A:A,MATCH($C8,'Policy Characteristics'!$C:$C,0))) -> Buildings and Appliances | B8: =IF(ISBLANK(INDEX('Policy Characteristics'!B:B,MATCH($C8,'Policy Characteristics'!$C:$C,0))),"",INDEX('Policy Characteristics'!B:B,MATCH($C8,'Policy Characteristics'!$C:$C,0))) -> Building Component Electrification | C8: Fraction of New Bldg Components Shifted to Other Fuels | D8: cooling and ventilation | E8: rural residential | F8: Cooling and Ventilation | G8: Rural Residential | H8: 441 | I8: No | J8: =IF(ISBLANK(INDEX('Policy Characteristics'!D:D,MATCH($C8,'Policy Characteristics'!$C:$C,0))),"",INDEX('Policy Characteristics'!D:D,MATCH($C8,'Policy Characteristics'!$C:$C,0))) -> Building Component Electrification | K8: =IF(ISBLANK(INDEX('Policy Characteristics'!E:E,MATCH($C8,'Policy Characteristics'!$C:$C,0))),"",INDEX('Policy Characteristics'!E:E,MATCH($C8,'Policy Characteristics'!$C:$C,0))) -> bldgs new component fuel shifting | L8: =IF(ISBLANK(INDEX('Policy Characteristics'!F:F,MATCH($C8,'Policy Characteristics'!$C:$C,0))),"",INDEX('Policy Characteristics'!F:F,MATCH($C8,'Policy Characteristics'!$C:$C,0))) -> 0 | M8: =IF(ISBLANK(INDEX('Policy Characteristics'!G:G,MATCH($C8,'Policy Characteristics'!$C:$C,0))),"",INDEX('Policy Characteristics'!G:G,MATCH($C8,'Policy Characteristics'!$C:$C,0))) -> 1 | N8: =IF(ISBLANK(INDEX('Policy Characteristics'!H:H,MATCH($C8,'Policy Characteristics'!$C:$C,0))),"",INDEX('Policy Characteristics'!H:H,MATCH($C8,'Policy Characteristics'!$C:$C,0))) -> 0.01 | O8: =IF(ISBLANK(INDEX('Policy Characteristics'!I:I,MATCH($C8,'Policy Characteristics'!$C:$C,0))),"",INDEX('Policy Characteristics'!I:I,MATCH($C8,'Policy Characteristics'!$C:$C,0))) -> % of newly sold non-electric building components | P8: =IF(ISBLANK(INDEX('Policy Characteristics'!J:J,MATCH($C8,'Policy Characteristics'!$C:$C,0))),"",INDEX('Policy Characteristics'!J:J,MATCH($C8,'Policy Characteristics'!$C:$C,0))) -> **Description:** This policy replaces the specified fraction of newly sold non-electric building components of the selected type(s) in buildings of the selected type(s) with electricity-using components. | Q8: =IF(ISBLANK(INDEX('Policy Characteristics'!K:K,MATCH($C8,'Policy Characteristics'!$C:$C,0))),"",INDEX('Policy Characteristics'!K:K,MATCH($C8,'Policy Characteristics'!$C:$C,0))) -> buildings-sector-main.html#component-elec | R8: =IF(ISBLANK(INDEX('Policy Characteristics'!L:L,MATCH($C8,'Policy Characteristics'!$C:$C,0))),"",INDEX('Policy Characteristics'!L:L,MATCH($C8,'Policy Characteristics'!$C:$C,0))) -> building-component-electrification.html
A9: =IF(ISBLANK(INDEX('Policy Characteristics'!A:A,MATCH($C9,'Policy Characteristics'!$C:$C,0))),"",INDEX('Policy Characteristics'!A:A,MATCH($C9,'Policy Characteristics'!$C:$C,0))) -> Buildings and Appliances | B9: =IF(ISBLANK(INDEX('Policy Characteristics'!B:B,MATCH($C9,'Policy Characteristics'!$C:$C,0))),"",INDEX('Policy Characteristics'!B:B,MATCH($C9,'Policy Characteristics'!$C:$C,0))) -> Building Component Electrification | C9: Fraction of New Bldg Components Shifted to Other Fuels | D9: lighting | E9: rural residential | F9: Lighting | G9: Rural Residential | H9: 442 | I9: No | J9: =IF(ISBLANK(INDEX('Policy Characteristics'!D:D,MATCH($C9,'Policy Characteristics'!$C:$C,0))),"",INDEX('Policy Characteristics'!D:D,MATCH($C9,'Policy Characteristics'!$C:$C,0))) -> Building Component Electrification | K9: =IF(ISBLANK(INDEX('Policy Characteristics'!E:E,MATCH($C9,'Policy Characteristics'!$C:$C,0))),"",INDEX('Policy Characteristics'!E:E,MATCH($C9,'Policy Characteristics'!$C:$C,0))) -> bldgs new component fuel shifting | L9: =IF(ISBLANK(INDEX('Policy Characteristics'!F:F,MATCH($C9,'Policy Characteristics'!$C:$C,0))),"",INDEX('Policy Characteristics'!F:F,MATCH($C9,'Policy Characteristics'!$C:$C,0))) -> 0 | M9: =IF(ISBLANK(INDEX('Policy Characteristics'!G:G,MATCH($C9,'Policy Characteristics'!$C:$C,0))),"",INDEX('Policy Characteristics'!G:G,MATCH($C9,'Policy Characteristics'!$C:$C,0))) -> 1 | N9: =IF(ISBLANK(INDEX('Policy Characteristics'!H:H,MATCH($C9,'Policy Characteristics'!$C:$C,0))),"",INDEX('Policy Characteristics'!H:H,MATCH($C9,'Policy Characteristics'!$C:$C,0))) -> 0.01 | O9: =IF(ISBLANK(INDEX('Policy Characteristics'!I:I,MATCH($C9,'Policy Characteristics'!$C:$C,0))),"",INDEX('Policy Characteristics'!I:I,MATCH($C9,'Policy Characteristics'!$C:$C,0))) -> % of newly sold non-electric building components | P9: =IF(ISBLANK(INDEX('Policy Characteristics'!J:J,MATCH($C9,'Policy Characteristics'!$C:$C,0))),"",INDEX('Policy Characteristics'!J:J,MATCH($C9,'Policy Characteristics'!$C:$C,0))) -> **Description:** This policy replaces the specified fraction of newly sold non-electric building components of the selected type(s) in buildings of the selected type(s) with electricity-using components. | Q9: =IF(ISBLANK(INDEX('Policy Characteristics'!K:K,MATCH($C9,'Policy Characteristics'!$C:$C,0))),"",INDEX('Policy Characteristics'!K:K,MATCH($C9,'Policy Characteristics'!$C:$C,0))) -> buildings-sector-main.html#component-elec | R9: =IF(ISBLANK(INDEX('Policy Characteristics'!L:L,MATCH($C9,'Policy Characteristics'!$C:$C,0))),"",INDEX('Policy Characteristics'!L:L,MATCH($C9,'Policy Characteristics'!$C:$C,0))) -> building-component-electrification.html
A10: =IF(ISBLANK(INDEX('Policy Characteristics'!A:A,MATCH($C10,'Policy Characteristics'!$C:$C,0))),"",INDEX('Policy Characteristics'!A:A,MATCH($C10,'Policy Characteristics'!$C:$C,0))) -> Buildings and Appliances | B10: =IF(ISBLANK(INDEX('Policy Characteristics'!B:B,MATCH($C10,'Policy Characteristics'!$C:$C,0))),"",INDEX('Policy Characteristics'!B:B,MATCH($C10,'Policy Characteristics'!$C:$C,0))) -> Building Component Electrification | C10: Fraction of New Bldg Components Shifted to Other Fuels | D10: appliances | E10: rural residential | F10: Appliances | G10: Rural Residential | H10: 443 | I10: Yes | J10: =IF(ISBLANK(INDEX('Policy Characteristics'!D:D,MATCH($C10,'Policy Characteristics'!$C:$C,0))),"",INDEX('Policy Characteristics'!D:D,MATCH($C10,'Policy Characteristics'!$C:$C,0))) -> Building Component Electrification | K10: =IF(ISBLANK(INDEX('Policy Characteristics'!E:E,MATCH($C10,'Policy Characteristics'!$C:$C,0))),"",INDEX('Policy Characteristics'!E:E,MATCH($C10,'Policy Characteristics'!$C:$C,0))) -> bldgs new component fuel shifting | L10: =IF(ISBLANK(INDEX('Policy Characteristics'!F:F,MATCH($C10,'Policy Characteristics'!$C:$C,0))),"",INDEX('Policy Characteristics'!F:F,MATCH($C10,'Policy Characteristics'!$C:$C,0))) -> 0 | M10: =IF(ISBLANK(INDEX('Policy Characteristics'!G:G,MATCH($C10,'Policy Characteristics'!$C:$C,0))),"",INDEX('Policy Characteristics'!G:G,MATCH($C10,'Policy Characteristics'!$C:$C,0))) -> 1 | N10: =IF(ISBLANK(INDEX('Policy Characteristics'!H:H,MATCH($C10,'Policy Characteristics'!$C:$C,0))),"",INDEX('Policy Characteristics'!H:H,MATCH($C10,'Policy Characteristics'!$C:$C,0))) -> 0.01 | O10: =IF(ISBLANK(INDEX('Policy Characteristics'!I:I,MATCH($C10,'Policy Characteristics'!$C:$C,0))),"",INDEX('Policy Characteristics'!I:I,MATCH($C10,'Policy Characteristics'!$C:$C,0))) -> % of newly sold non-electric building components | P10: =IF(ISBLANK(INDEX('Policy Characteristics'!J:J,MATCH($C10,'Policy Characteristics'!$C:$C,0))),"",INDEX('Policy Characteristics'!J:J,MATCH($C10,'Policy Characteristics'!$C:$C,0))) -> **Description:** This policy replaces the specified fraction of newly sold non-electric building components of the selected type(s) in buildings of the selected type(s) with electricity-using components. | Q10: =IF(ISBLANK(INDEX('Policy Characteristics'!K:K,MATCH($C10,'Policy Characteristics'!$C:$C,0))),"",INDEX('Policy Characteristics'!K:K,MATCH($C10,'Policy Characteristics'!$C:$C,0))) -> buildings-sector-main.html#component-elec | R10: =IF(ISBLANK(INDEX('Policy Characteristics'!L:L,MATCH($C10,'Policy Characteristics'!$C:$C,0))),"",INDEX('Policy Characteristics'!L:L,MATCH($C10,'Policy Characteristics'!$C:$C,0))) -> building-component-electrification.html
A11: =IF(ISBLANK(INDEX('Policy Characteristics'!A:A,MATCH($C11,'Policy Characteristics'!$C:$C,0))),"",INDEX('Policy Characteristics'!A:A,MATCH($C11,'Policy Characteristics'!$C:$C,0))) -> Buildings and Appliances | B11: =IF(ISBLANK(INDEX('Policy Characteristics'!B:B,MATCH($C11,'Policy Characteristics'!$C:$C,0))),"",INDEX('Policy Characteristics'!B:B,MATCH($C11,'Policy Characteristics'!$C:$C,0))) -> Building Component Electrification | C11: Fraction of New Bldg Components Shifted to Other Fuels | D11: other component | E11: rural residential | F11: Other Components | G11: Rural Residential | H11: 444 | I11: Yes | J11: =IF(ISBLANK(INDEX('Policy Characteristics'!D:D,MATCH($C11,'Policy Characteristics'!$C:$C,0))),"",INDEX('Policy Characteristics'!D:D,MATCH($C11,'Policy Characteristics'!$C:$C,0))) -> Building Component Electrification | K11: =IF(ISBLANK(INDEX('Policy Characteristics'!E:E,MATCH($C11,'Policy Characteristics'!$C:$C,0))),"",INDEX('Policy Characteristics'!E:E,MATCH($C11,'Policy Characteristics'!$C:$C,0))) -> bldgs new component fuel shifting | L11: =IF(ISBLANK(INDEX('Policy Characteristics'!F:F,MATCH($C11,'Policy Characteristics'!$C:$C,0))),"",INDEX('Policy Characteristics'!F:F,MATCH($C11,'Policy Characteristics'!$C:$C,0))) -> 0 | M11: =IF(ISBLANK(INDEX('Policy Characteristics'!G:G,MATCH($C11,'Policy Characteristics'!$C:$C,0))),"",INDEX('Policy Characteristics'!G:G,MATCH($C11,'Policy Characteristics'!$C:$C,0))) -> 1 | N11: =IF(ISBLANK(INDEX('Policy Characteristics'!H:H,MATCH($C11,'Policy Characteristics'!$C:$C,0))),"",INDEX('Policy Characteristics'!H:H,MATCH($C11,'Policy Characteristics'!$C:$C,0))) -> 0.01 | O11: =IF(ISBLANK(INDEX('Policy Characteristics'!I:I,MATCH($C11,'Policy Characteristics'!$C:$C,0))),"",INDEX('Policy Characteristics'!I:I,MATCH($C11,'Policy Characteristics'!$C:$C,0))) -> % of newly sold non-electric building components | P11: =IF(ISBLANK(INDEX('Policy Characteristics'!J:J,MATCH($C11,'Policy Characteristics'!$C:$C,0))),"",INDEX('Policy Characteristics'!J:J,MATCH($C11,'Policy Characteristics'!$C:$C,0))) -> **Description:** This policy replaces the specified fraction of newly sold non-electric building components of the selected type(s) in buildings of the selected type(s) with electricity-using components. | Q11: =IF(ISBLANK(INDEX('Policy Characteristics'!K:K,MATCH($C11,'Policy Characteristics'!$C:$C,0))),"",INDEX('Policy Characteristics'!K:K,MATCH($C11,'Policy Characteristics'!$C:$C,0))) -> buildings-sector-main.html#component-elec | R11: =IF(ISBLANK(INDEX('Policy Characteristics'!L:L,MATCH($C11,'Policy Characteristics'!$C:$C,0))),"",INDEX('Policy Characteristics'!L:L,MATCH($C11,'Policy Characteristics'!$C:$C,0))) -> building-component-electrification.html
A12: =IF(ISBLANK(INDEX('Policy Characteristics'!A:A,MATCH($C12,'Policy Characteristics'!$C:$C,0))),"",INDEX('Policy Characteristics'!A:A,MATCH($C12,'Policy Characteristics'!$C:$C,0))) -> Buildings and Appliances | B12: =IF(ISBLANK(INDEX('Policy Characteristics'!B:B,MATCH($C12,'Policy Characteristics'!$C:$C,0))),"",INDEX('Policy Characteristics'!B:B,MATCH($C12,'Policy Characteristics'!$C:$C,0))) -> Building Component Electrification | C12: Fraction of New Bldg Components Shifted to Other Fuels | D12: heating | E12: commercial | F12: Heating | G12: Commercial | H12: 445 | I12: Yes | J12: =IF(ISBLANK(INDEX('Policy Characteristics'!D:D,MATCH($C12,'Policy Characteristics'!$C:$C,0))),"",INDEX('Policy Characteristics'!D:D,MATCH($C12,'Policy Characteristics'!$C:$C,0))) -> Building Component Electrification | K12: =IF(ISBLANK(INDEX('Policy Characteristics'!E:E,MATCH($C12,'Policy Characteristics'!$C:$C,0))),"",INDEX('Policy Characteristics'!E:E,MATCH($C12,'Policy Characteristics'!$C:$C,0))) -> bldgs new component fuel shifting | L12: =IF(ISBLANK(INDEX('Policy Characteristics'!F:F,MATCH($C12,'Policy Characteristics'!$C:$C,0))),"",INDEX('Policy Characteristics'!F:F,MATCH($C12,'Policy Characteristics'!$C:$C,0))) -> 0 | M12: =IF(ISBLANK(INDEX('Policy Characteristics'!G:G,MATCH($C12,'Policy Characteristics'!$C:$C,0))),"",INDEX('Policy Characteristics'!G:G,MATCH($C12,'Policy Characteristics'!$C:$C,0))) -> 1 | N12: =IF(ISBLANK(INDEX('Policy Characteristics'!H:H,MATCH($C12,'Policy Characteristics'!$C:$C,0))),"",INDEX('Policy Characteristics'!H:H,MATCH($C12,'Policy Characteristics'!$C:$C,0))) -> 0.01 | O12: =IF(ISBLANK(INDEX('Policy Characteristics'!I:I,MATCH($C12,'Policy Characteristics'!$C:$C,0))),"",INDEX('Policy Characteristics'!I:I,MATCH($C12,'Policy Characteristics'!$C:$C,0))) -> % of newly sold non-electric building components | P12: =IF(ISBLANK(INDEX('Policy Characteristics'!J:J,MATCH($C12,'Policy Characteristics'!$C:$C,0))),"",INDEX('Policy Characteristics'!J:J,MATCH($C12,'Policy Characteristics'!$C:$C,0))) -> **Description:** This policy replaces the specified fraction of newly sold non-electric building components of the selected type(s) in buildings of the selected type(s) with electricity-using components. | Q12: =IF(ISBLANK(INDEX('Policy Characteristics'!K:K,MATCH($C12,'Policy Characteristics'!$C:$C,0))),"",INDEX('Policy Characteristics'!K:K,MATCH($C12,'Policy Characteristics'!$C:$C,0))) -> buildings-sector-main.html#component-elec | R12: =IF(ISBLANK(INDEX('Policy Characteristics'!L:L,MATCH($C12,'Policy Characteristics'!$C:$C,0))),"",INDEX('Policy Characteristics'!L:L,MATCH($C12,'Policy Characteristics'!$C:$C,0))) -> building-component-electrification.html
A13: =IF(ISBLANK(INDEX('Policy Characteristics'!A:A,MATCH($C13,'Policy Characteristics'!$C:$C,0))),"",INDEX('Policy Characteristics'!A:A,MATCH($C13,'Policy Characteristics'!$C:$C,0))) -> Buildings and Appliances | B13: =IF(ISBLANK(INDEX('Policy Characteristics'!B:B,MATCH($C13,'Policy Characteristics'!$C:$C,0))),"",INDEX('Policy Characteristics'!B:B,MATCH($C13,'Policy Characteristics'!$C:$C,0))) -> Building Component Electrification | C13: Fraction of New Bldg Components Shifted to Other Fuels | D13: cooling and ventilation | E13: commercial | F13: Cooling and Ventilation | G13: Commercial | H13: 446 | I13: No | J13: =IF(ISBLANK(INDEX('Policy Characteristics'!D:D,MATCH($C13,'Policy Characteristics'!$C:$C,0))),"",INDEX('Policy Characteristics'!D:D,MATCH($C13,'Policy Characteristics'!$C:$C,0))) -> Building Component Electrification | K13: =IF(ISBLANK(INDEX('Policy Characteristics'!E:E,MATCH($C13,'Policy Characteristics'!$C:$C,0))),"",INDEX('Policy Characteristics'!E:E,MATCH($C13,'Policy Characteristics'!$C:$C,0))) -> bldgs new component fuel shifting | L13: =IF(ISBLANK(INDEX('Policy Characteristics'!F:F,MATCH($C13,'Policy Characteristics'!$C:$C,0))),"",INDEX('Policy Characteristics'!F:F,MATCH($C13,'Policy Characteristics'!$C:$C,0))) -> 0 | M13: =IF(ISBLANK(INDEX('Policy Characteristics'!G:G,MATCH($C13,'Policy Characteristics'!$C:$C,0))),"",INDEX('Policy Characteristics'!G:G,MATCH($C13,'Policy Characteristics'!$C:$C,0))) -> 1 | N13: =IF(ISBLANK(INDEX('Policy Characteristics'!H:H,MATCH($C13,'Policy Characteristics'!$C:$C,0))),"",INDEX('Policy Characteristics'!H:H,MATCH($C13,'Policy Characteristics'!$C:$C,0))) -> 0.01 | O13: =IF(ISBLANK(INDEX('Policy Characteristics'!I:I,MATCH($C13,'Policy Characteristics'!$C:$C,0))),"",INDEX('Policy Characteristics'!I:I,MATCH($C13,'Policy Characteristics'!$C:$C,0))) -> % of newly sold non-electric building components | P13: =IF(ISBLANK(INDEX('Policy Characteristics'!J:J,MATCH($C13,'Policy Characteristics'!$C:$C,0))),"",INDEX('Policy Characteristics'!J:J,MATCH($C13,'Policy Characteristics'!$C:$C,0))) -> **Description:** This policy replaces the specified fraction of newly sold non-electric building components of the selected type(s) in buildings of the selected type(s) with electricity-using components. | Q13: =IF(ISBLANK(INDEX('Policy Characteristics'!K:K,MATCH($C13,'Policy Characteristics'!$C:$C,0))),"",INDEX('Policy Characteristics'!K:K,MATCH($C13,'Policy Characteristics'!$C:$C,0))) -> buildings-sector-main.html#component-elec | R13: =IF(ISBLANK(INDEX('Policy Characteristics'!L:L,MATCH($C13,'Policy Characteristics'!$C:$C,0))),"",INDEX('Policy Characteristics'!L:L,MATCH($C13,'Policy Characteristics'!$C:$C,0))) -> building-component-electrification.html
A14: =IF(ISBLANK(INDEX('Policy Characteristics'!A:A,MATCH($C14,'Policy Characteristics'!$C:$C,0))),"",INDEX('Policy Characteristics'!A:A,MATCH($C14,'Policy Characteristics'!$C:$C,0))) -> Buildings and Appliances | B14: =IF(ISBLANK(INDEX('Policy Characteristics'!B:B,MATCH($C14,'Policy Characteristics'!$C:$C,0))),"",INDEX('Policy Characteristics'!B:B,MATCH($C14,'Policy Characteristics'!$C:$C,0))) -> Building Component Electrification | C14: Fraction of New Bldg Components Shifted to Other Fuels | D14: lighting | E14: commercial | F14: Lighting | G14: Commercial | H14: 447 | I14: No | J14: =IF(ISBLANK(INDEX('Policy Characteristics'!D:D,MATCH($C14,'Policy Characteristics'!$C:$C,0))),"",INDEX('Policy Characteristics'!D:D,MATCH($C14,'Policy Characteristics'!$C:$C,0))) -> Building Component Electrification | K14: =IF(ISBLANK(INDEX('Policy Characteristics'!E:E,MATCH($C14,'Policy Characteristics'!$C:$C,0))),"",INDEX('Policy Characteristics'!E:E,MATCH($C14,'Policy Characteristics'!$C:$C,0))) -> bldgs new component fuel shifting | L14: =IF(ISBLANK(INDEX('Policy Characteristics'!F:F,MATCH($C14,'Policy Characteristics'!$C:$C,0))),"",INDEX('Policy Characteristics'!F:F,MATCH($C14,'Policy Characteristics'!$C:$C,0))) -> 0 | M14: =IF(ISBLANK(INDEX('Policy Characteristics'!G:G,MATCH($C14,'Policy Characteristics'!$C:$C,0))),"",INDEX('Policy Characteristics'!G:G,MATCH($C14,'Policy Characteristics'!$C:$C,0))) -> 1 | N14: =IF(ISBLANK(INDEX('Policy Characteristics'!H:H,MATCH($C14,'Policy Characteristics'!$C:$C,0))),"",INDEX('Policy Characteristics'!H:H,MATCH($C14,'Policy Characteristics'!$C:$C,0))) -> 0.01 | O14: =IF(ISBLANK(INDEX('Policy Characteristics'!I:I,MATCH($C14,'Policy Characteristics'!$C:$C,0))),"",INDEX('Policy Characteristics'!I:I,MATCH($C14,'Policy Characteristics'!$C:$C,0))) -> % of newly sold non-electric building components | P14: =IF(ISBLANK(INDEX('Policy Characteristics'!J:J,MATCH($C14,'Policy Characteristics'!$C:$C,0))),"",INDEX('Policy Characteristics'!J:J,MATCH($C14,'Policy Characteristics'!$C:$C,0))) -> **Description:** This policy replaces the specified fraction of newly sold non-electric building components of the selected type(s) in buildings of the selected type(s) with electricity-using components. | Q14: =IF(ISBLANK(INDEX('Policy Characteristics'!K:K,MATCH($C14,'Policy Characteristics'!$C:$C,0))),"",INDEX('Policy Characteristics'!K:K,MATCH($C14,'Policy Characteristics'!$C:$C,0))) -> buildings-sector-main.html#component-elec | R14: =IF(ISBLANK(INDEX('Policy Characteristics'!L:L,MATCH($C14,'Policy Characteristics'!$C:$C,0))),"",INDEX('Policy Characteristics'!L:L,MATCH($C14,'Policy Characteristics'!$C:$C,0))) -> building-component-electrification.html
... A16: =IF(ISBLANK(INDEX('Policy Characteristics'!A:A,MATCH($C16,'Policy Characteristics'!$C:$C,0))),"",INDEX('Policy Characteristics'!A:A,MATCH($C16,'Policy Characteristics'!$C:$C,0))) -> Buildings and Appliances | B16: =IF(ISBLANK(INDEX('Policy Characteristics'!B:B,MATCH($C16,'Policy Characteristics'!$C:$C,0))),"",INDEX('Policy Characteristics'!B:B,MATCH($C16,'Policy Characteristics'!$C:$C,0))) -> Building Component Electrification | C16: Fraction of New Bldg Components Shifted to Other Fuels | D16: other component | E16: commercial | F16: Other Components | G16: Commercial | H16: 449 | I16: Yes | J16: =IF(ISBLANK(INDEX('Policy Characteristics'!D:D,MATCH($C16,'Policy Characteristics'!$C:$C,0))),"",INDEX('Policy Characteristics'!D:D,MATCH($C16,'Policy Characteristics'!$C:$C,0))) -> Building Component Electrification | K16: =IF(ISBLANK(INDEX('Policy Characteristics'!E:E,MATCH($C16,'Policy Characteristics'!$C:$C,0))),"",INDEX('Policy Characteristics'!E:E,MATCH($C16,'Policy Characteristics'!$C:$C,0))) -> bldgs new component fuel shifting | L16: =IF(ISBLANK(INDEX('Policy Characteristics'!F:F,MATCH($C16,'Policy Characteristics'!$C:$C,0))),"",INDEX('Policy Characteristics'!F:F,MATCH($C16,'Policy Characteristics'!$C:$C,0))) -> 0 | M16: =IF(ISBLANK(INDEX('Policy Characteristics'!G:G,MATCH($C16,'Policy Characteristics'!$C:$C,0))),"",INDEX('Policy Characteristics'!G:G,MATCH($C16,'Policy Characteristics'!$C:$C,0))) -> 1 | N16: =IF(ISBLANK(INDEX('Policy Characteristics'!H:H,MATCH($C16,'Policy Characteristics'!$C:$C,0))),"",INDEX('Policy Characteristics'!H:H,MATCH($C16,'Policy Characteristics'!$C:$C,0))) -> 0.01 | O16: =IF(ISBLANK(INDEX('Policy Characteristics'!I:I,MATCH($C16,'Policy Characteristics'!$C:$C,0))),"",INDEX('Policy Characteristics'!I:I,MATCH($C16,'Policy Characteristics'!$C:$C,0))) -> % of newly sold non-electric building components | P16: =IF(ISBLANK(INDEX('Policy Characteristics'!J:J,MATCH($C16,'Policy Characteristics'!$C:$C,0))),"",INDEX('Policy Characteristics'!J:J,MATCH($C16,'Policy Characteristics'!$C:$C,0))) -> **Description:** This policy replaces the specified fraction of newly sold non-electric building components of the selected type(s) in buildings of the selected type(s) with electricity-using components. | Q16: =IF(ISBLANK(INDEX('Policy Characteristics'!K:K,MATCH($C16,'Policy Characteristics'!$C:$C,0))),"",INDEX('Policy Characteristics'!K:K,MATCH($C16,'Policy Characteristics'!$C:$C,0))) -> buildings-sector-main.html#component-elec | R16: =IF(ISBLANK(INDEX('Policy Characteristics'!L:L,MATCH($C16,'Policy Characteristics'!$C:$C,0))),"",INDEX('Policy Characteristics'!L:L,MATCH($C16,'Policy Characteristics'!$C:$C,0))) -> building-component-electrification.html
A17: =IF(ISBLANK(INDEX('Policy Characteristics'!A:A,MATCH($C17,'Policy Characteristics'!$C:$C,0))),"",INDEX('Policy Characteristics'!A:A,MATCH($C17,'Policy Characteristics'!$C:$C,0))) -> Buildings and Appliances | B17: =IF(ISBLANK(INDEX('Policy Characteristics'!B:B,MATCH($C17,'Policy Characteristics'!$C:$C,0))),"",INDEX('Policy Characteristics'!B:B,MATCH($C17,'Policy Characteristics'!$C:$C,0))) -> Building Energy Efficiency Standards | C17: Reduction in E Use Allowed by Component Eff Std | D17: heating | E17: urban residential | F17: Heating | G17: Urban Residential | H17: 13 | I17: Yes | J17: =IF(ISBLANK(INDEX('Policy Characteristics'!D:D,MATCH($C17,'Policy Characteristics'!$C:$C,0))),"",INDEX('Policy Characteristics'!D:D,MATCH($C17,'Policy Characteristics'!$C:$C,0))) -> Building Energy Efficiency Standards | K17: =IF(ISBLANK(INDEX('Policy Characteristics'!E:E,MATCH($C17,'Policy Characteristics'!$C:$C,0))),"",INDEX('Policy Characteristics'!E:E,MATCH($C17,'Policy Characteristics'!$C:$C,0))) -> bldgs efficiency standards | L17: =IF(ISBLANK(INDEX('Policy Characteristics'!F:F,MATCH($C17,'Policy Characteristics'!$C:$C,0))),"",INDEX('Policy Characteristics'!F:F,MATCH($C17,'Policy Characteristics'!$C:$C,0))) -> 0 | M17: =IF(ISBLANK(INDEX('Policy Characteristics'!G:G,MATCH($C17,'Policy Characteristics'!$C:$C,0))),"",INDEX('Policy Characteristics'!G:G,MATCH($C17,'Policy Characteristics'!$C:$C,0))) -> 0.75 | N17: =IF(ISBLANK(INDEX('Policy Characteristics'!H:H,MATCH($C17,'Policy Characteristics'!$C:$C,0))),"",INDEX('Policy Characteristics'!H:H,MATCH($C17,'Policy Characteristics'!$C:$C,0))) -> 0.01 | O17: =IF(ISBLANK(INDEX('Policy Characteristics'!I:I,MATCH($C17,'Policy Characteristics'!$C:$C,0))),"",INDEX('Policy Characteristics'!I:I,MATCH($C17,'Policy Characteristics'!$C:$C,0))) -> % reduction in energy use | P17: =IF(ISBLANK(INDEX('Policy Characteristics'!J:J,MATCH($C17,'Policy Characteristics'!$C:$C,0))),"",INDEX('Policy Characteristics'!J:J,MATCH($C17,'Policy Characteristics'!$C:$C,0))) -> **Description:** This policy tightens energy efficiency standards for the selected component(s) in the selected building type(s). The policy only applies to newly sold components each year (whether for new buildings or replacement of old components of existing buildings). // **Guidance for setting values:** In "Assessment of Electricity Savings in the U.S. Achievable through New Appliance/Equipment Efficiency Standards and Building Efficiency Codes, 2010-2025" (2011), the Edison Foundation considered a 30% reduction in whole-building energy use (moderate case) and 40-45% (aggressive case) relative to BAU from 2010 to 2025. | Q17: =IF(ISBLANK(INDEX('Policy Characteristics'!K:K,MATCH($C17,'Policy Characteristics'!$C:$C,0))),"",INDEX('Policy Characteristics'!K:K,MATCH($C17,'Policy Characteristics'!$C:$C,0))) -> buildings-sector-main.html#eff-stds | R17: =IF(ISBLANK(INDEX('Policy Characteristics'!L:L,MATCH($C17,'Policy Characteristics'!$C:$C,0))),"",INDEX('Policy Characteristics'!L:L,MATCH($C17,'Policy Characteristics'!$C:$C,0))) -> building-energy-efficiency-standards.html | S17: Set minimum energy efficiency criteria for new buildings and appliances.
A18: =IF(ISBLANK(INDEX('Policy Characteristics'!A:A,MATCH($C18,'Policy Characteristics'!$C:$C,0))),"",INDEX('Policy Characteristics'!A:A,MATCH($C18,'Policy Characteristics'!$C:$C,0))) -> Buildings and Appliances | B18: =IF(ISBLANK(INDEX('Policy Characteristics'!B:B,MATCH($C18,'Policy Characteristics'!$C:$C,0))),"",INDEX('Policy Characteristics'!B:B,MATCH($C18,'Policy Characteristics'!$C:$C,0))) -> Building Energy Efficiency Standards | C18: Reduction in E Use Allowed by Component Eff Std | D18: cooling and ventilation | E18: urban residential | F18: Cooling and Ventilation | G18: Urban Residential | H18: 14 | I18: Yes | J18: =IF(ISBLANK(INDEX('Policy Characteristics'!D:D,MATCH($C18,'Policy Characteristics'!$C:$C,0))),"",INDEX('Policy Characteristics'!D:D,MATCH($C18,'Policy Characteristics'!$C:$C,0))) -> Building Energy Efficiency Standards | K18: =IF(ISBLANK(INDEX('Policy Characteristics'!E:E,MATCH($C18,'Policy Characteristics'!$C:$C,0))),"",INDEX('Policy Characteristics'!E:E,MATCH($C18,'Policy Characteristics'!$C:$C,0))) -> bldgs efficiency standards | L18: =IF(ISBLANK(INDEX('Policy Characteristics'!F:F,MATCH($C18,'Policy Characteristics'!$C:$C,0))),"",INDEX('Policy Characteristics'!F:F,MATCH($C18,'Policy Characteristics'!$C:$C,0))) -> 0 | M18: =IF(ISBLANK(INDEX('Policy Characteristics'!G:G,MATCH($C18,'Policy Characteristics'!$C:$C,0))),"",INDEX('Policy Characteristics'!G:G,MATCH($C18,'Policy Characteristics'!$C:$C,0))) -> 0.75 | N18: =IF(ISBLANK(INDEX('Policy Characteristics'!H:H,MATCH($C18,'Policy Characteristics'!$C:$C,0))),"",INDEX('Policy Characteristics'!H:H,MATCH($C18,'Policy Characteristics'!$C:$C,0))) -> 0.01 | O18: =IF(ISBLANK(INDEX('Policy Characteristics'!I:I,MATCH($C18,'Policy Characteristics'!$C:$C,0))),"",INDEX('Policy Characteristics'!I:I,MATCH($C18,'Policy Characteristics'!$C:$C,0))) -> % reduction in energy use | P18: =IF(ISBLANK(INDEX('Policy Characteristics'!J:J,MATCH($C18,'Policy Characteristics'!$C:$C,0))),"",INDEX('Policy Characteristics'!J:J,MATCH($C18,'Policy Characteristics'!$C:$C,0))) -> **Description:** This policy tightens energy efficiency standards for the selected component(s) in the selected building type(s). The policy only applies to newly sold components each year (whether for new buildings or replacement of old components of existing buildings). // **Guidance for setting values:** In "Assessment of Electricity Savings in the U.S. Achievable through New Appliance/Equipment Efficiency Standards and Building Efficiency Codes, 2010-2025" (2011), the Edison Foundation considered a 30% reduction in whole-building energy use (moderate case) and 40-45% (aggressive case) relative to BAU from 2010 to 2025. | Q18: =IF(ISBLANK(INDEX('Policy Characteristics'!K:K,MATCH($C18,'Policy Characteristics'!$C:$C,0))),"",INDEX('Policy Characteristics'!K:K,MATCH($C18,'Policy Characteristics'!$C:$C,0))) -> buildings-sector-main.html#eff-stds | R18: =IF(ISBLANK(INDEX('Policy Characteristics'!L:L,MATCH($C18,'Policy Characteristics'!$C:$C,0))),"",INDEX('Policy Characteristics'!L:L,MATCH($C18,'Policy Characteristics'!$C:$C,0))) -> building-energy-efficiency-standards.html
A19: =IF(ISBLANK(INDEX('Policy Characteristics'!A:A,MATCH($C19,'Policy Characteristics'!$C:$C,0))),"",INDEX('Policy Characteristics'!A:A,MATCH($C19,'Policy Characteristics'!$C:$C,0))) -> Buildings and Appliances | B19: =IF(ISBLANK(INDEX('Policy Characteristics'!B:B,MATCH($C19,'Policy Characteristics'!$C:$C,0))),"",INDEX('Policy Characteristics'!B:B,MATCH($C19,'Policy Characteristics'!$C:$C,0))) -> Building Energy Efficiency Standards | C19: Reduction in E Use Allowed by Component Eff Std | D19: envelope | E19: urban residential | F19: Envelope | G19: Urban Residential | H19: 15 | I19: Yes | J19: =IF(ISBLANK(INDEX('Policy Characteristics'!D:D,MATCH($C19,'Policy Characteristics'!$C:$C,0))),"",INDEX('Policy Characteristics'!D:D,MATCH($C19,'Policy Characteristics'!$C:$C,0))) -> Building Energy Efficiency Standards | K19: =IF(ISBLANK(INDEX('Policy Characteristics'!E:E,MATCH($C19,'Policy Characteristics'!$C:$C,0))),"",INDEX('Policy Characteristics'!E:E,MATCH($C19,'Policy Characteristics'!$C:$C,0))) -> bldgs efficiency standards | L19: =IF(ISBLANK(INDEX('Policy Characteristics'!F:F,MATCH($C19,'Policy Characteristics'!$C:$C,0))),"",INDEX('Policy Characteristics'!F:F,MATCH($C19,'Policy Characteristics'!$C:$C,0))) -> 0 | M19: =IF(ISBLANK(INDEX('Policy Characteristics'!G:G,MATCH($C19,'Policy Characteristics'!$C:$C,0))),"",INDEX('Policy Characteristics'!G:G,MATCH($C19,'Policy Characteristics'!$C:$C,0))) -> 0.75 | N19: =IF(ISBLANK(INDEX('Policy Characteristics'!H:H,MATCH($C19,'Policy Characteristics'!$C:$C,0))),"",INDEX('Policy Characteristics'!H:H,MATCH($C19,'Policy Characteristics'!$C:$C,0))) -> 0.01 | O19: =IF(ISBLANK(INDEX('Policy Characteristics'!I:I,MATCH($C19,'Policy Characteristics'!$C:$C,0))),"",INDEX('Policy Characteristics'!I:I,MATCH($C19,'Policy Characteristics'!$C:$C,0))) -> % reduction in energy use | P19: =IF(ISBLANK(INDEX('Policy Characteristics'!J:J,MATCH($C19,'Policy Characteristics'!$C:$C,0))),"",INDEX('Policy Characteristics'!J:J,MATCH($C19,'Policy Characteristics'!$C:$C,0))) -> **Description:** This policy tightens energy efficiency standards for the selected component(s) in the selected building type(s). The policy only applies to newly sold components each year (whether for new buildings or replacement of old components of existing buildings). // **Guidance for setting values:** In "Assessment of Electricity Savings in the U.S. Achievable through New Appliance/Equipment Efficiency Standards and Building Efficiency Codes, 2010-2025" (2011), the Edison Foundation considered a 30% reduction in whole-building energy use (moderate case) and 40-45% (aggressive case) relative to BAU from 2010 to 2025. | Q19: =IF(ISBLANK(INDEX('Policy Characteristics'!K:K,MATCH($C19,'Policy Characteristics'!$C:$C,0))),"",INDEX('Policy Characteristics'!K:K,MATCH($C19,'Policy Characteristics'!$C:$C,0))) -> buildings-sector-main.html#eff-stds | R19: =IF(ISBLANK(INDEX('Policy Characteristics'!L:L,MATCH($C19,'Policy Characteristics'!$C:$C,0))),"",INDEX('Policy Characteristics'!L:L,MATCH($C19,'Policy Characteristics'!$C:$C,0))) -> building-energy-efficiency-standards.html
A20: =IF(ISBLANK(INDEX('Policy Characteristics'!A:A,MATCH($C20,'Policy Characteristics'!$C:$C,0))),"",INDEX('Policy Characteristics'!A:A,MATCH($C20,'Policy Characteristics'!$C:$C,0))) -> Buildings and Appliances | B20: =IF(ISBLANK(INDEX('Policy Characteristics'!B:B,MATCH($C20,'Policy Characteristics'!$C:$C,0))),"",INDEX('Policy Characteristics'!B:B,MATCH($C20,'Policy Characteristics'!$C:$C,0))) -> Building Energy Efficiency Standards | C20: Reduction in E Use Allowed by Component Eff Std | D20: lighting | E20: urban residential | F20: Lighting | G20: Urban Residential | H20: 16 | I20: Yes | J20: =IF(ISBLANK(INDEX('Policy Characteristics'!D:D,MATCH($C20,'Policy Characteristics'!$C:$C,0))),"",INDEX('Policy Characteristics'!D:D,MATCH($C20,'Policy Characteristics'!$C:$C,0))) -> Building Energy Efficiency Standards | K20: =IF(ISBLANK(INDEX('Policy Characteristics'!E:E,MATCH($C20,'Policy Characteristics'!$C:$C,0))),"",INDEX('Policy Characteristics'!E:E,MATCH($C20,'Policy Characteristics'!$C:$C,0))) -> bldgs efficiency standards | L20: =IF(ISBLANK(INDEX('Policy Characteristics'!F:F,MATCH($C20,'Policy Characteristics'!$C:$C,0))),"",INDEX('Policy Characteristics'!F:F,MATCH($C20,'Policy Characteristics'!$C:$C,0))) -> 0 | M20: =IF(ISBLANK(INDEX('Policy Characteristics'!G:G,MATCH($C20,'Policy Characteristics'!$C:$C,0))),"",INDEX('Policy Characteristics'!G:G,MATCH($C20,'Policy Characteristics'!$C:$C,0))) -> 0.75 | N20: =IF(ISBLANK(INDEX('Policy Characteristics'!H:H,MATCH($C20,'Policy Characteristics'!$C:$C,0))),"",INDEX('Policy Characteristics'!H:H,MATCH($C20,'Policy Characteristics'!$C:$C,0))) -> 0.01 | O20: =IF(ISBLANK(INDEX('Policy Characteristics'!I:I,MATCH($C20,'Policy Characteristics'!$C:$C,0))),"",INDEX('Policy Characteristics'!I:I,MATCH($C20,'Policy Characteristics'!$C:$C,0))) -> % reduction in energy use | P20: =IF(ISBLANK(INDEX('Policy Characteristics'!J:J,MATCH($C20,'Policy Characteristics'!$C:$C,0))),"",INDEX('Policy Characteristics'!J:J,MATCH($C20,'Policy Characteristics'!$C:$C,0))) -> **Description:** This policy tightens energy efficiency standards for the selected component(s) in the selected building type(s). The policy only applies to newly sold components each year (whether for new buildings or replacement of old components of existing buildings). // **Guidance for setting values:** In "Assessment of Electricity Savings in the U.S. Achievable through New Appliance/Equipment Efficiency Standards and Building Efficiency Codes, 2010-2025" (2011), the Edison Foundation considered a 30% reduction in whole-building energy use (moderate case) and 40-45% (aggressive case) relative to BAU from 2010 to 2025. | Q20: =IF(ISBLANK(INDEX('Policy Characteristics'!K:K,MATCH($C20,'Policy Characteristics'!$C:$C,0))),"",INDEX('Policy Characteristics'!K:K,MATCH($C20,'Policy Characteristics'!$C:$C,0))) -> buildings-sector-main.html#eff-stds | R20: =IF(ISBLANK(INDEX('Policy Characteristics'!L:L,MATCH($C20,'Policy Characteristics'!$C:$C,0))),"",INDEX('Policy Characteristics'!L:L,MATCH($C20,'Policy Characteristics'!$C:$C,0))) -> building-energy-efficiency-standards.html
A21: =IF(ISBLANK(INDEX('Policy Characteristics'!A:A,MATCH($C21,'Policy Characteristics'!$C:$C,0))),"",INDEX('Policy Characteristics'!A:A,MATCH($C21,'Policy Characteristics'!$C:$C,0))) -> Buildings and Appliances | B21: =IF(ISBLANK(INDEX('Policy Characteristics'!B:B,MATCH($C21,'Policy Characteristics'!$C:$C,0))),"",INDEX('Policy Characteristics'!B:B,MATCH($C21,'Policy Characteristics'!$C:$C,0))) -> Building Energy Efficiency Standards | C21: Reduction in E Use Allowed by Component Eff Std | D21: appliances | E21: urban residential | F21: Appliances | G21: Urban Residential | H21: 17 | I21: Yes | J21: =IF(ISBLANK(INDEX('Policy Characteristics'!D:D,MATCH($C21,'Policy Characteristics'!$C:$C,0))),"",INDEX('Policy Characteristics'!D:D,MATCH($C21,'Policy Characteristics'!$C:$C,0))) -> Building Energy Efficiency Standards | K21: =IF(ISBLANK(INDEX('Policy Characteristics'!E:E,MATCH($C21,'Policy Characteristics'!$C:$C,0))),"",INDEX('Policy Characteristics'!E:E,MATCH($C21,'Policy Characteristics'!$C:$C,0))) -> bldgs efficiency standards | L21: =IF(ISBLANK(INDEX('Policy Characteristics'!F:F,MATCH($C21,'Policy Characteristics'!$C:$C,0))),"",INDEX('Policy Characteristics'!F:F,MATCH($C21,'Policy Characteristics'!$C:$C,0))) -> 0 | M21: =IF(ISBLANK(INDEX('Policy Characteristics'!G:G,MATCH($C21,'Policy Characteristics'!$C:$C,0))),"",INDEX('Policy Characteristics'!G:G,MATCH($C21,'Policy Characteristics'!$C:$C,0))) -> 0.75 | N21: =IF(ISBLANK(INDEX('Policy Characteristics'!H:H,MATCH($C21,'Policy Characteristics'!$C:$C,0))),"",INDEX('Policy Characteristics'!H:H,MATCH($C21,'Policy Characteristics'!$C:$C,0))) -> 0.01 | O21: =IF(ISBLANK(INDEX('Policy Characteristics'!I:I,MATCH($C21,'Policy Characteristics'!$C:$C,0))),"",INDEX('Policy Characteristics'!I:I,MATCH($C21,'Policy Characteristics'!$C:$C,0))) -> % reduction in energy use | P21: =IF(ISBLANK(INDEX('Policy Characteristics'!J:J,MATCH($C21,'Policy Characteristics'!$C:$C,0))),"",INDEX('Policy Characteristics'!J:J,MATCH($C21,'Policy Characteristics'!$C:$C,0))) -> **Description:** This policy tightens energy efficiency standards for the selected component(s) in the selected building type(s). The policy only applies to newly sold components each year (whether for new buildings or replacement of old components of existing buildings). // **Guidance for setting values:** In "Assessment of Electricity Savings in the U.S. Achievable through New Appliance/Equipment Efficiency Standards and Building Efficiency Codes, 2010-2025" (2011), the Edison Foundation considered a 30% reduction in whole-building energy use (moderate case) and 40-45% (aggressive case) relative to BAU from 2010 to 2025. | Q21: =IF(ISBLANK(INDEX('Policy Characteristics'!K:K,MATCH($C21,'Policy Characteristics'!$C:$C,0))),"",INDEX('Policy Characteristics'!K:K,MATCH($C21,'Policy Characteristics'!$C:$C,0))) -> buildings-sector-main.html#eff-stds | R21: =IF(ISBLANK(INDEX('Policy Characteristics'!L:L,MATCH($C21,'Policy Characteristics'!$C:$C,0))),"",INDEX('Policy Characteristics'!L:L,MATCH($C21,'Policy Characteristics'!$C:$C,0))) -> building-energy-efficiency-standards.html
A22: =IF(ISBLANK(INDEX('Policy Characteristics'!A:A,MATCH($C22,'Policy Characteristics'!$C:$C,0))),"",INDEX('Policy Characteristics'!A:A,MATCH($C22,'Policy Characteristics'!$C:$C,0))) -> Buildings and Appliances | B22: =IF(ISBLANK(INDEX('Policy Characteristics'!B:B,MATCH($C22,'Policy Characteristics'!$C:$C,0))),"",INDEX('Policy Characteristics'!B:B,MATCH($C22,'Policy Characteristics'!$C:$C,0))) -> Building Energy Efficiency Standards | C22: Reduction in E Use Allowed by Component Eff Std | D22: other component | E22: urban residential | F22: Other Components | G22: Urban Residential | H22: 18 | I22: Yes | J22: =IF(ISBLANK(INDEX('Policy Characteristics'!D:D,MATCH($C22,'Policy Characteristics'!$C:$C,0))),"",INDEX('Policy Characteristics'!D:D,MATCH($C22,'Policy Characteristics'!$C:$C,0))) -> Building Energy Efficiency Standards | K22: =IF(ISBLANK(INDEX('Policy Characteristics'!E:E,MATCH($C22,'Policy Characteristics'!$C:$C,0))),"",INDEX('Policy Characteristics'!E:E,MATCH($C22,'Policy Characteristics'!$C:$C,0))) -> bldgs efficiency standards | L22: =IF(ISBLANK(INDEX('Policy Characteristics'!F:F,MATCH($C22,'Policy Characteristics'!$C:$C,0))),"",INDEX('Policy Characteristics'!F:F,MATCH($C22,'Policy Characteristics'!$C:$C,0))) -> 0 | M22: =IF(ISBLANK(INDEX('Policy Characteristics'!G:G,MATCH($C22,'Policy Characteristics'!$C:$C,0))),"",INDEX('Policy Characteristics'!G:G,MATCH($C22,'Policy Characteristics'!$C:$C,0))) -> 0.75 | N22: =IF(ISBLANK(INDEX('Policy Characteristics'!H:H,MATCH($C22,'Policy Characteristics'!$C:$C,0))),"",INDEX('Policy Characteristics'!H:H,MATCH($C22,'Policy Characteristics'!$C:$C,0))) -> 0.01 | O22: =IF(ISBLANK(INDEX('Policy Characteristics'!I:I,MATCH($C22,'Policy Characteristics'!$C:$C,0))),"",INDEX('Policy Characteristics'!I:I,MATCH($C22,'Policy Characteristics'!$C:$C,0))) -> % reduction in energy use | P22: =IF(ISBLANK(INDEX('Policy Characteristics'!J:J,MATCH($C22,'Policy Characteristics'!$C:$C,0))),"",INDEX('Policy Characteristics'!J:J,MATCH($C22,'Policy Characteristics'!$C:$C,0))) -> **Description:** This policy tightens energy efficiency standards for the selected component(s) in the selected building type(s). The policy only applies to newly sold components each year (whether for new buildings or replacement of old components of existing buildings). // **Guidance for setting values:** In "Assessment of Electricity Savings in the U.S. Achievable through New Appliance/Equipment Efficiency Standards and Building Efficiency Codes, 2010-2025" (2011), the Edison Foundation considered a 30% reduction in whole-building energy use (moderate case) and 40-45% (aggressive case) relative to BAU from 2010 to 2025. | Q22: =IF(ISBLANK(INDEX('Policy Characteristics'!K:K,MATCH($C22,'Policy Characteristics'!$C:$C,0))),"",INDEX('Policy Characteristics'!K:K,MATCH($C22,'Policy Characteristics'!$C:$C,0))) -> buildings-sector-main.html#eff-stds | R22: =IF(ISBLANK(INDEX('Policy Characteristics'!L:L,MATCH($C22,'Policy Characteristics'!$C:$C,0))),"",INDEX('Policy Characteristics'!L:L,MATCH($C22,'Policy Characteristics'!$C:$C,0))) -> building-energy-efficiency-standards.html
A23: =IF(ISBLANK(INDEX('Policy Characteristics'!A:A,MATCH($C23,'Policy Characteristics'!$C:$C,0))),"",INDEX('Policy Characteristics'!A:A,MATCH($C23,'Policy Characteristics'!$C:$C,0))) -> Buildings and Appliances | B23: =IF(ISBLANK(INDEX('Policy Characteristics'!B:B,MATCH($C23,'Policy Characteristics'!$C:$C,0))),"",INDEX('Policy Characteristics'!B:B,MATCH($C23,'Policy Characteristics'!$C:$C,0))) -> Building Energy Efficiency Standards | C23: Reduction in E Use Allowed by Component Eff Std | D23: heating | E23: rural residential | F23: Heating | G23: Rural Residential | H23: 150 | I23: Yes | J23: =IF(ISBLANK(INDEX('Policy Characteristics'!D:D,MATCH($C23,'Policy Characteristics'!$C:$C,0))),"",INDEX('Policy Characteristics'!D:D,MATCH($C23,'Policy Characteristics'!$C:$C,0))) -> Building Energy Efficiency Standards | K23: =IF(ISBLANK(INDEX('Policy Characteristics'!E:E,MATCH($C23,'Policy Characteristics'!$C:$C,0))),"",INDEX('Policy Characteristics'!E:E,MATCH($C23,'Policy Characteristics'!$C:$C,0))) -> bldgs efficiency standards | L23: =IF(ISBLANK(INDEX('Policy Characteristics'!F:F,MATCH($C23,'Policy Characteristics'!$C:$C,0))),"",INDEX('Policy Characteristics'!F:F,MATCH($C23,'Policy Characteristics'!$C:$C,0))) -> 0 | M23: =IF(ISBLANK(INDEX('Policy Characteristics'!G:G,MATCH($C23,'Policy Characteristics'!$C:$C,0))),"",INDEX('Policy Characteristics'!G:G,MATCH($C23,'Policy Characteristics'!$C:$C,0))) -> 0.75 | N23: =IF(ISBLANK(INDEX('Policy Characteristics'!H:H,MATCH($C23,'Policy Characteristics'!$C:$C,0))),"",INDEX('Policy Characteristics'!H:H,MATCH($C23,'Policy Characteristics'!$C:$C,0))) -> 0.01 | O23: =IF(ISBLANK(INDEX('Policy Characteristics'!I:I,MATCH($C23,'Policy Characteristics'!$C:$C,0))),"",INDEX('Policy Characteristics'!I:I,MATCH($C23,'Policy Characteristics'!$C:$C,0))) -> % reduction in energy use | P23: =IF(ISBLANK(INDEX('Policy Characteristics'!J:J,MATCH($C23,'Policy Characteristics'!$C:$C,0))),"",INDEX('Policy Characteristics'!J:J,MATCH($C23,'Policy Characteristics'!$C:$C,0))) -> **Description:** This policy tightens energy efficiency standards for the selected component(s) in the selected building type(s). The policy only applies to newly sold components each year (whether for new buildings or replacement of old components of existing buildings). // **Guidance for setting values:** In "Assessment of Electricity Savings in the U.S. Achievable through New Appliance/Equipment Efficiency Standards and Building Efficiency Codes, 2010-2025" (2011), the Edison Foundation considered a 30% reduction in whole-building energy use (moderate case) and 40-45% (aggressive case) relative to BAU from 2010 to 2025. | Q23: =IF(ISBLANK(INDEX('Policy Characteristics'!K:K,MATCH($C23,'Policy Characteristics'!$C:$C,0))),"",INDEX('Policy Characteristics'!K:K,MATCH($C23,'Policy Characteristics'!$C:$C,0))) -> buildings-sector-main.html#eff-stds | R23: =IF(ISBLANK(INDEX('Policy Characteristics'!L:L,MATCH($C23,'Policy Characteristics'!$C:$C,0))),"",INDEX('Policy Characteristics'!L:L,MATCH($C23,'Policy Characteristics'!$C:$C,0))) -> building-energy-efficiency-standards.html
A24: =IF(ISBLANK(INDEX('Policy Characteristics'!A:A,MATCH($C24,'Policy Characteristics'!$C:$C,0))),"",INDEX('Policy Characteristics'!A:A,MATCH($C24,'Policy Characteristics'!$C:$C,0))) -> Buildings and Appliances | B24: =IF(ISBLANK(INDEX('Policy Characteristics'!B:B,MATCH($C24,'Policy Characteristics'!$C:$C,0))),"",INDEX('Policy Characteristics'!B:B,MATCH($C24,'Policy Characteristics'!$C:$C,0))) -> Building Energy Efficiency Standards | C24: Reduction in E Use Allowed by Component Eff Std | D24: cooling and ventilation | E24: rural residential | F24: Cooling and Ventilation | G24: Rural Residential | H24: 151 | I24: Yes | J24: =IF(ISBLANK(INDEX('Policy Characteristics'!D:D,MATCH($C24,'Policy Characteristics'!$C:$C,0))),"",INDEX('Policy Characteristics'!D:D,MATCH($C24,'Policy Characteristics'!$C:$C,0))) -> Building Energy Efficiency Standards | K24: =IF(ISBLANK(INDEX('Policy Characteristics'!E:E,MATCH($C24,'Policy Characteristics'!$C:$C,0))),"",INDEX('Policy Characteristics'!E:E,MATCH($C24,'Policy Characteristics'!$C:$C,0))) -> bldgs efficiency standards | L24: =IF(ISBLANK(INDEX('Policy Characteristics'!F:F,MATCH($C24,'Policy Characteristics'!$C:$C,0))),"",INDEX('Policy Characteristics'!F:F,MATCH($C24,'Policy Characteristics'!$C:$C,0))) -> 0 | M24: =IF(ISBLANK(INDEX('Policy Characteristics'!G:G,MATCH($C24,'Policy Characteristics'!$C:$C,0))),"",INDEX('Policy Characteristics'!G:G,MATCH($C24,'Policy Characteristics'!$C:$C,0))) -> 0.75 | N24: =IF(ISBLANK(INDEX('Policy Characteristics'!H:H,MATCH($C24,'Policy Characteristics'!$C:$C,0))),"",INDEX('Policy Characteristics'!H:H,MATCH($C24,'Policy Characteristics'!$C:$C,0))) -> 0.01 | O24: =IF(ISBLANK(INDEX('Policy Characteristics'!I:I,MATCH($C24,'Policy Characteristics'!$C:$C,0))),"",INDEX('Policy Characteristics'!I:I,MATCH($C24,'Policy Characteristics'!$C:$C,0))) -> % reduction in energy use | P24: =IF(ISBLANK(INDEX('Policy Characteristics'!J:J,MATCH($C24,'Policy Characteristics'!$C:$C,0))),"",INDEX('Policy Characteristics'!J:J,MATCH($C24,'Policy Characteristics'!$C:$C,0))) -> **Description:** This policy tightens energy efficiency standards for the selected component(s) in the selected building type(s). The policy only applies to newly sold components each year (whether for new buildings or replacement of old components of existing buildings). // **Guidance for setting values:** In "Assessment of Electricity Savings in the U.S. Achievable through New Appliance/Equipment Efficiency Standards and Building Efficiency Codes, 2010-2025" (2011), the Edison Foundation considered a 30% reduction in whole-building energy use (moderate case) and 40-45% (aggressive case) relative to BAU from 2010 to 2025. | Q24: =IF(ISBLANK(INDEX('Policy Characteristics'!K:K,MATCH($C24,'Policy Characteristics'!$C:$C,0))),"",INDEX('Policy Characteristics'!K:K,MATCH($C24,'Policy Characteristics'!$C:$C,0))) -> buildings-sector-main.html#eff-stds | R24: =IF(ISBLANK(INDEX('Policy Characteristics'!L:L,MATCH($C24,'Policy Characteristics'!$C:$C,0))),"",INDEX('Policy Characteristics'!L:L,MATCH($C24,'Policy Characteristics'!$C:$C,0))) -> building-energy-efficiency-standards.html
A25: =IF(ISBLANK(INDEX('Policy Characteristics'!A:A,MATCH($C25,'Policy Characteristics'!$C:$C,0))),"",INDEX('Policy Characteristics'!A:A,MATCH($C25,'Policy Characteristics'!$C:$C,0))) -> Buildings and Appliances | B25: =IF(ISBLANK(INDEX('Policy Characteristics'!B:B,MATCH($C25,'Policy Characteristics'!$C:$C,0))),"",INDEX('Policy Characteristics'!B:B,MATCH($C25,'Policy Characteristics'!$C:$C,0))) -> Building Energy Efficiency Standards | C25: Reduction in E Use Allowed by Component Eff Std | D25: envelope | E25: rural residential | F25: Envelope | G25: Rural Residential | H25: 152 | I25: Yes | J25: =IF(ISBLANK(INDEX('Policy Characteristics'!D:D,MATCH($C25,'Policy Characteristics'!$C:$C,0))),"",INDEX('Policy Characteristics'!D:D,MATCH($C25,'Policy Characteristics'!$C:$C,0))) -> Building Energy Efficiency Standards | K25: =IF(ISBLANK(INDEX('Policy Characteristics'!E:E,MATCH($C25,'Policy Characteristics'!$C:$C,0))),"",INDEX('Policy Characteristics'!E:E,MATCH($C25,'Policy Characteristics'!$C:$C,0))) -> bldgs efficiency standards | L25: =IF(ISBLANK(INDEX('Policy Characteristics'!F:F,MATCH($C25,'Policy Characteristics'!$C:$C,0))),"",INDEX('Policy Characteristics'!F:F,MATCH($C25,'Policy Characteristics'!$C:$C,0))) -> 0 | M25: =IF(ISBLANK(INDEX('Policy Characteristics'!G:G,MATCH($C25,'Policy Characteristics'!$C:$C,0))),"",INDEX('Policy Characteristics'!G:G,MATCH($C25,'Policy Characteristics'!$C:$C,0))) -> 0.75 | N25: =IF(ISBLANK(INDEX('Policy Characteristics'!H:H,MATCH($C25,'Policy Characteristics'!$C:$C,0))),"",INDEX('Policy Characteristics'!H:H,MATCH($C25,'Policy Characteristics'!$C:$C,0))) -> 0.01 | O25: =IF(ISBLANK(INDEX('Policy Characteristics'!I:I,MATCH($C25,'Policy Characteristics'!$C:$C,0))),"",INDEX('Policy Characteristics'!I:I,MATCH($C25,'Policy Characteristics'!$C:$C,0))) -> % reduction in energy use | P25: =IF(ISBLANK(INDEX('Policy Characteristics'!J:J,MATCH($C25,'Policy Characteristics'!$C:$C,0))),"",INDEX('Policy Characteristics'!J:J,MATCH($C25,'Policy Characteristics'!$C:$C,0))) -> **Description:** This policy tightens energy efficiency standards for the selected component(s) in the selected building type(s). The policy only applies to newly sold components each year (whether for new buildings or replacement of old components of existing buildings). // **Guidance for setting values:** In "Assessment of Electricity Savings in the U.S. Achievable through New Appliance/Equipment Efficiency Standards and Building Efficiency Codes, 2010-2025" (2011), the Edison Foundation considered a 30% reduction in whole-building energy use (moderate case) and 40-45% (aggressive case) relative to BAU from 2010 to 2025. | Q25: =IF(ISBLANK(INDEX('Policy Characteristics'!K:K,MATCH($C25,'Policy Characteristics'!$C:$C,0))),"",INDEX('Policy Characteristics'!K:K,MATCH($C25,'Policy Characteristics'!$C:$C,0))) -> buildings-sector-main.html#eff-stds | R25: =IF(ISBLANK(INDEX('Policy Characteristics'!L:L,MATCH($C25,'Policy Characteristics'!$C:$C,0))),"",INDEX('Policy Characteristics'!L:L,MATCH($C25,'Policy Characteristics'!$C:$C,0))) -> building-energy-efficiency-standards.html
A26: =IF(ISBLANK(INDEX('Policy Characteristics'!A:A,MATCH($C26,'Policy Characteristics'!$C:$C,0))),"",INDEX('Policy Characteristics'!A:A,MATCH($C26,'Policy Characteristics'!$C:$C,0))) -> Buildings and Appliances | B26: =IF(ISBLANK(INDEX('Policy Characteristics'!B:B,MATCH($C26,'Policy Characteristics'!$C:$C,0))),"",INDEX('Policy Characteristics'!B:B,MATCH($C26,'Policy Characteristics'!$C:$C,0))) -> Building Energy Efficiency Standards | C26: Reduction in E Use Allowed by Component Eff Std | D26: lighting | E26: rural residential | F26: Lighting | G26: Rural Residential | H26: 153 | I26: Yes | J26: =IF(ISBLANK(INDEX('Policy Characteristics'!D:D,MATCH($C26,'Policy Characteristics'!$C:$C,0))),"",INDEX('Policy Characteristics'!D:D,MATCH($C26,'Policy Characteristics'!$C:$C,0))) -> Building Energy Efficiency Standards | K26: =IF(ISBLANK(INDEX('Policy Characteristics'!E:E,MATCH($C26,'Policy Characteristics'!$C:$C,0))),"",INDEX('Policy Characteristics'!E:E,MATCH($C26,'Policy Characteristics'!$C:$C,0))) -> bldgs efficiency standards | L26: =IF(ISBLANK(INDEX('Policy Characteristics'!F:F,MATCH($C26,'Policy Characteristics'!$C:$C,0))),"",INDEX('Policy Characteristics'!F:F,MATCH($C26,'Policy Characteristics'!$C:$C,0))) -> 0 | M26: =IF(ISBLANK(INDEX('Policy Characteristics'!G:G,MATCH($C26,'Policy Characteristics'!$C:$C,0))),"",INDEX('Policy Characteristics'!G:G,MATCH($C26,'Policy Characteristics'!$C:$C,0))) -> 0.75 | N26: =IF(ISBLANK(INDEX('Policy Characteristics'!H:H,MATCH($C26,'Policy Characteristics'!$C:$C,0))),"",INDEX('Policy Characteristics'!H:H,MATCH($C26,'Policy Characteristics'!$C:$C,0))) -> 0.01 | O26: =IF(ISBLANK(INDEX('Policy Characteristics'!I:I,MATCH($C26,'Policy Characteristics'!$C:$C,0))),"",INDEX('Policy Characteristics'!I:I,MATCH($C26,'Policy Characteristics'!$C:$C,0))) -> % reduction in energy use | P26: =IF(ISBLANK(INDEX('Policy Characteristics'!J:J,MATCH($C26,'Policy Characteristics'!$C:$C,0))),"",INDEX('Policy Characteristics'!J:J,MATCH($C26,'Policy Characteristics'!$C:$C,0))) -> **Description:** This policy tightens energy efficiency standards for the selected component(s) in the selected building type(s). The policy only applies to newly sold components each year (whether for new buildings or replacement of old components of existing buildings). // **Guidance for setting values:** In "Assessment of Electricity Savings in the U.S. Achievable through New Appliance/Equipment Efficiency Standards and Building Efficiency Codes, 2010-2025" (2011), the Edison Foundation considered a 30% reduction in whole-building energy use (moderate case) and 40-45% (aggressive case) relative to BAU from 2010 to 2025. | Q26: =IF(ISBLANK(INDEX('Policy Characteristics'!K:K,MATCH($C26,'Policy Characteristics'!$C:$C,0))),"",INDEX('Policy Characteristics'!K:K,MATCH($C26,'Policy Characteristics'!$C:$C,0))) -> buildings-sector-main.html#eff-stds | R26: =IF(ISBLANK(INDEX('Policy Characteristics'!L:L,MATCH($C26,'Policy Characteristics'!$C:$C,0))),"",INDEX('Policy Characteristics'!L:L,MATCH($C26,'Policy Characteristics'!$C:$C,0))) -> building-energy-efficiency-standards.html
A27: =IF(ISBLANK(INDEX('Policy Characteristics'!A:A,MATCH($C27,'Policy Characteristics'!$C:$C,0))),"",INDEX('Policy Characteristics'!A:A,MATCH($C27,'Policy Characteristics'!$C:$C,0))) -> Buildings and Appliances | B27: =IF(ISBLANK(INDEX('Policy Characteristics'!B:B,MATCH($C27,'Policy Characteristics'!$C:$C,0))),"",INDEX('Policy Characteristics'!B:B,MATCH($C27,'Policy Characteristics'!$C:$C,0))) -> Building Energy Efficiency Standards | C27: Reduction in E Use Allowed by Component Eff Std | D27: appliances | E27: rural residential | F27: Appliances | G27: Rural Residential | H27: 154 | I27: Yes | J27: =IF(ISBLANK(INDEX('Policy Characteristics'!D:D,MATCH($C27,'Policy Characteristics'!$C:$C,0))),"",INDEX('Policy Characteristics'!D:D,MATCH($C27,'Policy Characteristics'!$C:$C,0))) -> Building Energy Efficiency Standards | K27: =IF(ISBLANK(INDEX('Policy Characteristics'!E:E,MATCH($C27,'Policy Characteristics'!$C:$C,0))),"",INDEX('Policy Characteristics'!E:E,MATCH($C27,'Policy Characteristics'!$C:$C,0))) -> bldgs efficiency standards | L27: =IF(ISBLANK(INDEX('Policy Characteristics'!F:F,MATCH($C27,'Policy Characteristics'!$C:$C,0))),"",INDEX('Policy Characteristics'!F:F,MATCH($C27,'Policy Characteristics'!$C:$C,0))) -> 0 | M27: =IF(ISBLANK(INDEX('Policy Characteristics'!G:G,MATCH($C27,'Policy Characteristics'!$C:$C,0))),"",INDEX('Policy Characteristics'!G:G,MATCH($C27,'Policy Characteristics'!$C:$C,0))) -> 0.75 | N27: =IF(ISBLANK(INDEX('Policy Characteristics'!H:H,MATCH($C27,'Policy Characteristics'!$C:$C,0))),"",INDEX('Policy Characteristics'!H:H,MATCH($C27,'Policy Characteristics'!$C:$C,0))) -> 0.01 | O27: =IF(ISBLANK(INDEX('Policy Characteristics'!I:I,MATCH($C27,'Policy Characteristics'!$C:$C,0))),"",INDEX('Policy Characteristics'!I:I,MATCH($C27,'Policy Characteristics'!$C:$C,0))) -> % reduction in energy use | P27: =IF(ISBLANK(INDEX('Policy Characteristics'!J:J,MATCH($C27,'Policy Characteristics'!$C:$C,0))),"",INDEX('Policy Characteristics'!J:J,MATCH($C27,'Policy Characteristics'!$C:$C,0))) -> **Description:** This policy tightens energy efficiency standards for the selected component(s) in the selected building type(s). The policy only applies to newly sold components each year (whether for new buildings or replacement of old components of existing buildings). // **Guidance for setting values:** In "Assessment of Electricity Savings in the U.S. Achievable through New Appliance/Equipment Efficiency Standards and Building Efficiency Codes, 2010-2025" (2011), the Edison Foundation considered a 30% reduction in whole-building energy use (moderate case) and 40-45% (aggressive case) relative to BAU from 2010 to 2025. | Q27: =IF(ISBLANK(INDEX('Policy Characteristics'!K:K,MATCH($C27,'Policy Characteristics'!$C:$C,0))),"",INDEX('Policy Characteristics'!K:K,MATCH($C27,'Policy Characteristics'!$C:$C,0))) -> buildings-sector-main.html#eff-stds | R27: =IF(ISBLANK(INDEX('Policy Characteristics'!L:L,MATCH($C27,'Policy Characteristics'!$C:$C,0))),"",INDEX('Policy Characteristics'!L:L,MATCH($C27,'Policy Characteristics'!$C:$C,0))) -> building-energy-efficiency-standards.html
A28: =IF(ISBLANK(INDEX('Policy Characteristics'!A:A,MATCH($C28,'Policy Characteristics'!$C:$C,0))),"",INDEX('Policy Characteristics'!A:A,MATCH($C28,'Policy Characteristics'!$C:$C,0))) -> Buildings and Appliances | B28: =IF(ISBLANK(INDEX('Policy Characteristics'!B:B,MATCH($C28,'Policy Characteristics'!$C:$C,0))),"",INDEX('Policy Characteristics'!B:B,MATCH($C28,'Policy Characteristics'!$C:$C,0))) -> Building Energy Efficiency Standards | C28: Reduction in E Use Allowed by Component Eff Std | D28: other component | E28: rural residential | F28: Other Components | G28: Rural Residential | H28: 155 | I28: Yes | J28: =IF(ISBLANK(INDEX('Policy Characteristics'!D:D,MATCH($C28,'Policy Characteristics'!$C:$C,0))),"",INDEX('Policy Characteristics'!D:D,MATCH($C28,'Policy Characteristics'!$C:$C,0))) -> Building Energy Efficiency Standards | K28: =IF(ISBLANK(INDEX('Policy Characteristics'!E:E,MATCH($C28,'Policy Characteristics'!$C:$C,0))),"",INDEX('Policy Characteristics'!E:E,MATCH($C28,'Policy Characteristics'!$C:$C,0))) -> bldgs efficiency standards | L28: =IF(ISBLANK(INDEX('Policy Characteristics'!F:F,MATCH($C28,'Policy Characteristics'!$C:$C,0))),"",INDEX('Policy Characteristics'!F:F,MATCH($C28,'Policy Characteristics'!$C:$C,0))) -> 0 | M28: =IF(ISBLANK(INDEX('Policy Characteristics'!G:G,MATCH($C28,'Policy Characteristics'!$C:$C,0))),"",INDEX('Policy Characteristics'!G:G,MATCH($C28,'Policy Characteristics'!$C:$C,0))) -> 0.75 | N28: =IF(ISBLANK(INDEX('Policy Characteristics'!H:H,MATCH($C28,'Policy Characteristics'!$C:$C,0))),"",INDEX('Policy Characteristics'!H:H,MATCH($C28,'Policy Characteristics'!$C:$C,0))) -> 0.01 | O28: =IF(ISBLANK(INDEX('Policy Characteristics'!I:I,MATCH($C28,'Policy Characteristics'!$C:$C,0))),"",INDEX('Policy Characteristics'!I:I,MATCH($C28,'Policy Characteristics'!$C:$C,0))) -> % reduction in energy use | P28: =IF(ISBLANK(INDEX('Policy Characteristics'!J:J,MATCH($C28,'Policy Characteristics'!$C:$C,0))),"",INDEX('Policy Characteristics'!J:J,MATCH($C28,'Policy Characteristics'!$C:$C,0))) -> **Description:** This policy tightens energy efficiency standards for the selected component(s) in the selected building type(s). The policy only applies to newly sold components each year (whether for new buildings or replacement of old components of existing buildings). // **Guidance for setting values:** In "Assessment of Electricity Savings in the U.S. Achievable through New Appliance/Equipment Efficiency Standards and Building Efficiency Codes, 2010-2025" (2011), the Edison Foundation considered a 30% reduction in whole-building energy use (moderate case) and 40-45% (aggressive case) relative to BAU from 2010 to 2025. | Q28: =IF(ISBLANK(INDEX('Policy Characteristics'!K:K,MATCH($C28,'Policy Characteristics'!$C:$C,0))),"",INDEX('Policy Characteristics'!K:K,MATCH($C28,'Policy Characteristics'!$C:$C,0))) -> buildings-sector-main.html#eff-stds | R28: =IF(ISBLANK(INDEX('Policy Characteristics'!L:L,MATCH($C28,'Policy Characteristics'!$C:$C,0))),"",INDEX('Policy Characteristics'!L:L,MATCH($C28,'Policy Characteristics'!$C:$C,0))) -> building-energy-efficiency-standards.html
A29: =IF(ISBLANK(INDEX('Policy Characteristics'!A:A,MATCH($C29,'Policy Characteristics'!$C:$C,0))),"",INDEX('Policy Characteristics'!A:A,MATCH($C29,'Policy Characteristics'!$C:$C,0))) -> Buildings and Appliances | B29: =IF(ISBLANK(INDEX('Policy Characteristics'!B:B,MATCH($C29,'Policy Characteristics'!$C:$C,0))),"",INDEX('Policy Characteristics'!B:B,MATCH($C29,'Policy Characteristics'!$C:$C,0))) -> Building Energy Efficiency Standards | C29: Reduction in E Use Allowed by Component Eff Std | D29: heating | E29: commercial | F29: Heating | G29: Commercial | H29: 156 | I29: Yes | J29: =IF(ISBLANK(INDEX('Policy Characteristics'!D:D,MATCH($C29,'Policy Characteristics'!$C:$C,0))),"",INDEX('Policy Characteristics'!D:D,MATCH($C29,'Policy Characteristics'!$C:$C,0))) -> Building Energy Efficiency Standards | K29: =IF(ISBLANK(INDEX('Policy Characteristics'!E:E,MATCH($C29,'Policy Characteristics'!$C:$C,0))),"",INDEX('Policy Characteristics'!E:E,MATCH($C29,'Policy Characteristics'!$C:$C,0))) -> bldgs efficiency standards | L29: =IF(ISBLANK(INDEX('Policy Characteristics'!F:F,MATCH($C29,'Policy Characteristics'!$C:$C,0))),"",INDEX('Policy Characteristics'!F:F,MATCH($C29,'Policy Characteristics'!$C:$C,0))) -> 0 | M29: =IF(ISBLANK(INDEX('Policy Characteristics'!G:G,MATCH($C29,'Policy Characteristics'!$C:$C,0))),"",INDEX('Policy Characteristics'!G:G,MATCH($C29,'Policy Characteristics'!$C:$C,0))) -> 0.75 | N29: =IF(ISBLANK(INDEX('Policy Characteristics'!H:H,MATCH($C29,'Policy Characteristics'!$C:$C,0))),"",INDEX('Policy Characteristics'!H:H,MATCH($C29,'Policy Characteristics'!$C:$C,0))) -> 0.01 | O29: =IF(ISBLANK(INDEX('Policy Characteristics'!I:I,MATCH($C29,'Policy Characteristics'!$C:$C,0))),"",INDEX('Policy Characteristics'!I:I,MATCH($C29,'Policy Characteristics'!$C:$C,0))) -> % reduction in energy use | P29: =IF(ISBLANK(INDEX('Policy Characteristics'!J:J,MATCH($C29,'Policy Characteristics'!$C:$C,0))),"",INDEX('Policy Characteristics'!J:J,MATCH($C29,'Policy Characteristics'!$C:$C,0))) -> **Description:** This policy tightens energy efficiency standards for the selected component(s) in the selected building type(s). The policy only applies to newly sold components each year (whether for new buildings or replacement of old components of existing buildings). // **Guidance for setting values:** In "Assessment of Electricity Savings in the U.S. Achievable through New Appliance/Equipment Efficiency Standards and Building Efficiency Codes, 2010-2025" (2011), the Edison Foundation considered a 30% reduction in whole-building energy use (moderate case) and 40-45% (aggressive case) relative to BAU from 2010 to 2025. | Q29: =IF(ISBLANK(INDEX('Policy Characteristics'!K:K,MATCH($C29,'Policy Characteristics'!$C:$C,0))),"",INDEX('Policy Characteristics'!K:K,MATCH($C29,'Policy Characteristics'!$C:$C,0))) -> buildings-sector-main.html#eff-stds | R29: =IF(ISBLANK(INDEX('Policy Characteristics'!L:L,MATCH($C29,'Policy Characteristics'!$C:$C,0))),"",INDEX('Policy Characteristics'!L:L,MATCH($C29,'Policy Characteristics'!$C:$C,0))) -> building-energy-efficiency-standards.html
... A34: =IF(ISBLANK(INDEX('Policy Characteristics'!A:A,MATCH($C34,'Policy Characteristics'!$C:$C,0))),"",INDEX('Policy Characteristics'!A:A,MATCH($C34,'Policy Characteristics'!$C:$C,0))) -> Buildings and Appliances | B34: =IF(ISBLANK(INDEX('Policy Characteristics'!B:B,MATCH($C34,'Policy Characteristics'!$C:$C,0))),"",INDEX('Policy Characteristics'!B:B,MATCH($C34,'Policy Characteristics'!$C:$C,0))) -> Building Energy Efficiency Standards | C34: Reduction in E Use Allowed by Component Eff Std | D34: other component | E34: commercial | F34: Other Components | G34: Commercial | H34: 161 | I34: Yes | J34: =IF(ISBLANK(INDEX('Policy Characteristics'!D:D,MATCH($C34,'Policy Characteristics'!$C:$C,0))),"",INDEX('Policy Characteristics'!D:D,MATCH($C34,'Policy Characteristics'!$C:$C,0))) -> Building Energy Efficiency Standards | K34: =IF(ISBLANK(INDEX('Policy Characteristics'!E:E,MATCH($C34,'Policy Characteristics'!$C:$C,0))),"",INDEX('Policy Characteristics'!E:E,MATCH($C34,'Policy Characteristics'!$C:$C,0))) -> bldgs efficiency standards | L34: =IF(ISBLANK(INDEX('Policy Characteristics'!F:F,MATCH($C34,'Policy Characteristics'!$C:$C,0))),"",INDEX('Policy Characteristics'!F:F,MATCH($C34,'Policy Characteristics'!$C:$C,0))) -> 0 | M34: =IF(ISBLANK(INDEX('Policy Characteristics'!G:G,MATCH($C34,'Policy Characteristics'!$C:$C,0))),"",INDEX('Policy Characteristics'!G:G,MATCH($C34,'Policy Characteristics'!$C:$C,0))) -> 0.75 | N34: =IF(ISBLANK(INDEX('Policy Characteristics'!H:H,MATCH($C34,'Policy Characteristics'!$C:$C,0))),"",INDEX('Policy Characteristics'!H:H,MATCH($C34,'Policy Characteristics'!$C:$C,0))) -> 0.01 | O34: =IF(ISBLANK(INDEX('Policy Characteristics'!I:I,MATCH($C34,'Policy Characteristics'!$C:$C,0))),"",INDEX('Policy Characteristics'!I:I,MATCH($C34,'Policy Characteristics'!$C:$C,0))) -> % reduction in energy use | P34: =IF(ISBLANK(INDEX('Policy Characteristics'!J:J,MATCH($C34,'Policy Characteristics'!$C:$C,0))),"",INDEX('Policy Characteristics'!J:J,MATCH($C34,'Policy Characteristics'!$C:$C,0))) -> **Description:** This policy tightens energy efficiency standards for the selected component(s) in the selected building type(s). The policy only applies to newly sold components each year (whether for new buildings or replacement of old components of existing buildings). // **Guidance for setting values:** In "Assessment of Electricity Savings in the U.S. Achievable through New Appliance/Equipment Efficiency Standards and Building Efficiency Codes, 2010-2025" (2011), the Edison Foundation considered a 30% reduction in whole-building energy use (moderate case) and 40-45% (aggressive case) relative to BAU from 2010 to 2025. | Q34: =IF(ISBLANK(INDEX('Policy Characteristics'!K:K,MATCH($C34,'Policy Characteristics'!$C:$C,0))),"",INDEX('Policy Characteristics'!K:K,MATCH($C34,'Policy Characteristics'!$C:$C,0))) -> buildings-sector-main.html#eff-stds | R34: =IF(ISBLANK(INDEX('Policy Characteristics'!L:L,MATCH($C34,'Policy Characteristics'!$C:$C,0))),"",INDEX('Policy Characteristics'!L:L,MATCH($C34,'Policy Characteristics'!$C:$C,0))) -> building-energy-efficiency-standards.html
A35: =IF(ISBLANK(INDEX('Policy Characteristics'!A:A,MATCH($C35,'Policy Characteristics'!$C:$C,0))),"",INDEX('Policy Characteristics'!A:A,MATCH($C35,'Policy Characteristics'!$C:$C,0))) -> Buildings and Appliances | B35: =IF(ISBLANK(INDEX('Policy Characteristics'!B:B,MATCH($C35,'Policy Characteristics'!$C:$C,0))),"",INDEX('Policy Characteristics'!B:B,MATCH($C35,'Policy Characteristics'!$C:$C,0))) -> Contractor Training | C35: Boolean Improved Contractor Edu and Training | H35: 19 | I35: Yes | J35: =IF(ISBLANK(INDEX('Policy Characteristics'!D:D,MATCH($C35,'Policy Characteristics'!$C:$C,0))),"",INDEX('Policy Characteristics'!D:D,MATCH($C35,'Policy Characteristics'!$C:$C,0))) -> Contractor Training | K35: =IF(ISBLANK(INDEX('Policy Characteristics'!E:E,MATCH($C35,'Policy Characteristics'!$C:$C,0))),"",INDEX('Policy Characteristics'!E:E,MATCH($C35,'Policy Characteristics'!$C:$C,0))) -> bldgs contractor training | L35: =IF(ISBLANK(INDEX('Policy Characteristics'!F:F,MATCH($C35,'Policy Characteristics'!$C:$C,0))),"",INDEX('Policy Characteristics'!F:F,MATCH($C35,'Policy Characteristics'!$C:$C,0))) -> 0 | M35: =IF(ISBLANK(INDEX('Policy Characteristics'!G:G,MATCH($C35,'Policy Characteristics'!$C:$C,0))),"",INDEX('Policy Characteristics'!G:G,MATCH($C35,'Policy Characteristics'!$C:$C,0))) -> 1 | N35: =IF(ISBLANK(INDEX('Policy Characteristics'!H:H,MATCH($C35,'Policy Characteristics'!$C:$C,0))),"",INDEX('Policy Characteristics'!H:H,MATCH($C35,'Policy Characteristics'!$C:$C,0))) -> 1 | O35: =IF(ISBLANK(INDEX('Policy Characteristics'!I:I,MATCH($C35,'Policy Characteristics'!$C:$C,0))),"",INDEX('Policy Characteristics'!I:I,MATCH($C35,'Policy Characteristics'!$C:$C,0))) -> on/off | P35: =IF(ISBLANK(INDEX('Policy Characteristics'!J:J,MATCH($C35,'Policy Characteristics'!$C:$C,0))),"",INDEX('Policy Characteristics'!J:J,MATCH($C35,'Policy Characteristics'!$C:$C,0))) -> **Description:** This policy represents a program to train contractors in energy-efficient products and installation practices. This covers activities such as air sealing, building framing, and choice and application of insulation. This policy affects newly sold building envelope components, which reduce the energy use of heating, cooling, and ventilation systems in buildings by 3.7% (based on a 2006 study from the Energy Center of Wisconsin). | Q35: =IF(ISBLANK(INDEX('Policy Characteristics'!K:K,MATCH($C35,'Policy Characteristics'!$C:$C,0))),"",INDEX('Policy Characteristics'!K:K,MATCH($C35,'Policy Characteristics'!$C:$C,0))) -> buildings-sector-main.html#contractor-ed | R35: =IF(ISBLANK(INDEX('Policy Characteristics'!L:L,MATCH($C35,'Policy Characteristics'!$C:$C,0))),"",INDEX('Policy Characteristics'!L:L,MATCH($C35,'Policy Characteristics'!$C:$C,0))) -> contractor-training.html | S35: Turn the lever "on" to train contractors in energy-efficient products and installation practice.
A36: =IF(ISBLANK(INDEX('Policy Characteristics'!A:A,MATCH($C36,'Policy Characteristics'!$C:$C,0))),"",INDEX('Policy Characteristics'!A:A,MATCH($C36,'Policy Characteristics'!$C:$C,0))) -> Buildings and Appliances | B36: =IF(ISBLANK(INDEX('Policy Characteristics'!B:B,MATCH($C36,'Policy Characteristics'!$C:$C,0))),"",INDEX('Policy Characteristics'!B:B,MATCH($C36,'Policy Characteristics'!$C:$C,0))) -> Distributed Solar Capacity Requirement | C36: Min Required Rooftop Solar Capacity | D36: urban residential | F36: Urban Residential | H36: 2433 | I36: Yes | J36: =IF(ISBLANK(INDEX('Policy Characteristics'!D:D,MATCH($C36,'Policy Characteristics'!$C:$C,0))),"",INDEX('Policy Characteristics'!D:D,MATCH($C36,'Policy Characteristics'!$C:$C,0))) -> Distributed Solar Promotion | K36: =IF(ISBLANK(INDEX('Policy Characteristics'!E:E,MATCH($C36,'Policy Characteristics'!$C:$C,0))),"",INDEX('Policy Characteristics'!E:E,MATCH($C36,'Policy Characteristics'!$C:$C,0))) -> bldgs min req rooftop solar | L36: =IF(ISBLANK(INDEX('Policy Characteristics'!F:F,MATCH($C36,'Policy Characteristics'!$C:$C,0))),"",INDEX('Policy Characteristics'!F:F,MATCH($C36,'Policy Characteristics'!$C:$C,0))) -> 0 | M36: =IF(ISBLANK(INDEX('Policy Characteristics'!G:G,MATCH($C36,'Policy Characteristics'!$C:$C,0))),"",INDEX('Policy Characteristics'!G:G,MATCH($C36,'Policy Characteristics'!$C:$C,0))) -> 600000 | N36: =IF(ISBLANK(INDEX('Policy Characteristics'!H:H,MATCH($C36,'Policy Characteristics'!$C:$C,0))),"",INDEX('Policy Characteristics'!H:H,MATCH($C36,'Policy Characteristics'!$C:$C,0))) -> 5000 | O36: =IF(ISBLANK(INDEX('Policy Characteristics'!I:I,MATCH($C36,'Policy Characteristics'!$C:$C,0))),"",INDEX('Policy Characteristics'!I:I,MATCH($C36,'Policy Characteristics'!$C:$C,0))) -> MW | P36: =IF(ISBLANK(INDEX('Policy Characteristics'!J:J,MATCH($C36,'Policy Characteristics'!$C:$C,0))),"",INDEX('Policy Characteristics'!J:J,MATCH($C36,'Policy Characteristics'!$C:$C,0))) -> **Description:** This policy requires at least the specified capacity of distributed solar be built by the model. | Q36: =IF(ISBLANK(INDEX('Policy Characteristics'!K:K,MATCH($C36,'Policy Characteristics'!$C:$C,0))),"",INDEX('Policy Characteristics'!K:K,MATCH($C36,'Policy Characteristics'!$C:$C,0))) | R36: =IF(ISBLANK(INDEX('Policy Characteristics'!L:L,MATCH($C36,'Policy Characteristics'!$C:$C,0))),"",INDEX('Policy Characteristics'!L:L,MATCH($C36,'Policy Characteristics'!$C:$C,0))) | S36: Require that distributed solar can produce a certain number of megawatts.
A37: =IF(ISBLANK(INDEX('Policy Characteristics'!A:A,MATCH($C37,'Policy Characteristics'!$C:$C,0))),"",INDEX('Policy Characteristics'!A:A,MATCH($C37,'Policy Characteristics'!$C:$C,0))) -> Buildings and Appliances | B37: =IF(ISBLANK(INDEX('Policy Characteristics'!B:B,MATCH($C37,'Policy Characteristics'!$C:$C,0))),"",INDEX('Policy Characteristics'!B:B,MATCH($C37,'Policy Characteristics'!$C:$C,0))) -> Distributed Solar Capacity Requirement | C37: Min Required Rooftop Solar Capacity | D37: rural residential | F37: Rural Residential | H37: 2434 | I37: Yes | J37: =IF(ISBLANK(INDEX('Policy Characteristics'!D:D,MATCH($C37,'Policy Characteristics'!$C:$C,0))),"",INDEX('Policy Characteristics'!D:D,MATCH($C37,'Policy Characteristics'!$C:$C,0))) -> Distributed Solar Promotion | K37: =IF(ISBLANK(INDEX('Policy Characteristics'!E:E,MATCH($C37,'Policy Characteristics'!$C:$C,0))),"",INDEX('Policy Characteristics'!E:E,MATCH($C37,'Policy Characteristics'!$C:$C,0))) -> bldgs min req rooftop solar | L37: =IF(ISBLANK(INDEX('Policy Characteristics'!F:F,MATCH($C37,'Policy Characteristics'!$C:$C,0))),"",INDEX('Policy Characteristics'!F:F,MATCH($C37,'Policy Characteristics'!$C:$C,0))) -> 0 | M37: =IF(ISBLANK(INDEX('Policy Characteristics'!G:G,MATCH($C37,'Policy Characteristics'!$C:$C,0))),"",INDEX('Policy Characteristics'!G:G,MATCH($C37,'Policy Characteristics'!$C:$C,0))) -> 600000 | N37: =IF(ISBLANK(INDEX('Policy Characteristics'!H:H,MATCH($C37,'Policy Characteristics'!$C:$C,0))),"",INDEX('Policy Characteristics'!H:H,MATCH($C37,'Policy Characteristics'!$C:$C,0))) -> 5000 | O37: =IF(ISBLANK(INDEX('Policy Characteristics'!I:I,MATCH($C37,'Policy Characteristics'!$C:$C,0))),"",INDEX('Policy Characteristics'!I:I,MATCH($C37,'Policy Characteristics'!$C:$C,0))) -> MW | P37: =IF(ISBLANK(INDEX('Policy Characteristics'!J:J,MATCH($C37,'Policy Characteristics'!$C:$C,0))),"",INDEX('Policy Characteristics'!J:J,MATCH($C37,'Policy Characteristics'!$C:$C,0))) -> **Description:** This policy requires at least the specified capacity of distributed solar be built by the model. | Q37: =IF(ISBLANK(INDEX('Policy Characteristics'!K:K,MATCH($C37,'Policy Characteristics'!$C:$C,0))),"",INDEX('Policy Characteristics'!K:K,MATCH($C37,'Policy Characteristics'!$C:$C,0))) | R37: =IF(ISBLANK(INDEX('Policy Characteristics'!L:L,MATCH($C37,'Policy Characteristics'!$C:$C,0))),"",INDEX('Policy Characteristics'!L:L,MATCH($C37,'Policy Characteristics'!$C:$C,0)))
A38: =IF(ISBLANK(INDEX('Policy Characteristics'!A:A,MATCH($C38,'Policy Characteristics'!$C:$C,0))),"",INDEX('Policy Characteristics'!A:A,MATCH($C38,'Policy Characteristics'!$C:$C,0))) -> Buildings and Appliances | B38: =IF(ISBLANK(INDEX('Policy Characteristics'!B:B,MATCH($C38,'Policy Characteristics'!$C:$C,0))),"",INDEX('Policy Characteristics'!B:B,MATCH($C38,'Policy Characteristics'!$C:$C,0))) -> Distributed Solar Capacity Requirement | C38: Min Required Rooftop Solar Capacity | D38: commercial | F38: Commercial | H38: 2435 | I38: Yes | J38: =IF(ISBLANK(INDEX('Policy Characteristics'!D:D,MATCH($C38,'Policy Characteristics'!$C:$C,0))),"",INDEX('Policy Characteristics'!D:D,MATCH($C38,'Policy Characteristics'!$C:$C,0))) -> Distributed Solar Promotion | K38: =IF(ISBLANK(INDEX('Policy Characteristics'!E:E,MATCH($C38,'Policy Characteristics'!$C:$C,0))),"",INDEX('Policy Characteristics'!E:E,MATCH($C38,'Policy Characteristics'!$C:$C,0))) -> bldgs min req rooftop solar | L38: =IF(ISBLANK(INDEX('Policy Characteristics'!F:F,MATCH($C38,'Policy Characteristics'!$C:$C,0))),"",INDEX('Policy Characteristics'!F:F,MATCH($C38,'Policy Characteristics'!$C:$C,0))) -> 0 | M38: =IF(ISBLANK(INDEX('Policy Characteristics'!G:G,MATCH($C38,'Policy Characteristics'!$C:$C,0))),"",INDEX('Policy Characteristics'!G:G,MATCH($C38,'Policy Characteristics'!$C:$C,0))) -> 600000 | N38: =IF(ISBLANK(INDEX('Policy Characteristics'!H:H,MATCH($C38,'Policy Characteristics'!$C:$C,0))),"",INDEX('Policy Characteristics'!H:H,MATCH($C38,'Policy Characteristics'!$C:$C,0))) -> 5000 | O38: =IF(ISBLANK(INDEX('Policy Characteristics'!I:I,MATCH($C38,'Policy Characteristics'!$C:$C,0))),"",INDEX('Policy Characteristics'!I:I,MATCH($C38,'Policy Characteristics'!$C:$C,0))) -> MW | P38: =IF(ISBLANK(INDEX('Policy Characteristics'!J:J,MATCH($C38,'Policy Characteristics'!$C:$C,0))),"",INDEX('Policy Characteristics'!J:J,MATCH($C38,'Policy Characteristics'!$C:$C,0))) -> **Description:** This policy requires at least the specified capacity of distributed solar be built by the model. | Q38: =IF(ISBLANK(INDEX('Policy Characteristics'!K:K,MATCH($C38,'Policy Characteristics'!$C:$C,0))),"",INDEX('Policy Characteristics'!K:K,MATCH($C38,'Policy Characteristics'!$C:$C,0))) | R38: =IF(ISBLANK(INDEX('Policy Characteristics'!L:L,MATCH($C38,'Policy Characteristics'!$C:$C,0))),"",INDEX('Policy Characteristics'!L:L,MATCH($C38,'Policy Characteristics'!$C:$C,0)))
